Workbook
Name FromArray_1: _xlfn.ANCHORARRAY([2]БДДС!$IOT$1)
Name FromArray_1: _xlfn.ANCHORARRAY([2]БДДС!$IOT$1)
Name FromArray_1: _xlfn.ANCHORARRAY(#REF!)
Name FromArray_1: _xlfn.ANCHORARRAY(#REF!)
Name FromArray_1: _xlfn.ANCHORARRAY([2]БДДС!$IOT$1)
Name path: #REF!
Name path: #REF!
Name Дата_платежа: DATE(YEAR(Начало_кредита),MONTH(Начало_кредита)+'Анализ чувствительности '!Номер_платежа,DAY(Начало_кредита))
Name Дата_платежа: DATE(YEAR(Начало_кредита),MONTH(Начало_кредита)+'Диаграмма эластичности'!Номер_платежа,DAY(Начало_кредита))
Name Дата_платежа: DATE(YEAR(Начало_кредита),MONTH(Начало_кредита)+[0]!Номер_платежа,DAY(Начало_кредита))
Name Дата_платежа: DATE(YEAR(Начало_кредита),MONTH(Начало_кредита)+Номер_платежа,DAY(Начало_кредита))
Name Ежемесячный_платеж: -PMT(Процентная_ставка/12,Количество_платежей,Сумма_кредита)
Name Ежемесячный_платеж: -PMT(Процентная_ставка/12,Количество_платежей,Сумма_кредита)
Name Ежемесячный_платеж: -PMT(Процентная_ставка/12,Количество_платежей,Сумма_кредита)
Name Ежемесячный_платеж: -PMT(Процентная_ставка/12,Количество_платежей,Сумма_кредита)
Name Земнал: [3]Предпосылки!$E$72
Name Земнал: [4]Предпосылки!$E$72
Name Земнал: [5]Предпосылки!$E$72
Name КЗ_инж: [3]Предпосылки!$E$109
Name КЗ_инж: [4]Предпосылки!$E$109
Name КЗ_инж: [5]Предпосылки!$E$109
Name КЗ_ИТ: [3]Предпосылки!$E$108
Name КЗ_ИТ: [4]Предпосылки!$E$108
Name КЗ_ИТ: [5]Предпосылки!$E$108
Name КЗ_ком: [3]Предпосылки!$E$105
Name КЗ_ком: [4]Предпосылки!$E$105
Name КЗ_ком: [5]Предпосылки!$E$105
Name КЗ_охрана: [3]Предпосылки!$E$107
Name КЗ_охрана: [4]Предпосылки!$E$107
Name КЗ_охрана: [5]Предпосылки!$E$107
Name КЗ_проч_содерж: [3]Предпосылки!$E$110
Name КЗ_проч_содерж: [4]Предпосылки!$E$110
Name КЗ_проч_содерж: [5]Предпосылки!$E$110
Name КЗ_прочие: [3]Предпосылки!$E$111
Name КЗ_прочие: [4]Предпосылки!$E$111
Name КЗ_прочие: [5]Предпосылки!$E$111
Name КЗ_СВ: [3]Предпосылки!$E$103
Name КЗ_СВ: [4]Предпосылки!$E$103
Name КЗ_СВ: [5]Предпосылки!$E$103
Name КЗ_уборка: [3]Предпосылки!$E$106
Name КЗ_уборка: [4]Предпосылки!$E$106
Name КЗ_уборка: [5]Предпосылки!$E$106
Name КЗ_ФОТ: [3]Предпосылки!$E$102
Name КЗ_ФОТ: [4]Предпосылки!$E$102
Name КЗ_ФОТ: [5]Предпосылки!$E$102
Name Конечный_баланс: -FV(Процентная_ставка/12,'Анализ чувствительности '!Номер_платежа,-'Анализ чувствительности '!Ежемесячный_платеж,Сумма_кредита)
Name Конечный_баланс: -FV(Процентная_ставка/12,'Диаграмма эластичности'!Номер_платежа,-'Диаграмма эластичности'!Ежемесячный_платеж,Сумма_кредита)
Name Конечный_баланс: -FV(Процентная_ставка/12,[0]!Номер_платежа,-'ФинРез Кампус'!Ежемесячный_платеж,Сумма_кредита)
Name Конечный_баланс: -FV(Процентная_ставка/12,Номер_платежа,-Ежемесячный_платеж,Сумма_кредита)
Name Наценка_комаренда: [3]Предпосылки!$E$86
Name Наценка_комаренда: [4]Предпосылки!$E$86
Name Наценка_комаренда: [5]Предпосылки!$E$86
Name Наценка_рез: [3]Предпосылки!#REF!
Name Наценка_рез: [4]Предпосылки!#REF!
Name Начальный_баланс: -FV(Процентная_ставка/12,'Анализ чувствительности '!Номер_платежа-1,-'Анализ чувствительности '!Ежемесячный_платеж,Сумма_кредита)
Name Начальный_баланс: -FV(Процентная_ставка/12,'Диаграмма эластичности'!Номер_платежа-1,-'Диаграмма эластичности'!Ежемесячный_платеж,Сумма_кредита)
Name Начальный_баланс: -FV(Процентная_ставка/12,[0]!Номер_платежа-1,-'ФинРез Кампус'!Ежемесячный_платеж,Сумма_кредита)
Name Начальный_баланс: -FV(Процентная_ставка/12,Номер_платежа-1,-Ежемесячный_платеж,Сумма_кредита)
Name НДФЛ: [3]Предпосылки!$E$70
Name НДФЛ: [4]Предпосылки!$E$70

Sheet Паспорт
D3: Общие характеристики
C5: № п/п | D5: Наименование | E5: Значение
C6: 1 | D6: Параметры кампуса
C7: =C6+1 -> 2 | D7: Общие сведения
C8: =C7+1 -> 3 | D8: =[9]Предпосылки!$D$12 -> Научно-технологический образовательный кампус "Долина Ростеха" в г. Фрязино Московской обл.
C9: =C8+1 -> 4 | D9: Срок сдачи в эксплуатацию | E9: =[9]Предпосылки!E13 -> 49491 | G9: Источник данных - модель инфраструктуры
C10: =C9+1 -> 5 | D10: Общая площадь территорий | E10: =[9]Предпосылки!E14 -> 311600
C11: =C10+1 -> 6 | D11: Общая площадь зданий и сооружений | E11: =[9]Предпосылки!E15 -> 92000
C12: =C11+1 -> 7 | D12: учебные площади | E12: =[9]Предпосылки!E16 -> 19800
C13: =C12+1 -> 8 | D13: лабораторные площади | E13: =[9]Предпосылки!E17 -> 6800
C14: =C13+1 -> 9 | D14: офисные площади | E14: =[9]Предпосылки!E18 -> 2250
C15: =C14+1 -> 10 | D15: переговорные, коворкинги, конференц-залы | E15: =[9]Предпосылки!E19 -> 17160
C16: =C15+1 -> 11 | D16: производственные площади | E16: =[9]Предпосылки!E20 -> 8000
C17: =C16+1 -> 12 | D17: площади для размещения объектов здравоохранения | E17: =[9]Предпосылки!E21 -> 0
C18: =C17+1 -> 13 | D18: площади для размещения пунктов питания | E18: =[9]Предпосылки!E22 -> 960
C19: =C18+1 -> 14 | D19: площади спортивных объектов | E19: =[9]Предпосылки!E23 -> 1770.25
C20: =C19+1 -> 15 | D20: площади для размещения объектов проживания | E20: =[9]Предпосылки!E24 -> 18278.14
C21: =C20+1 -> 16 | D21: коммерческие площади свободного назначения | E21: =[9]Предпосылки!E25 -> 0
... C24: =C23+1 -> 19 | D24: прочие площади | E24: =[9]Предпосылки!E28 -> 12454.59
C25: 20 | D25: Распределение иной полезной площади
C26: 21 | D26: Использование и содержание головным ВУЗом | E26: =[9]Предпосылки!E30 -> 79545.41
C27: 22 | D27: Сдача в аренду | E27: =[9]Предпосылки!E31 -> 54545.41
C28: 23 | D28: Использование для ведения иной коммерческой деятельности | E28: =[9]Предпосылки!E32 -> 25000
C29: 26 | D29: Виды иной коммерческой деятельности
C30: 27 | D30: Оказание услуг питания | E30: =[9]Предпосылки!E34 -> Не реализуется
C31: 28 | D31: Торговля | E31: =[9]Предпосылки!E35 -> Не реализуется
C32: 29 | D32: Управление объектами размещенния (гостиницы, общежития) | E32: =[9]Предпосылки!E36 -> Реализуется
C33: 30 | D33: Деятельность по проведению мероприятий | E33: =[9]Предпосылки!E37 -> Не реализуется
C34: 31 | D34: Управление объектами спортивной инфраструктуры | E34: =[9]Предпосылки!E38 -> Не реализуется

Sheet ФинРез и инд-ры ВУЗ
AV2: 1 | AW2: 1 | AX2: 1 | AY2: 1 | AZ2: 1 | BA2: 1 | BB2: 1 | BC2: 1 | BD2: 1 | BE2: 1 | BF2: 1 | BG2: 1 | BH2: 1 | BI2: 1 | BJ2: 1 | BK2: 1 | BL2: 1 | BM2: 1 | BN2: 1 | BO2: 1 | BP2: 1 | DH2: 1 | DI2: 1 | DJ2: 1 | DK2: 1 | DL2: 1 | DM2: 1 | DN2: 1 | DO2: 1 | DP2: 1 | DQ2: 1 | DR2: 1 | DS2: 1 | DT2: 1 | DU2: 1 | DV2: 1 | DW2: 1 | DX2: 1 | DY2: 1 | DZ2: 1 | EA2: 1 | EB2: 1
D3: Индикаторы деятельности вузов | F3: МИРЭА — Российский технологический университет (РТУ МИРЭА)
F4: Сценарий 1 | AV4: Сценарий 1 | BR4: Сценарий 2 | DH4: Сценарий 1 | ED4: Дельта (сценарий 2 - сценарий 1)
C5: № п/п | D5: Наименование показателей | E5: ед. | F5: 2022 | G5: 2023 | H5: 2024 | I5: 2025 | J5: 2026 | K5: 2027 | L5: 2028 | M5: 2029 | N5: 2030 | O5: 2031 | P5: 2032 | Q5: 2033 | R5: 2034 | S5: 2035 | T5: 2036 | U5: 2037 | V5: 2038 | W5: 2039 | X5: 2040 | Y5: 2041 | Z5: 2042 | BQ5: Итого за период 2026-2042 гг | BR5: 2022 | BS5: 2023 | BT5: 2024 | BU5: 2025 | BV5: 2026 | BW5: 2027 | BX5: 2028 | BY5: 2029 | BZ5: 2030 | CA5: 2031 | CB5: 2032 | CC5: 2033 | CD5: 2034 | CE5: 2035 | CF5: 2036 | CG5: 2037 | CH5: 2038 | CI5: 2039 | CJ5: 2040 | CK5: 2041 | CL5: 2042 | EC5: Итого за период 2026-2042 гг | ED5: 2022 | EE5: 2023 | EF5: 2024 | EG5: 2025 | EH5: 2026 | EI5: 2027 | EJ5: 2028 | EK5: 2029 | EL5: 2030 | EM5: 2031 | EN5: 2032 | EO5: 2033 | EP5: 2034 | EQ5: 2035 | ER5: 2036 | ES5: 2037 | ET5: 2038 | EU5: 2039 | EV5: 2040 | EW5: 2041 | EX5: 2042 | EY5: Итого за период 2026-2042 гг
F6: факт | G6: факт | H6: факт | I6: план | J6: план | K6: план | L6: план | M6: план | N6: план | O6: план | P6: план | Q6: план | R6: план | S6: план | T6: план | U6: план | V6: план | W6: план | X6: план | Y6: план | Z6: план | BR6: факт | BS6: факт | BT6: факт | BU6: план | BV6: план | BW6: план | BX6: план | BY6: план | BZ6: план | CA6: план | CB6: план | CC6: план | CD6: план | CE6: план | CF6: план | CG6: план | CH6: план | CI6: план | CJ6: план | CK6: план | CL6: план | ED6: факт | EE6: факт | EF6: факт | EG6: план | EH6: план | EI6: план | EJ6: план | EK6: план | EL6: план | EM6: план | EN6: план | EO6: план | EP6: план | EQ6: план | ER6: план | ES6: план | ET6: план | EU6: план | EV6: план | EW6: план | EX6: план
D8: Финансовые показатели
C9: 1 | D9: ФИНАНСОВЫЙ РЕЗУЛЬТАТ КАМПУСА (интегрированный) | F9: =F10-F11-F12 -> 5539689.5 | G9: =G10-G11-G12 -> 6357827.8 | H9: =H10-H11-H12 -> 7564444.6 | I9: =I10-I11-I12 -> 8103936.4 | J9: =J10-J11-J12 -> 8519190.9 | K9: =K10-K11-K12 -> 8995587.1 | L9: =L10-L11-L12 -> 9480539.2 | M9: =M10-M11-M12 -> 9958076.7 | ... Z9: =Z10-Z11-Z12 -> 19749143 | BQ9: =BQ10-BQ11-BQ12 -> 2.2717526e+08 | BR9: =BR10-BR11-BR12 -> 5539689.5 | BS9: =BS10-BS11-BS12 -> 6357827.8 | BT9: =BT10-BT11-BT12 -> 7564444.6 | BU9: =BU10-BU11-BU12 -> 7953786 | BV9: =BV10-BV11-BV12 -> 8779454.4 | BW9: =BW10-BW11-BW12 -> 11860961 | BX9: =BX10-BX11-BX12 -> 11560327 | ... CL9: =CL10-CL11-CL12 -> 25388408 | EC9: =EC10-EC11-EC12 -> 3.1476351e+08 | ED9: =ED10-ED11-ED12 -> 0 | EE9: =EE10-EE11-EE12 -> 0 | EF9: =EF10-EF11-EF12 -> 0 | EG9: =EG10-EG11-EG12 -> 367624.03 | EH9: =EH10-EH11-EH12 -> 822670.37 | EI9: =EI10-EI11-EI12 -> 1183604.5 | EJ9: =EJ10-EJ11-EJ12 -> 1514961.6 | ... EY9: =EY10-EY11-EY12 -> 40055291
C10: 2 | D10: Доходы | F10: =F38 -> 10491307 | G10: =G38 -> 12413481 | H10: =H38 -> 15281575 | I10: =I38 -> 16541920 | J10: =J38 -> 17535322 | K10: =K38 -> 18604050 | L10: =L38 -> 19471726 | M10: =M38 -> 20345931 | ... Z10: =Z38 -> 37046659 | AA10: 844890.95 | AB10: 1540312.3 | AC10: 2978551.2 | AD10: 4875098.2 | AE10: 6884480 | AF10: 9062036.2 | AG10: 11419275 | AH10: 13933192 | AI10: 16634713 | AJ10: 19532618 | AK10: 22643126 | AL10: 25980160 | AM10: 29556966 | AN10: 33394567 | AO10: 37505010 | AP10: 41909414 | AQ10: 46625582 | AR10: 51675275 | AS10: 57082954 | AT10: 62870272 | AU10: 69061737 | AV10: =AA10=F10 -> FALSE | AW10: =AB10=G10 -> FALSE | AX10: =AC10=H10 -> FALSE | AY10: =AD10=I10 -> FALSE | AZ10: =AE10=J10 -> FALSE | BA10: =AF10=K10 -> FALSE | BB10: =AG10=L10 -> FALSE | BC10: =AH10=M10 -> FALSE | ... BP10: =AU10=Z10 -> FALSE | BQ10: =SUM(J10:Z10) -> 4.4581021e+08 | BR10: =BR38 -> 10491307 | BS10: =BS38 -> 12413481 | BT10: =BT38 -> 15281575 | BU10: =BU38 -> 16798888 | BV10: =BV38 -> 18753447 | BW10: =BW38 -> 22555695 | BX10: =BX38 -> 22784137 | BY10: =BY38 -> 23185804 | ... CL10: =CL38 -> 45147510 | CM10: 844890.95 | CN10: 1540312.3 | CO10: 2978551.2 | CP10: 4732514.5 | CQ10: 7235055.3 | CR10: 11362033 | CS10: 15446989 | CT10: 19479870 | CU10: 30243615 | CV10: 41475722 | CW10: 51739482 | CX10: 62750361 | CY10: 70149867 | CZ10: 78137154 | DA10: 86569339 | DB10: 95347432 | DC10: 1.0445796e+08 | DD10: 1.1325971e+08 | DE10: 1.2310187e+08 | DF10: 1.333393e+08 | DG10: 1.4400058e+08 | DH10: =CM10=BR10 -> FALSE | DI10: =CN10=BS10 -> FALSE | DJ10: =CO10=BT10 -> FALSE | DK10: =CP10=BU10 -> FALSE | DL10: =CQ10=BV10 -> FALSE | DM10: =CR10=BW10 -> FALSE | DN10: =CS10=BX10 -> FALSE | DO10: =CT10=BY10 -> FALSE | ... EB10: =DG10=CL10 -> FALSE | EC10: =SUM(BV10:CL10) -> 5.6283073e+08 | ED10: =ED14+ED19+'ФинРез Кампус'!F210 -> 0 | EE10: =EE14+EE19+'ФинРез Кампус'!G210 -> 0 | EF10: =EF14+EF19+'ФинРез Кампус'!H210 -> 0 | EG10: =EG14+EG19+'ФинРез Кампус'!I210 -> 774741.98 | EH10: =EH14+EH19+'ФинРез Кампус'!J210 -> 1780531.5 | EI10: =EI14+EI19+'ФинРез Кампус'!K210 -> 2269875.5 | EJ10: =EJ14+EJ19+'ФинРез Кампус'!L210 -> 2747586 | EK10: =EK14+EK19+'ФинРез Кампус'!M210 -> 2996662.4 | ... EX10: =EX14+EX19+'ФинРез Кампус'!Z210 -> 6503951.5 | EY10: =SUM(EH10:EX10) -> 72273351
C11: 3 | D11: Переменные расходы (ФОТ основного персонала, матзапасы, НМА, соисполнители) | F11: =F43 -> 4951617.5 | G11: =G43 -> 6055653 | H11: =H43 -> 7717130.8 | I11: =I43 -> 8437984 | J11: =J43 -> 9016131.3 | K11: =K43 -> 9608462.5 | L11: =L43 -> 9991186.5 | M11: =M43 -> 10387854 | ... Z11: =Z43 -> 17297516 | AA11: 844890.95 | AB11: 695421.31 | AC11: 1438239 | AD11: 1896547 | AE11: 2009381.8 | AF11: 2177556.2 | AG11: 2357238.6 | AH11: 2513917 | AI11: 2701521.6 | AJ11: 2897905.1 | AK11: 3110508 | AL11: 3337033 | AM11: 3576806.2 | AN11: 3837601.1 | AO11: 4110443.2 | AP11: 4404403.8 | AQ11: 4716168.1 | AR11: 5049693 | AS11: 5407679 | AT11: 5787317.9 | AU11: 6191465.4 | AV11: =AA11=F11 -> FALSE | AW11: =AB11=G11 -> FALSE | AX11: =AC11=H11 -> FALSE | AY11: =AD11=I11 -> FALSE | AZ11: =AE11=J11 -> FALSE | BA11: =AF11=K11 -> FALSE | BB11: =AG11=L11 -> FALSE | BC11: =AH11=M11 -> FALSE | ... BP11: =AU11=Z11 -> FALSE | BQ11: =SUM(J11:Z11) -> 2.1863495e+08 | BR11: =BR43 -> 4951617.5 | BS11: =BS43 -> 6055653 | BT11: =BT43 -> 7717130.8 | BU11: =BU43 -> 8845102 | BV11: =BV43 -> 9973992.5 | BW11: =BW43 -> 10694734 | BX11: =BX43 -> 11223811 | BY11: =BY43 -> 11701892 | ... CL11: =CL43 -> 19759102 | CM11: 844890.95 | CN11: 695421.31 | CO11: 1438239 | CP11: 1753963.3 | CQ11: 2502540.8 | CR11: 4126978.2 | CS11: 4084956 | CT11: 4032880.6 | CU11: 10763745 | CV11: 11232107 | CW11: 10263760 | CX11: 11010879 | CY11: 7399506 | CZ11: 7987286.4 | DA11: 8432185.4 | DB11: 8778092.9 | DC11: 9110524 | DD11: 8801754.1 | DE11: 9842155.6 | DF11: 10237432 | DG11: 10661278 | DH11: =CM11=BR11 -> FALSE | DI11: =CN11=BS11 -> FALSE | DJ11: =CO11=BT11 -> FALSE | DK11: =CP11=BU11 -> FALSE | DL11: =CQ11=BV11 -> FALSE | DM11: =CR11=BW11 -> FALSE | DN11: =CS11=BX11 -> FALSE | DO11: =CT11=BY11 -> FALSE | ... EB11: =DG11=CL11 -> FALSE | EC11: =SUM(BV11:CL11) -> 2.4754995e+08 | ED11: =ED15+ED20+'ФинРез Кампус'!F212 -> 0 | EE11: =EE15+EE20+'ФинРез Кампус'!G212 -> 0 | EF11: =EF15+EF20+'ФинРез Кампус'!H212 -> 0 | EG11: =EG15+EG20+'ФинРез Кампус'!I212 -> 407117.95 | EH11: =EH15+EH20+'ФинРез Кампус'!J212 -> 957861.17 | EI11: =EI15+EI20+'ФинРез Кампус'!K212 -> 1086271.1 | EJ11: =EJ15+EJ20+'ФинРез Кампус'!L212 -> 1232624.4 | EK11: =EK15+EK20+'ФинРез Кампус'!M212 -> 1314038.1 | ... EX11: =EX15+EX20+'ФинРез Кампус'!Z212 -> 2547854.2 | EY11: =SUM(EH11:EX11) -> 29486620
C12: 5 | D12: Постоянные расходы (кампус) | AA12: -108964.17 | AB12: -363566.02 | AC12: -143885.64 | AD12: 243226.76 | AE12: 289928.75 | AF12: 389325.07 | AG12: 497478.17 | AH12: 579766.15 | AI12: 690004.77 | AJ12: 805927.57 | AK12: 934851.42 | AL12: 1074350.2 | AM12: 1223616 | AN12: 1390283.3 | AO12: 1565232.7 | AP12: 1757384.9 | AQ12: 1963268.4 | AR12: 2186677.3 | AS12: 2430142.7 | AT12: 2690680.1 | AU12: 2970962.1 | AV12: =AA12=F12 -> FALSE | AW12: =AB12=G12 -> FALSE | AX12: =AC12=H12 -> FALSE | AY12: =AD12=I12 -> FALSE | AZ12: =AE12=J12 -> FALSE | BA12: =AF12=K12 -> FALSE | BB12: =AG12=L12 -> FALSE | BC12: =AH12=M12 -> FALSE | ... BP12: =AU12=Z12 -> FALSE | BR12: =ED12 -> 0 | BS12: =EE12 -> 0 | BT12: =EF12 -> 0 | BU12: =EG12 -> 0 | BV12: =EH12 -> 0 | BW12: =EI12 -> 0 | BX12: =EJ12 -> 0 | BY12: =EK12 -> 0 | ... CF12: =ER12 -> 355344.12 | CG12: =EZ12 -> 0 | CH12: =FA12 -> 0 | CI12: =FB12 -> 0 | CJ12: =FC12 -> 0 | CK12: =FD12 -> 0 | CL12: =FE12 -> 0 | CM12: -108964.17 | CN12: -363566.02 | CO12: -143885.64 | CP12: 100643.09 | CQ12: 783087.73 | CR12: 2338747 | CS12: 2225195.6 | CT12: 2223107.7 | CU12: 2100269.7 | CV12: 2222092.4 | CW12: 3291597.6 | CX12: 3759830.2 | CY12: 3946315.8 | CZ12: 5539968.6 | DA12: 5886974.9 | DB12: 6131073.9 | DC12: 6357624.3 | DD12: 5938738.4 | DE12: 6864619.2 | DF12: 7140794 | DG12: 7440775 | DH12: =CM12=BR12 -> FALSE | DI12: =CN12=BS12 -> FALSE | DJ12: =CO12=BT12 -> FALSE | DK12: =CP12=BU12 -> FALSE | DL12: =CQ12=BV12 -> FALSE | DM12: =CR12=BW12 -> FALSE | DN12: =CS12=BX12 -> FALSE | DO12: =CT12=BY12 -> FALSE | ... EB12: =DG12=CL12 -> FALSE | EC12: =SUM(BV12:CL12) -> 517265.22 | ED12: ='ФинРез Кампус'!F7 -> 0 | EE12: ='ФинРез Кампус'!G7 -> 0 | EF12: ='ФинРез Кампус'!H7 -> 0 | EG12: ='ФинРез Кампус'!I7 -> 0 | EH12: ='ФинРез Кампус'!J7 -> 0 | EI12: ='ФинРез Кампус'!K7 -> 0 | EJ12: ='ФинРез Кампус'!L7 -> 0 | EK12: ='ФинРез Кампус'!M7 -> 0 | ... EX12: ='ФинРез Кампус'!Z7 -> 410954.51 | EY12: =SUM(EH12:EX12) -> 2731439.7
D13: Образование | AV13: =AA13=F13 -> TRUE | AW13: =AB13=G13 -> TRUE | AX13: =AC13=H13 -> TRUE | AY13: =AD13=I13 -> TRUE | AZ13: =AE13=J13 -> TRUE | BA13: =AF13=K13 -> TRUE | BB13: =AG13=L13 -> TRUE | BC13: =AH13=M13 -> TRUE | ... BP13: =AU13=Z13 -> TRUE | DH13: =CM13=BR13 -> TRUE | DI13: =CN13=BS13 -> TRUE | DJ13: =CO13=BT13 -> TRUE | DK13: =CP13=BU13 -> TRUE | DL13: =CQ13=BV13 -> TRUE | DM13: =CR13=BW13 -> TRUE | DN13: =CS13=BX13 -> TRUE | DO13: =CT13=BY13 -> TRUE | ... EB13: =DG13=CL13 -> TRUE | ED13: =ED14-ED15-ED16 -> 0 | EE13: =EE14-EE15-EE16 -> 0 | EF13: =EF14-EF15-EF16 -> 0 | EG13: =EG14-EG15-EG16 -> 367011.76 | EH13: =EH14-EH15-EH16 -> 782713.72 | EI13: =EI14-EI15-EI16 -> 1143020.3 | EJ13: =EJ14-EJ15-EJ16 -> 1469945.2 | EK13: =EK14-EK15-EK16 -> 1636817.1 | ... EX13: =EX14-EX15-EX16 -> 2016699
C14: 6 | D14: Доходы | E14: тыс. руб. | F14: ='[10]Данные для переноса'!F14 -> 8984824.4 | G14: ='[10]Данные для переноса'!G14 -> 10045646 | H14: ='[10]Данные для переноса'!H14 -> 11942291 | I14: ='[10]Данные для переноса'!I14 -> 12450116 | J14: ='[10]Данные для переноса'!J14 -> 13279852 | K14: ='[10]Данные для переноса'!K14 -> 14178366 | L14: ='[10]Данные для переноса'!L14 -> 14869021 | M14: ='[10]Данные для переноса'!M14 -> 15559124 | ... Z14: ='[10]Данные для переноса'!Z14 -> 29076364 | AA14: 8984824.4 | AB14: 10045646 | AC14: 11942291 | AD14: 12450116 | AE14: 13279852 | AF14: 14178366 | AG14: 14869021 | AH14: 15559124 | AI14: 16308490 | AJ14: 17093187 | AK14: 17922049 | AL14: 18794253 | AM14: 19710689 | AN14: 20680802 | AO14: 21697375 | AP14: 22771346 | AQ14: 23901377 | AR14: 25093528 | AS14: 26352732 | AT14: 27678551 | AU14: 29076364 | AV14: =AA14=F14 -> TRUE | AW14: =AB14=G14 -> TRUE | AX14: =AC14=H14 -> TRUE | AY14: =AD14=I14 -> TRUE | AZ14: =AE14=J14 -> TRUE | BA14: =AF14=K14 -> TRUE | BB14: =AG14=L14 -> TRUE | BC14: =AH14=M14 -> TRUE | ... BP14: =AU14=Z14 -> TRUE | BQ14: =SUM(J14:Z14) -> 3.449671e+08 | BR14: ='[10]Данные для переноса'!AB14 -> 8984824.4 | BS14: ='[10]Данные для переноса'!AC14 -> 10045646 | BT14: ='[10]Данные для переноса'!AD14 -> 11942291 | BU14: ='[10]Данные для переноса'!AE14 -> 13217205 | BV14: ='[10]Данные для переноса'!AF14 -> 14560925 | BW14: ='[10]Данные для переноса'!AG14 -> 15940940 | BX14: ='[10]Данные для переноса'!AH14 -> 17053902 | BY14: ='[10]Данные для переноса'!AI14 -> 17983197 | ... CL14: ='[10]Данные для переноса'!AV14 -> 32897557 | CM14: 8984824.4 | CN14: 10045646 | CO14: 11942291 | CP14: 13217205 | CQ14: 14560925 | CR14: 15940940 | CS14: 17053902 | CT14: 17983197 | CU14: 18827670 | CV14: 19698717 | CW14: 20615205 | CX14: 21579163 | CY14: 22592107 | CZ14: 23658905 | DA14: 24775829 | DB14: 25975642 | DC14: 27220943 | DD14: 28528405 | DE14: 29914885 | DF14: 31362727 | DG14: 32897557 | DH14: =CM14=BR14 -> TRUE | DI14: =CN14=BS14 -> TRUE | DJ14: =CO14=BT14 -> TRUE | DK14: =CP14=BU14 -> TRUE | DL14: =CQ14=BV14 -> TRUE | DM14: =CR14=BW14 -> TRUE | DN14: =CS14=BX14 -> TRUE | DO14: =CT14=BY14 -> TRUE | ... EB14: =DG14=CL14 -> TRUE | EC14: =SUM(BV14:CL14) -> 3.9318672e+08 | ED14: =BR14-F14 -> 0 | EE14: =BS14-G14 -> 0 | EF14: =BT14-H14 -> 0 | EG14: =BU14-I14 -> 767088.6 | EH14: =BV14-J14 -> 1281073.5 | EI14: =BW14-K14 -> 1762573.6 | EJ14: =BX14-L14 -> 2184880.8 | EK14: =BY14-M14 -> 2424073.7 | ... EX14: =CL14-Z14 -> 3821193.4 | EY14: =SUM(EH14:EX14) -> 48219616
C15: 7 | D15: Переменные расходы (ФОТ основного персонала, матзапасы, НМА, соисполнители) | E15: тыс. руб. | F15: ='[10]Данные для переноса'!F15 -> 3882674.3 | G15: ='[10]Данные для переноса'!G15 -> 4550089.5 | H15: ='[10]Данные для переноса'!H15 -> 5312139.2 | I15: ='[10]Данные для переноса'!I15 -> 5811953.8 | J15: ='[10]Данные для переноса'!J15 -> 6316299.1 | K15: ='[10]Данные для переноса'!K15 -> 6822832.9 | L15: ='[10]Данные для переноса'!L15 -> 7094131.8 | M15: ='[10]Данные для переноса'!M15 -> 7374917.2 | ... Z15: ='[10]Данные для переноса'!Z15 -> 12280755 | AA15: 3882674.3 | AB15: 4550089.5 | AC15: 5312139.2 | AD15: 5811953.8 | AE15: 6316299.1 | AF15: 6822832.9 | AG15: 7094131.8 | AH15: 7374917.2 | AI15: 7669950.5 | AJ15: 7976788.2 | AK15: 8295902.6 | AL15: 8627785 | AM15: 8972946.6 | AN15: 9331918.7 | AO15: 9705254.1 | AP15: 10093528 | AQ15: 10497338 | AR15: 10917305 | AS15: 11354078 | AT15: 11808328 | AU15: 12280755 | AV15: =AA15=F15 -> TRUE | AW15: =AB15=G15 -> TRUE | AX15: =AC15=H15 -> TRUE | AY15: =AD15=I15 -> TRUE | AZ15: =AE15=J15 -> TRUE | BA15: =AF15=K15 -> TRUE | BB15: =AG15=L15 -> TRUE | BC15: =AH15=M15 -> TRUE | ... BP15: =AU15=Z15 -> TRUE | BQ15: =SUM(J15:Z15) -> 1.5514006e+08 | BR15: ='[10]Данные для переноса'!AB15 -> 3882674.3 | BS15: ='[10]Данные для переноса'!AC15 -> 4550089.5 | BT15: ='[10]Данные для переноса'!AD15 -> 5312139.2 | BU15: ='[10]Данные для переноса'!AE15 -> 6212030.6 | BV15: ='[10]Данные для переноса'!AF15 -> 6814658.8 | BW15: ='[10]Данные для переноса'!AG15 -> 7442386.3 | BX15: ='[10]Данные для переноса'!AH15 -> 7809067.4 | BY15: ='[10]Данные для переноса'!AI15 -> 8162173.7 | ... CL15: ='[10]Данные для переноса'!AV15 -> 14085249 | CM15: 3882674.3 | CN15: 4550089.5 | CO15: 5312139.2 | CP15: 6212030.6 | CQ15: 6814658.8 | CR15: 7442386.3 | CS15: 7809067.4 | CT15: 8162173.7 | CU15: 8512533.7 | CV15: 8876864.9 | CW15: 9257140 | CX15: 9654068.5 | CY15: 10068391 | CZ15: 10497843 | DA15: 10945544 | DB15: 11423650 | DC15: 11914338 | DD15: 12422177 | DE15: 12955851 | DF15: 13506428 | DG15: 14085249 | DH15: =CM15=BR15 -> TRUE | DI15: =CN15=BS15 -> TRUE | DJ15: =CO15=BT15 -> TRUE | DK15: =CP15=BU15 -> TRUE | DL15: =CQ15=BV15 -> TRUE | DM15: =CR15=BW15 -> TRUE | DN15: =CS15=BX15 -> TRUE | DO15: =CT15=BY15 -> TRUE | ... EB15: =DG15=CL15 -> TRUE | EC15: =SUM(BV15:CL15) -> 1.7434836e+08 | ED15: =BR15-F15 -> 0 | EE15: =BS15-G15 -> 0 | EF15: =BT15-H15 -> 0 | EG15: =BU15-I15 -> 400076.84 | EH15: =BV15-J15 -> 498359.74 | EI15: =BW15-K15 -> 619553.31 | EJ15: =BX15-L15 -> 714935.6 | EK15: =BY15-M15 -> 787256.52 | ... EX15: =CL15-Z15 -> 1804494.4 | EY15: =SUM(EH15:EX15) -> 19208307
C16: 8 | D16: Постоянные расходы | E16: тыс. руб. | AV16: =AA16=F16 -> TRUE | AW16: =AB16=G16 -> TRUE | AX16: =AC16=H16 -> TRUE | AY16: =AD16=I16 -> TRUE | AZ16: =AE16=J16 -> TRUE | BA16: =AF16=K16 -> TRUE | BB16: =AG16=L16 -> TRUE | BC16: =AH16=M16 -> TRUE | ... BP16: =AU16=Z16 -> TRUE | DH16: =CM16=BR16 -> TRUE | DI16: =CN16=BS16 -> TRUE | DJ16: =CO16=BT16 -> TRUE | DK16: =CP16=BU16 -> TRUE | DL16: =CQ16=BV16 -> TRUE | DM16: =CR16=BW16 -> TRUE | DN16: =CS16=BX16 -> TRUE | DO16: =CT16=BY16 -> TRUE | ... EB16: =DG16=CL16 -> TRUE | ED16: ='ФинРез Кампус'!F23 -> 0 | EE16: ='ФинРез Кампус'!G23 -> 0 | EF16: ='ФинРез Кампус'!H23 -> 0 | EG16: ='ФинРез Кампус'!I23 -> 0 | EH16: ='ФинРез Кампус'!J23 -> 0 | EI16: ='ФинРез Кампус'!K23 -> 0 | EJ16: ='ФинРез Кампус'!L23 -> 0 | EK16: ='ФинРез Кампус'!M23 -> 0 | ... EX16: ='ФинРез Кампус'!Z23 -> 0
C17: 9 | D17: Инвестиционные расходы (включая приобретение основных средств) | E17: тыс. руб. | F17: ='[10]Данные для переноса'!F16 -> 481773.37 | G17: ='[10]Данные для переноса'!G16 -> 580219.16 | H17: ='[10]Данные для переноса'!H16 -> 873016.36 | I17: ='[10]Данные для переноса'!I16 -> 912302.1 | J17: ='[10]Данные для переноса'!J16 -> 948794.18 | K17: ='[10]Данные для переноса'!K16 -> 986745.95 | L17: ='[10]Данные для переноса'!L16 -> 1026215.8 | M17: ='[10]Данные для переноса'!M16 -> 1067264.4 | ... Z17: ='[10]Данные для переноса'!Z16 -> 1777073.7 | AA17: 481773.37 | AB17: 580219.16 | AC17: 873016.36 | AD17: 912302.1 | AE17: 948794.18 | AF17: 986745.95 | AG17: 1026215.8 | AH17: 1067264.4 | AI17: 1109955 | AJ17: 1154353.2 | AK17: 1200527.3 | AL17: 1248548.4 | AM17: 1298490.4 | AN17: 1350430 | AO17: 1404447.2 | AP17: 1460625.1 | AQ17: 1519050.1 | AR17: 1579812.1 | AS17: 1643004.5 | AT17: 1708724.7 | AU17: 1777073.7 | AV17: =AA17=F17 -> TRUE | AW17: =AB17=G17 -> TRUE | AX17: =AC17=H17 -> TRUE | AY17: =AD17=I17 -> TRUE | AZ17: =AE17=J17 -> TRUE | BA17: =AF17=K17 -> TRUE | BB17: =AG17=L17 -> TRUE | BC17: =AH17=M17 -> TRUE | ... BP17: =AU17=Z17 -> TRUE | BQ17: =SUM(J17:Z17) -> 22484062 | BR17: ='[10]Данные для переноса'!AB16 -> 481773.37 | BS17: ='[10]Данные для переноса'!AC16 -> 580219.16 | BT17: ='[10]Данные для переноса'!AD16 -> 873016.36 | BU17: ='[10]Данные для переноса'!AE16 -> 912302.1 | BV17: ='[10]Данные для переноса'!AF16 -> 948794.18 | BW17: ='[10]Данные для переноса'!AG16 -> 986745.95 | BX17: ='[10]Данные для переноса'!AH16 -> 1026215.8 | BY17: ='[10]Данные для переноса'!AI16 -> 1067264.4 | ... CL17: ='[10]Данные для переноса'!AV16 -> 1777073.7 | CM17: 481773.37 | CN17: 580219.16 | CO17: 873016.36 | CP17: 912302.1 | CQ17: 948794.18 | CR17: 986745.95 | CS17: 1026215.8 | CT17: 1067264.4 | CU17: 1109955 | CV17: 1154353.2 | CW17: 1200527.3 | CX17: 1248548.4 | CY17: 1298490.4 | CZ17: 1350430 | DA17: 1404447.2 | DB17: 1460625.1 | DC17: 1519050.1 | DD17: 1579812.1 | DE17: 1643004.5 | DF17: 1708724.7 | DG17: 1777073.7 | DH17: =CM17=BR17 -> TRUE | DI17: =CN17=BS17 -> TRUE | DJ17: =CO17=BT17 -> TRUE | DK17: =CP17=BU17 -> TRUE | DL17: =CQ17=BV17 -> TRUE | DM17: =CR17=BW17 -> TRUE | DN17: =CS17=BX17 -> TRUE | DO17: =CT17=BY17 -> TRUE | ... EB17: =DG17=CL17 -> TRUE | EC17: =SUM(BV17:CL17) -> 22484062 | ED17: =BR17-F17 -> 0 | EE17: =BS17-G17 -> 0 | EF17: =BT17-H17 -> 0 | EG17: =BU17-I17 -> 0 | EH17: =BV17-J17 -> 0 | EI17: =BW17-K17 -> 0 | EJ17: =BX17-L17 -> 0 | EK17: =BY17-M17 -> 0 | ... EX17: =CL17-Z17 -> 0 | EY17: =SUM(EH17:EX17) -> 0
D18: Наука | AV18: =AA18=F18 -> TRUE | AW18: =AB18=G18 -> TRUE | AX18: =AC18=H18 -> TRUE | AY18: =AD18=I18 -> TRUE | AZ18: =AE18=J18 -> TRUE | BA18: =AF18=K18 -> TRUE | BB18: =AG18=L18 -> TRUE | BC18: =AH18=M18 -> TRUE | ... BP18: =AU18=Z18 -> TRUE | DH18: =CM18=BR18 -> TRUE | DI18: =CN18=BS18 -> TRUE | DJ18: =CO18=BT18 -> TRUE | DK18: =CP18=BU18 -> TRUE | DL18: =CQ18=BV18 -> TRUE | DM18: =CR18=BW18 -> TRUE | DN18: =CS18=BX18 -> TRUE | DO18: =CT18=BY18 -> TRUE | ... EB18: =DG18=CL18 -> TRUE | ED18: =ED19-ED20-ED21 -> 0 | EE18: =EE19-EE20-EE21 -> 0 | EF18: =EF19-EF20-EF21 -> 0 | EG18: =EG19-EG20-EG21 -> 612.27064 | EH18: =EH19-EH20-EH21 -> 39956.646 | EI18: =EI19-EI20-EI21 -> 40584.153 | EJ18: =EJ19-EJ20-EJ21 -> 45016.417 | EK18: =EK19-EK20-EK21 -> 45807.097 | ... EX18: =EX19-EX20-EX21 -> 57138.351
C19: 9 | D19: Доходы | E19: тыс. руб. | F19: ='[10]Данные для переноса'!F18 -> 1171701.4 | G19: ='[10]Данные для переноса'!G18 -> 1960113.9 | H19: ='[10]Данные для переноса'!H18 -> 2636185 | I19: ='[10]Данные для переноса'!I18 -> 2854380.7 | J19: ='[10]Данные для переноса'!J18 -> 2934600.2 | K19: ='[10]Данные для переноса'!K18 -> 3027858.2 | L19: ='[10]Данные для переноса'!L18 -> 3148972.5 | M19: ='[10]Данные для переноса'!M18 -> 3274931.4 | ... Z19: ='[10]Данные для переноса'!Z18 -> 5453001.5 | AA19: 1171701.4 | AB19: 1960113.9 | AC19: 2636185 | AD19: 2854380.7 | AE19: 2934600.2 | AF19: 3027858.2 | AG19: 3148972.5 | AH19: 3274931.4 | AI19: 3405928.7 | AJ19: 3542165.8 | AK19: 3683852.5 | AL19: 3831206.6 | AM19: 3984454.8 | AN19: 4143833 | AO19: 4309586.3 | AP19: 4481969.8 | AQ19: 4661248.6 | AR19: 4847698.5 | AS19: 5041606.5 | AT19: 5243270.7 | AU19: 5453001.5 | AV19: =AA19=F19 -> TRUE | AW19: =AB19=G19 -> TRUE | AX19: =AC19=H19 -> TRUE | AY19: =AD19=I19 -> TRUE | AZ19: =AE19=J19 -> TRUE | BA19: =AF19=K19 -> TRUE | BB19: =AG19=L19 -> TRUE | BC19: =AH19=M19 -> TRUE | ... BP19: =AU19=Z19 -> TRUE | BQ19: =SUM(J19:Z19) -> 69016186 | BR19: ='[10]Данные для переноса'!AB18 -> 1171701.4 | BS19: ='[10]Данные для переноса'!AC18 -> 1960113.9 | BT19: ='[10]Данные для переноса'!AD18 -> 2636185 | BU19: ='[10]Данные для переноса'!AE18 -> 2862034 | BV19: ='[10]Данные для переноса'!AF18 -> 3434058.3 | BW19: ='[10]Данные для переноса'!AG18 -> 3535160.1 | BX19: ='[10]Данные для переноса'!AH18 -> 3711677.7 | BY19: ='[10]Данные для переноса'!AI18 -> 3847520.1 | ... CL19: ='[10]Данные для переноса'!AV18 -> 6167230.9 | CM19: 1171701.4 | CN19: 1960113.9 | CO19: 2636185 | CP19: 2862034 | CQ19: 3434058.3 | CR19: 3535160.1 | CS19: 3711677.7 | CT19: 3847520.1 | CU19: 3988543.7 | CV19: 4134950.7 | CW19: 4286951.3 | CX19: 4444763.9 | CY19: 4608615.8 | CZ19: 4778742.9 | DA19: 4955390.8 | DB19: 5138814.6 | DC19: 5329279.5 | DD19: 5527061.2 | DE19: 5732446.4 | DF19: 5945733 | DG19: 6167230.9 | DH19: =CM19=BR19 -> TRUE | DI19: =CN19=BS19 -> TRUE | DJ19: =CO19=BT19 -> TRUE | DK19: =CP19=BU19 -> TRUE | DL19: =CQ19=BV19 -> TRUE | DM19: =CR19=BW19 -> TRUE | DN19: =CS19=BX19 -> TRUE | DO19: =CT19=BY19 -> TRUE | ... EB19: =DG19=CL19 -> TRUE | EC19: =SUM(BV19:CL19) -> 79566941 | ED19: =BR19-F19 -> 0 | EE19: =BS19-G19 -> 0 | EF19: =BT19-H19 -> 0 | EG19: =BU19-I19 -> 7653.3831 | EH19: =BV19-J19 -> 499458.08 | EI19: =BW19-K19 -> 507301.91 | EJ19: =BX19-L19 -> 562705.22 | EK19: =BY19-M19 -> 572588.71 | ... EX19: =CL19-Z19 -> 714229.39 | EY19: =SUM(EH19:EX19) -> 10550755
C20: 10 | D20: Переменные расходы (ФОТ основного персонала, матзапасы, НМА, соисполнители) | E20: тыс. руб. | F20: ='[10]Данные для переноса'!F19 -> 1068943.2 | G20: ='[10]Данные для переноса'!G19 -> 1505563.5 | H20: ='[10]Данные для переноса'!H19 -> 2404991.6 | I20: ='[10]Данные для переноса'!I19 -> 2626030.2 | J20: ='[10]Данные для переноса'!J19 -> 2699832.2 | K20: ='[10]Данные для переноса'!K19 -> 2785629.5 | L20: ='[10]Данные для переноса'!L19 -> 2897054.7 | M20: ='[10]Данные для переноса'!M19 -> 3012936.9 | ... Z20: ='[10]Данные для переноса'!Z19 -> 5016761.4 | AA20: 1068943.2 | AB20: 1505563.5 | AC20: 2404991.6 | AD20: 2626030.2 | AE20: 2699832.2 | AF20: 2785629.5 | AG20: 2897054.7 | AH20: 3012936.9 | AI20: 3133454.4 | AJ20: 3258792.6 | AK20: 3389144.3 | AL20: 3524710 | AM20: 3665698.4 | AN20: 3812326.4 | AO20: 3964819.4 | AP20: 4123412.2 | AQ20: 4288348.7 | AR20: 4459882.6 | AS20: 4638277.9 | AT20: 4823809.1 | AU20: 5016761.4 | AV20: =AA20=F20 -> TRUE | AW20: =AB20=G20 -> TRUE | AX20: =AC20=H20 -> TRUE | AY20: =AD20=I20 -> TRUE | AZ20: =AE20=J20 -> TRUE | BA20: =AF20=K20 -> TRUE | BB20: =AG20=L20 -> TRUE | BC20: =AH20=M20 -> TRUE | ... BP20: =AU20=Z20 -> TRUE | BQ20: =SUM(J20:Z20) -> 63494891 | BR20: ='[10]Данные для переноса'!AB19 -> 1068943.2 | BS20: ='[10]Данные для переноса'!AC19 -> 1505563.5 | BT20: ='[10]Данные для переноса'!AD19 -> 2404991.6 | BU20: ='[10]Данные для переноса'!AE19 -> 2633071.3 | BV20: ='[10]Данные для переноса'!AF19 -> 3159333.6 | BW20: ='[10]Данные для переноса'!AG19 -> 3252347.3 | BX20: ='[10]Данные для переноса'!AH19 -> 3414743.5 | BY20: ='[10]Данные для переноса'!AI19 -> 3539718.5 | ... CL20: ='[10]Данные для переноса'!AV19 -> 5673852.5 | CM20: 1068943.2 | CN20: 1505563.5 | CO20: 2404991.6 | CP20: 2633071.3 | CQ20: 3159333.6 | CR20: 3252347.3 | CS20: 3414743.5 | CT20: 3539718.5 | CU20: 3669460.2 | CV20: 3804154.7 | CW20: 3943995.2 | CX20: 4089182.8 | CY20: 4239926.5 | CZ20: 4396443.5 | DA20: 4558959.6 | DB20: 4727709.4 | DC20: 4902937.1 | DD20: 5084896.3 | DE20: 5273850.7 | DF20: 5470074.4 | DG20: 5673852.5 | DH20: =CM20=BR20 -> TRUE | DI20: =CN20=BS20 -> TRUE | DJ20: =CO20=BT20 -> TRUE | DK20: =CP20=BU20 -> TRUE | DL20: =CQ20=BV20 -> TRUE | DM20: =CR20=BW20 -> TRUE | DN20: =CS20=BX20 -> TRUE | DO20: =CT20=BY20 -> TRUE | ... EB20: =DG20=CL20 -> TRUE | EC20: =SUM(BV20:CL20) -> 73201586 | ED20: =BR20-F20 -> 0 | EE20: =BS20-G20 -> 0 | EF20: =BT20-H20 -> 0 | EG20: =BU20-I20 -> 7041.1124 | EH20: =BV20-J20 -> 459501.43 | EI20: =BW20-K20 -> 466717.76 | EJ20: =BX20-L20 -> 517688.8 | EK20: =BY20-M20 -> 526781.61 | ... EX20: =CL20-Z20 -> 657091.04 | EY20: =SUM(EH20:EX20) -> 9706695
C21: 12 | D21: Постоянные расходы | E21: тыс. руб. | AV21: =AA21=F21 -> TRUE | AW21: =AB21=G21 -> TRUE | AX21: =AC21=H21 -> TRUE | AY21: =AD21=I21 -> TRUE | AZ21: =AE21=J21 -> TRUE | BA21: =AF21=K21 -> TRUE | BB21: =AG21=L21 -> TRUE | BC21: =AH21=M21 -> TRUE | ... BP21: =AU21=Z21 -> TRUE | BQ21: =SUM(J21:Z21) -> 0 | DH21: =CM21=BR21 -> TRUE | DI21: =CN21=BS21 -> TRUE | DJ21: =CO21=BT21 -> TRUE | DK21: =CP21=BU21 -> TRUE | DL21: =CQ21=BV21 -> TRUE | DM21: =CR21=BW21 -> TRUE | DN21: =CS21=BX21 -> TRUE | DO21: =CT21=BY21 -> TRUE | ... EB21: =DG21=CL21 -> TRUE | EC21: =SUM(BV21:CL21) -> 0 | ED21: ='ФинРез Кампус'!F90 -> 0 | EE21: ='ФинРез Кампус'!G90 -> 0 | EF21: ='ФинРез Кампус'!H90 -> 0 | EG21: ='ФинРез Кампус'!I90 -> 0 | EH21: ='ФинРез Кампус'!J90 -> 0 | EI21: ='ФинРез Кампус'!K90 -> 0 | EJ21: ='ФинРез Кампус'!L90 -> 0 | EK21: ='ФинРез Кампус'!M90 -> 0 | ... EX21: ='ФинРез Кампус'!Z90 -> 0 | EY21: =SUM(EH21:EX21) -> 0
C22: 11 | D22: Инвестиционные расходы (включая приобретение основных средств) | E22: тыс. руб. | F22: ='[10]Данные для переноса'!F20 -> 124641.6 | G22: ='[10]Данные для переноса'!G20 -> 143386.88 | H22: ='[10]Данные для переноса'!H20 -> 63284.984 | I22: ='[10]Данные для переноса'!I20 -> 66132.809 | J22: ='[10]Данные для переноса'!J20 -> 68778.121 | K22: ='[10]Данные для переноса'!K20 -> 71529.246 | L22: ='[10]Данные для переноса'!L20 -> 74390.416 | M22: ='[10]Данные для переноса'!M20 -> 77366.032 | ... Z22: ='[10]Данные для переноса'!Z20 -> 128820.13 | AA22: 124641.6 | AB22: 143386.88 | AC22: 63284.984 | AD22: 66132.809 | AE22: 68778.121 | AF22: 71529.246 | AG22: 74390.416 | AH22: 77366.032 | AI22: 80460.674 | AJ22: 83679.101 | AK22: 87026.265 | AL22: 90507.315 | AM22: 94127.608 | AN22: 97892.712 | AO22: 101808.42 | AP22: 105880.76 | AQ22: 110115.99 | AR22: 114520.63 | AS22: 119101.45 | AT22: 123865.51 | AU22: 128820.13 | AV22: =AA22=F22 -> TRUE | AW22: =AB22=G22 -> TRUE | AX22: =AC22=H22 -> TRUE | AY22: =AD22=I22 -> TRUE | AZ22: =AE22=J22 -> TRUE | BA22: =AF22=K22 -> TRUE | BB22: =AG22=L22 -> TRUE | BC22: =AH22=M22 -> TRUE | ... BP22: =AU22=Z22 -> TRUE | BQ22: =SUM(J22:Z22) -> 1629870.4 | BR22: ='[10]Данные для переноса'!AB20 -> 124641.6 | BS22: ='[10]Данные для переноса'!AC20 -> 143386.88 | BT22: ='[10]Данные для переноса'!AD20 -> 63284.984 | BU22: ='[10]Данные для переноса'!AE20 -> 66132.809 | BV22: ='[10]Данные для переноса'!AF20 -> 68778.121 | BW22: ='[10]Данные для переноса'!AG20 -> 71529.246 | BX22: ='[10]Данные для переноса'!AH20 -> 74390.416 | BY22: ='[10]Данные для переноса'!AI20 -> 77366.032 | ... CL22: ='[10]Данные для переноса'!AV20 -> 128820.13 | CM22: 124641.6 | CN22: 143386.88 | CO22: 63284.984 | CP22: 66132.809 | CQ22: 68778.121 | CR22: 71529.246 | CS22: 74390.416 | CT22: 77366.032 | CU22: 80460.674 | CV22: 83679.101 | CW22: 87026.265 | CX22: 90507.315 | CY22: 94127.608 | CZ22: 97892.712 | DA22: 101808.42 | DB22: 105880.76 | DC22: 110115.99 | DD22: 114520.63 | DE22: 119101.45 | DF22: 123865.51 | DG22: 128820.13 | DH22: =CM22=BR22 -> TRUE | DI22: =CN22=BS22 -> TRUE | DJ22: =CO22=BT22 -> TRUE | DK22: =CP22=BU22 -> TRUE | DL22: =CQ22=BV22 -> TRUE | DM22: =CR22=BW22 -> TRUE | DN22: =CS22=BX22 -> TRUE | DO22: =CT22=BY22 -> TRUE | ... EB22: =DG22=CL22 -> TRUE | EC22: =SUM(BV22:CL22) -> 1629870.4 | ED22: =BR22-F22 -> 0 | EE22: =BS22-G22 -> 0 | EF22: =BT22-H22 -> 0 | EG22: =BU22-I22 -> 0 | EH22: =BV22-J22 -> 0 | EI22: =BW22-K22 -> 0 | EJ22: =BX22-L22 -> 0 | EK22: =BY22-M22 -> 0 | ... EX22: =CL22-Z22 -> 0 | EY22: =SUM(EH22:EX22) -> 0
C23: 12 | D23: Потребность в дофинансировании (базовая) | E23: тыс.руб. | F23: =F24+F28 -> 0 | G23: =G24+G28 -> 0 | H23: =H24+H28 -> 0 | I23: =I24+I28 -> 0 | J23: =J24+J28 -> 0 | K23: =K24+K28 -> 0 | L23: =L24+L28 -> 0 | M23: =M24+M28 -> 0 | ... Z23: =Z24+Z28 -> 0 | AA23: 0 | AB23: 0 | AC23: 0 | AD23: 0 | AE23: 0 | AF23: 0 | AG23: 0 | AH23: 0 | AI23: 0 | AJ23: 0 | AK23: 0 | AL23: 0 | AM23: 0 | AN23: 0 | AO23: 0 | AP23: 0 | AQ23: 0 | AR23: 0 | AS23: 0 | AT23: 0 | AU23: 0 | AV23: =AA23=F23 -> TRUE | AW23: =AB23=G23 -> TRUE | AX23: =AC23=H23 -> TRUE | AY23: =AD23=I23 -> TRUE | AZ23: =AE23=J23 -> TRUE | BA23: =AF23=K23 -> TRUE | BB23: =AG23=L23 -> TRUE | BC23: =AH23=M23 -> TRUE | ... BP23: =AU23=Z23 -> TRUE | BQ23: =SUM(J23:Z23) -> 0 | BR23: =BR24+BR28 -> 0 | BS23: =BS24+BS28 -> 0 | BT23: =BT24+BT28 -> 0 | BU23: =BU24+BU28 -> 0 | BV23: =BV24+BV28 -> 0 | BW23: =BW24+BW28 -> 0 | BX23: =BX24+BX28 -> 0 | BY23: =BY24+BY28 -> 124377.91 | ... CL23: =CL24+CL28 -> 980888.58 | CM23: 0 | CN23: 0 | CO23: 0 | CP23: 0 | CQ23: 0 | CR23: 0 | CS23: 0 | CT23: 124377.91 | CU23: 124377.91 | CV23: 0 | CW23: 0 | CX23: 0.0001639314 | CY23: 0.00016393047 | CZ23: 541439.27 | DA23: 1109137.6 | DB23: 989732.15 | DC23: 988200.82 | DD23: 694786.35 | DE23: 984797.45 | DF23: 982910.28 | DG23: 980888.58 | DH23: =CM23=BR23 -> TRUE | DI23: =CN23=BS23 -> TRUE | DJ23: =CO23=BT23 -> TRUE | DK23: =CP23=BU23 -> TRUE | DL23: =CQ23=BV23 -> TRUE | DM23: =CR23=BW23 -> TRUE | DN23: =CS23=BX23 -> TRUE | DO23: =CT23=BY23 -> TRUE | ... EB23: =DG23=CL23 -> TRUE | EC23: =SUM(BV23:CL23) -> 7271892.5 | ED23: =BR23 -> 0 | EE23: =BS23 -> 0 | EF23: =BT23 -> 0 | EG23: =BU23 -> 0 | EH23: =BV23 -> 0 | EI23: =BW23 -> 0 | EJ23: =BX23 -> 0 | EK23: =BY23 -> 124377.91 | ... EX23: =CL23 -> 980888.58 | EY23: =SUM(EH23:EX23) -> 7271892.5
C24: 13 | D24: Потребность в дофинансировании на ввод в эксплуатацию и оснащение (фин.результат) | E24: тыс. руб. | F24: ='[10]Данные для переноса'!F22 -> 0 | G24: ='[10]Данные для переноса'!G22 -> 0 | H24: ='[10]Данные для переноса'!H22 -> 0 | I24: ='[10]Данные для переноса'!I22 -> 0 | J24: ='[10]Данные для переноса'!J22 -> 0 | K24: ='[10]Данные для переноса'!K22 -> 0 | L24: ='[10]Данные для переноса'!L22 -> 0 | M24: ='[10]Данные для переноса'!M22 -> 0 | ... Z24: ='[10]Данные для переноса'!Z22 -> 0 | AV24: =AA24=F24 -> TRUE | AW24: =AB24=G24 -> TRUE | AX24: =AC24=H24 -> TRUE | AY24: =AD24=I24 -> TRUE | AZ24: =AE24=J24 -> TRUE | BA24: =AF24=K24 -> TRUE | BB24: =AG24=L24 -> TRUE | BC24: =AH24=M24 -> TRUE | ... BP24: =AU24=Z24 -> TRUE | BQ24: =SUM(J24:Z24) -> 0 | BR24: ='[10]Данные для переноса'!AB22 -> 0 | BS24: ='[10]Данные для переноса'!AC22 -> 0 | BT24: ='[10]Данные для переноса'!AD22 -> 0 | BU24: ='[10]Данные для переноса'!AE22 -> 0 | BV24: ='[10]Данные для переноса'!AF22 -> 0 | BW24: ='[10]Данные для переноса'!AG22 -> 0 | BX24: ='[10]Данные для переноса'!AH22 -> 0 | BY24: ='[10]Данные для переноса'!AI22 -> 124377.91 | ... CL24: ='[10]Данные для переноса'!AV22 -> 0 | CM24: 0 | CN24: 0 | CO24: 0 | CP24: 0 | CQ24: 0 | CR24: 0 | CS24: 0 | CT24: 124377.91 | CU24: 0 | CV24: 0 | CW24: 0 | CX24: 0.0001639314 | CY24: 0 | CZ24: 124377.91 | DA24: 0 | DB24: 0 | DC24: 0 | DD24: 0 | DE24: 0 | DF24: 0 | DG24: 0 | DH24: =CM24=BR24 -> TRUE | DI24: =CN24=BS24 -> TRUE | DJ24: =CO24=BT24 -> TRUE | DK24: =CP24=BU24 -> TRUE | DL24: =CQ24=BV24 -> TRUE | DM24: =CR24=BW24 -> TRUE | DN24: =CS24=BX24 -> TRUE | DO24: =CT24=BY24 -> TRUE | ... EB24: =DG24=CL24 -> TRUE | EC24: =SUM(BV24:CL24) -> 248755.81 | ED24: =BR24 -> 0 | EE24: =BS24 -> 0 | EF24: =BT24 -> 0 | EG24: =BU24 -> 0 | EH24: =BV24 -> 0 | EI24: =BW24 -> 0 | EJ24: =BX24 -> 0 | EK24: =BY24 -> 124377.91 | ... EX24: =CL24 -> 0 | EY24: =SUM(EH24:EX24) -> 248755.81
D25: за счет федерального бюджета | E25: тыс. руб. | F25: ='[10]Данные для переноса'!F23 -> 0 | G25: ='[10]Данные для переноса'!G23 -> 0 | H25: ='[10]Данные для переноса'!H23 -> 0 | I25: ='[10]Данные для переноса'!I23 -> 0 | J25: ='[10]Данные для переноса'!J23 -> 0 | K25: ='[10]Данные для переноса'!K23 -> 0 | L25: ='[10]Данные для переноса'!L23 -> 0 | M25: ='[10]Данные для переноса'!M23 -> 0 | ... Z25: ='[10]Данные для переноса'!Z23 -> 0 | AV25: =AA25=F25 -> TRUE | AW25: =AB25=G25 -> TRUE | AX25: =AC25=H25 -> TRUE | AY25: =AD25=I25 -> TRUE | AZ25: =AE25=J25 -> TRUE | BA25: =AF25=K25 -> TRUE | BB25: =AG25=L25 -> TRUE | BC25: =AH25=M25 -> TRUE | ... BP25: =AU25=Z25 -> TRUE | BQ25: =SUM(J25:Z25) -> 0 | BR25: ='[10]Данные для переноса'!AB23 -> 0 | BS25: ='[10]Данные для переноса'!AC23 -> 0 | BT25: ='[10]Данные для переноса'!AD23 -> 0 | BU25: ='[10]Данные для переноса'!AE23 -> 0 | BV25: ='[10]Данные для переноса'!AF23 -> 0 | BW25: ='[10]Данные для переноса'!AG23 -> 0 | BX25: ='[10]Данные для переноса'!AH23 -> 0 | BY25: ='[10]Данные для переноса'!AI23 -> 0 | ... CL25: ='[10]Данные для переноса'!AV23 -> 0 | CM25: 0 | CN25: 0 | CO25: 0 | CP25: 0 | CQ25: 0 | CR25: 0 | CS25: 0 | CT25: 0 | CU25: 6651958.7 | CV25: 6918037 | CW25: 4796505.7 | CX25: 4988365.9 | CY25: 0 | CZ25: 0 | DA25: 0 | DB25: 0 | DC25: 0 | DD25: 0 | DE25: 0 | DF25: 0 | DG25: 0 | DH25: =CM25=BR25 -> TRUE | DI25: =CN25=BS25 -> TRUE | DJ25: =CO25=BT25 -> TRUE | DK25: =CP25=BU25 -> TRUE | DL25: =CQ25=BV25 -> TRUE | DM25: =CR25=BW25 -> TRUE | DN25: =CS25=BX25 -> TRUE | DO25: =CT25=BY25 -> TRUE | ... EB25: =DG25=CL25 -> TRUE | EC25: =SUM(BV25:CL25) -> 23354867 | ED25: =BR25 -> 0 | EE25: =BS25 -> 0 | EF25: =BT25 -> 0 | EG25: =BU25 -> 0 | EH25: =BV25 -> 0 | EI25: =BW25 -> 0 | EJ25: =BX25 -> 0 | EK25: =BY25 -> 0 | ... EX25: =CL25 -> 0 | EY25: =SUM(EH25:EX25) -> 23354867
D26: за счет регионального и местного бюджета | E26: тыс. руб. | F26: ='[10]Данные для переноса'!F24 -> 0 | G26: ='[10]Данные для переноса'!G24 -> 0 | H26: ='[10]Данные для переноса'!H24 -> 0 | I26: ='[10]Данные для переноса'!I24 -> 0 | J26: ='[10]Данные для переноса'!J24 -> 0 | K26: ='[10]Данные для переноса'!K24 -> 0 | L26: ='[10]Данные для переноса'!L24 -> 0 | M26: ='[10]Данные для переноса'!M24 -> 0 | ... Z26: ='[10]Данные для переноса'!Z24 -> 0 | AV26: =AA26=F26 -> TRUE | AW26: =AB26=G26 -> TRUE | AX26: =AC26=H26 -> TRUE | AY26: =AD26=I26 -> TRUE | AZ26: =AE26=J26 -> TRUE | BA26: =AF26=K26 -> TRUE | BB26: =AG26=L26 -> TRUE | BC26: =AH26=M26 -> TRUE | ... BP26: =AU26=Z26 -> TRUE | BQ26: =SUM(J26:Z26) -> 0 | BR26: ='[10]Данные для переноса'!AB24 -> 0 | BS26: ='[10]Данные для переноса'!AC24 -> 0 | BT26: ='[10]Данные для переноса'!AD24 -> 0 | BU26: ='[10]Данные для переноса'!AE24 -> 0 | BV26: ='[10]Данные для переноса'!AF24 -> 0 | BW26: ='[10]Данные для переноса'!AG24 -> 0 | BX26: ='[10]Данные для переноса'!AH24 -> 0 | BY26: ='[10]Данные для переноса'!AI24 -> 0 | ... CL26: ='[10]Данные для переноса'!AV24 -> 0 | CM26: 0 | CN26: 0 | CO26: 0 | CP26: 0 | CQ26: 0 | CR26: 0 | CS26: 0 | CT26: 0 | CU26: 0 | CV26: 0 | CW26: 0 | CX26: 0 | CY26: 1100000 | CZ26: 0 | DA26: 0 | DB26: 0 | DC26: 0 | DD26: 0 | DE26: 0 | DF26: 0 | DG26: 0 | DH26: =CM26=BR26 -> TRUE | DI26: =CN26=BS26 -> TRUE | DJ26: =CO26=BT26 -> TRUE | DK26: =CP26=BU26 -> TRUE | DL26: =CQ26=BV26 -> TRUE | DM26: =CR26=BW26 -> TRUE | DN26: =CS26=BX26 -> TRUE | DO26: =CT26=BY26 -> TRUE | ... EB26: =DG26=CL26 -> TRUE | EC26: =SUM(BV26:CL26) -> 1100000 | ED26: =BR26 -> 0 | EE26: =BS26 -> 0 | EF26: =BT26 -> 0 | EG26: =BU26 -> 0 | EH26: =BV26 -> 0 | EI26: =BW26 -> 0 | EJ26: =BX26 -> 0 | EK26: =BY26 -> 0 | ... EX26: =CL26 -> 0 | EY26: =SUM(EH26:EX26) -> 1100000
D27: за счет средств приносящей доход деятельности | E27: тыс. руб. | F27: ='[10]Данные для переноса'!F25 -> 0 | G27: ='[10]Данные для переноса'!G25 -> 0 | H27: ='[10]Данные для переноса'!H25 -> 0 | I27: ='[10]Данные для переноса'!I25 -> 0 | J27: ='[10]Данные для переноса'!J25 -> 0 | K27: ='[10]Данные для переноса'!K25 -> 0 | L27: ='[10]Данные для переноса'!L25 -> 0 | M27: ='[10]Данные для переноса'!M25 -> 0 | ... Z27: ='[10]Данные для переноса'!Z25 -> 0 | AV27: =AA27=F27 -> TRUE | AW27: =AB27=G27 -> TRUE | AX27: =AC27=H27 -> TRUE | AY27: =AD27=I27 -> TRUE | AZ27: =AE27=J27 -> TRUE | BA27: =AF27=K27 -> TRUE | BB27: =AG27=L27 -> TRUE | BC27: =AH27=M27 -> TRUE | ... BP27: =AU27=Z27 -> TRUE | BQ27: =SUM(J27:Z27) -> 0 | BR27: ='[10]Данные для переноса'!AB25 -> 0 | BS27: ='[10]Данные для переноса'!AC25 -> 0 | BT27: ='[10]Данные для переноса'!AD25 -> 0 | BU27: ='[10]Данные для переноса'!AE25 -> 0 | BV27: ='[10]Данные для переноса'!AF25 -> 0 | BW27: ='[10]Данные для переноса'!AG25 -> 1146128.1 | BX27: ='[10]Данные для переноса'!AH25 -> 598568.68 | BY27: ='[10]Данные для переноса'!AI25 -> 248880.19 | ... CL27: ='[10]Данные для переноса'!AV25 -> 0 | CM27: 0 | CN27: 0 | CO27: 0 | CP27: 0 | CQ27: 0 | CR27: 1146128.1 | CS27: 598568.68 | CT27: 248880.19 | CU27: 134307.14 | CV27: 139679.42 | CW27: 1081434.6 | CX27: 1413505.1 | CY27: 1449678.3 | CZ27: 0 | DA27: 0 | DB27: 0 | DC27: 0 | DD27: 0 | DE27: 0 | DF27: 0 | DG27: 0 | DH27: =CM27=BR27 -> TRUE | DI27: =CN27=BS27 -> TRUE | DJ27: =CO27=BT27 -> TRUE | DK27: =CP27=BU27 -> TRUE | DL27: =CQ27=BV27 -> TRUE | DM27: =CR27=BW27 -> TRUE | DN27: =CS27=BX27 -> TRUE | DO27: =CT27=BY27 -> TRUE | ... EB27: =DG27=CL27 -> TRUE | EC27: =SUM(BV27:CL27) -> 6212181.4 | ED27: =BR27 -> 0 | EE27: =BS27 -> 0 | EF27: =BT27 -> 0 | EG27: =BU27 -> 0 | EH27: =BV27 -> 0 | EI27: =BW27 -> 1146128.1 | EJ27: =BX27 -> 598568.68 | EK27: =BY27 -> 248880.19 | ... EX27: =CL27 -> 0 | EY27: =SUM(EH27:EX27) -> 6212181.4
C28: 14 | D28: Потребность в дофинансировании содержания имущества и операционной деятельности (фин.результат) | E28: тыс. руб. | F28: ='[10]Данные для переноса'!F26 -> 0 | G28: ='[10]Данные для переноса'!G26 -> 0 | H28: ='[10]Данные для переноса'!H26 -> 0 | I28: ='[10]Данные для переноса'!I26 -> 0 | J28: ='[10]Данные для переноса'!J26 -> 0 | K28: ='[10]Данные для переноса'!K26 -> 0 | L28: ='[10]Данные для переноса'!L26 -> 0 | M28: ='[10]Данные для переноса'!M26 -> 0 | ... Z28: ='[10]Данные для переноса'!Z26 -> 0 | AV28: =AA28=F28 -> TRUE | AW28: =AB28=G28 -> TRUE | AX28: =AC28=H28 -> TRUE | AY28: =AD28=I28 -> TRUE | AZ28: =AE28=J28 -> TRUE | BA28: =AF28=K28 -> TRUE | BB28: =AG28=L28 -> TRUE | BC28: =AH28=M28 -> TRUE | ... BP28: =AU28=Z28 -> TRUE | BQ28: =SUM(J28:Z28) -> 0 | BR28: ='[10]Данные для переноса'!AB26 -> 0 | BS28: ='[10]Данные для переноса'!AC26 -> 0 | BT28: ='[10]Данные для переноса'!AD26 -> 0 | BU28: ='[10]Данные для переноса'!AE26 -> 0 | BV28: ='[10]Данные для переноса'!AF26 -> 0 | BW28: ='[10]Данные для переноса'!AG26 -> 0 | BX28: ='[10]Данные для переноса'!AH26 -> 0 | BY28: ='[10]Данные для переноса'!AI26 -> 0 | ... CL28: ='[10]Данные для переноса'!AV26 -> 980888.58 | CM28: 0 | CN28: 0 | CO28: 0 | CP28: 0 | CQ28: 0 | CR28: 0 | CS28: 0 | CT28: 0 | CU28: 0 | CV28: 0 | CW28: 0 | CX28: 0 | CY28: 0 | CZ28: 417061.36 | DA28: 984759.66 | DB28: 989732.15 | DC28: 988200.82 | DD28: 694786.35 | DE28: 984797.45 | DF28: 982910.28 | DG28: 980888.58 | DH28: =CM28=BR28 -> TRUE | DI28: =CN28=BS28 -> TRUE | DJ28: =CO28=BT28 -> TRUE | DK28: =CP28=BU28 -> TRUE | DL28: =CQ28=BV28 -> TRUE | DM28: =CR28=BW28 -> TRUE | DN28: =CS28=BX28 -> TRUE | DO28: =CT28=BY28 -> TRUE | ... EB28: =DG28=CL28 -> TRUE | EC28: =SUM(BV28:CL28) -> 7023136.7 | ED28: =BR28 -> 0 | EE28: =BS28 -> 0 | EF28: =BT28 -> 0 | EG28: =BU28 -> 0 | EH28: =BV28 -> 0 | EI28: =BW28 -> 0 | EJ28: =BX28 -> 0 | EK28: =BY28 -> 0 | ... EX28: =CL28 -> 980888.58 | EY28: =SUM(EH28:EX28) -> 7023136.7
D29: за счет федерального бюджета | E29: тыс. руб. | F29: ='[10]Данные для переноса'!F27 -> 0 | G29: ='[10]Данные для переноса'!G27 -> 0 | H29: ='[10]Данные для переноса'!H27 -> 0 | I29: ='[10]Данные для переноса'!I27 -> 0 | J29: ='[10]Данные для переноса'!J27 -> 0 | K29: ='[10]Данные для переноса'!K27 -> 0 | L29: ='[10]Данные для переноса'!L27 -> 0 | M29: ='[10]Данные для переноса'!M27 -> 0 | ... Z29: ='[10]Данные для переноса'!Z27 -> 0 | AV29: =AA29=F29 -> TRUE | AW29: =AB29=G29 -> TRUE | AX29: =AC29=H29 -> TRUE | AY29: =AD29=I29 -> TRUE | AZ29: =AE29=J29 -> TRUE | BA29: =AF29=K29 -> TRUE | BB29: =AG29=L29 -> TRUE | BC29: =AH29=M29 -> TRUE | ... BP29: =AU29=Z29 -> TRUE | BQ29: =SUM(J29:Z29) -> 0 | BR29: ='[10]Данные для переноса'!AB27 -> 0 | BS29: ='[10]Данные для переноса'!AC27 -> 0 | BT29: ='[10]Данные для переноса'!AD27 -> 0 | BU29: ='[10]Данные для переноса'!AE27 -> 0 | BV29: ='[10]Данные для переноса'!AF27 -> 0 | BW29: ='[10]Данные для переноса'!AG27 -> 0 | BX29: ='[10]Данные для переноса'!AH27 -> 0 | BY29: ='[10]Данные для переноса'!AI27 -> 0 | ... CL29: ='[10]Данные для переноса'!AV27 -> 0 | CM29: 0 | CN29: 0 | CO29: 0 | CP29: 0 | CQ29: 0 | CR29: 0 | CS29: 0 | CT29: 0 | CU29: 0 | CV29: 0 | CW29: 0 | CX29: 0 | CY29: 0 | CZ29: 0 | DA29: 0 | DB29: 0 | DC29: 0 | DD29: 0 | DE29: 0 | DF29: 0 | DG29: 0 | DH29: =CM29=BR29 -> TRUE | DI29: =CN29=BS29 -> TRUE | DJ29: =CO29=BT29 -> TRUE | DK29: =CP29=BU29 -> TRUE | DL29: =CQ29=BV29 -> TRUE | DM29: =CR29=BW29 -> TRUE | DN29: =CS29=BX29 -> TRUE | DO29: =CT29=BY29 -> TRUE | ... EB29: =DG29=CL29 -> TRUE | EC29: =SUM(BV29:CL29) -> 0 | ED29: =BR29 -> 0 | EE29: =BS29 -> 0 | EF29: =BT29 -> 0 | EG29: =BU29 -> 0 | EH29: =BV29 -> 0 | EI29: =BW29 -> 0 | EJ29: =BX29 -> 0 | EK29: =BY29 -> 0 | ... EX29: =CL29 -> 0 | EY29: =SUM(EH29:EX29) -> 0
D30: за счет регионального и местного бюджета | E30: тыс. руб. | F30: ='[10]Данные для переноса'!F28 -> 0 | G30: ='[10]Данные для переноса'!G28 -> 0 | H30: ='[10]Данные для переноса'!H28 -> 0 | I30: ='[10]Данные для переноса'!I28 -> 0 | J30: ='[10]Данные для переноса'!J28 -> 0 | K30: ='[10]Данные для переноса'!K28 -> 0 | L30: ='[10]Данные для переноса'!L28 -> 0 | M30: ='[10]Данные для переноса'!M28 -> 0 | ... Z30: ='[10]Данные для переноса'!Z28 -> 0 | AV30: =AA30=F30 -> TRUE | AW30: =AB30=G30 -> TRUE | AX30: =AC30=H30 -> TRUE | AY30: =AD30=I30 -> TRUE | AZ30: =AE30=J30 -> TRUE | BA30: =AF30=K30 -> TRUE | BB30: =AG30=L30 -> TRUE | BC30: =AH30=M30 -> TRUE | ... BP30: =AU30=Z30 -> TRUE | BQ30: =SUM(J30:Z30) -> 0 | BR30: ='[10]Данные для переноса'!AB28 -> 0 | BS30: ='[10]Данные для переноса'!AC28 -> 0 | BT30: ='[10]Данные для переноса'!AD28 -> 0 | BU30: ='[10]Данные для переноса'!AE28 -> 0 | BV30: ='[10]Данные для переноса'!AF28 -> 0 | BW30: ='[10]Данные для переноса'!AG28 -> 0 | BX30: ='[10]Данные для переноса'!AH28 -> 0 | BY30: ='[10]Данные для переноса'!AI28 -> 0 | ... CL30: ='[10]Данные для переноса'!AV28 -> 0 | CM30: 0 | CN30: 0 | CO30: 0 | CP30: 0 | CQ30: 0 | CR30: 0 | CS30: 0 | CT30: 0 | CU30: 0 | CV30: 0 | CW30: 0 | CX30: 0 | CY30: 0 | CZ30: 0 | DA30: 0 | DB30: 0 | DC30: 0 | DD30: 0 | DE30: 0 | DF30: 0 | DG30: 0 | DH30: =CM30=BR30 -> TRUE | DI30: =CN30=BS30 -> TRUE | DJ30: =CO30=BT30 -> TRUE | DK30: =CP30=BU30 -> TRUE | DL30: =CQ30=BV30 -> TRUE | DM30: =CR30=BW30 -> TRUE | DN30: =CS30=BX30 -> TRUE | DO30: =CT30=BY30 -> TRUE | ... EB30: =DG30=CL30 -> TRUE | EC30: =SUM(BV30:CL30) -> 0 | ED30: =BR30 -> 0 | EE30: =BS30 -> 0 | EF30: =BT30 -> 0 | EG30: =BU30 -> 0 | EH30: =BV30 -> 0 | EI30: =BW30 -> 0 | EJ30: =BX30 -> 0 | EK30: =BY30 -> 0 | ... EX30: =CL30 -> 0 | EY30: =SUM(EH30:EX30) -> 0
D31: за счет средств приносящей доход деятельности | E31: тыс. руб. | F31: ='[10]Данные для переноса'!F29 -> 0 | G31: ='[10]Данные для переноса'!G29 -> 0 | H31: ='[10]Данные для переноса'!H29 -> 0 | I31: ='[10]Данные для переноса'!I29 -> 0 | J31: ='[10]Данные для переноса'!J29 -> 0 | K31: ='[10]Данные для переноса'!K29 -> 0 | L31: ='[10]Данные для переноса'!L29 -> 0 | M31: ='[10]Данные для переноса'!M29 -> 0 | ... Z31: ='[10]Данные для переноса'!Z29 -> 0 | AV31: =AA31=F31 -> TRUE | AW31: =AB31=G31 -> TRUE | AX31: =AC31=H31 -> TRUE | AY31: =AD31=I31 -> TRUE | AZ31: =AE31=J31 -> TRUE | BA31: =AF31=K31 -> TRUE | BB31: =AG31=L31 -> TRUE | BC31: =AH31=M31 -> TRUE | ... BP31: =AU31=Z31 -> TRUE | BQ31: =SUM(J31:Z31) -> 0 | BR31: ='[10]Данные для переноса'!AB29 -> 0 | BS31: ='[10]Данные для переноса'!AC29 -> 0 | BT31: ='[10]Данные для переноса'!AD29 -> 0 | BU31: ='[10]Данные для переноса'!AE29 -> 0 | BV31: ='[10]Данные для переноса'!AF29 -> 0 | BW31: ='[10]Данные для переноса'!AG29 -> 0 | BX31: ='[10]Данные для переноса'!AH29 -> 0 | BY31: ='[10]Данные для переноса'!AI29 -> 0 | ... CL31: ='[10]Данные для переноса'!AV29 -> 980888.58 | CM31: 0 | CN31: 0 | CO31: 0 | CP31: 0 | CQ31: 0 | CR31: 0 | CS31: 0 | CT31: 0 | CU31: 0 | CV31: 0 | CW31: 0 | CX31: 0 | CY31: 0 | CZ31: 417061.36 | DA31: 984759.66 | DB31: 989732.15 | DC31: 988200.82 | DD31: 694786.35 | DE31: 984797.45 | DF31: 982910.28 | DG31: 980888.58 | DH31: =CM31=BR31 -> TRUE | DI31: =CN31=BS31 -> TRUE | DJ31: =CO31=BT31 -> TRUE | DK31: =CP31=BU31 -> TRUE | DL31: =CQ31=BV31 -> TRUE | DM31: =CR31=BW31 -> TRUE | DN31: =CS31=BX31 -> TRUE | DO31: =CT31=BY31 -> TRUE | ... EB31: =DG31=CL31 -> TRUE | EC31: =SUM(BV31:CL31) -> 7023136.7 | ED31: =BR31 -> 0 | EE31: =BS31 -> 0 | EF31: =BT31 -> 0 | EG31: =BU31 -> 0 | EH31: =BV31 -> 0 | EI31: =BW31 -> 0 | EJ31: =BX31 -> 0 | EK31: =BY31 -> 0 | ... EX31: =CL31 -> 980888.58 | EY31: =SUM(EH31:EX31) -> 7023136.7
C32: 15 | D32: Положительный денежный поток от деятельности университета | E32: тыс. руб. | F32: ='[10]Данные для переноса'!F30 -> 0 | G32: ='[10]Данные для переноса'!G30 -> 0 | H32: ='[10]Данные для переноса'!H30 -> 0 | I32: ='[10]Данные для переноса'!I30 -> 0 | J32: ='[10]Данные для переноса'!J30 -> 0 | K32: ='[10]Данные для переноса'!K30 -> 0 | L32: ='[10]Данные для переноса'!L30 -> 0 | M32: ='[10]Данные для переноса'!M30 -> 0 | ... Z32: ='[10]Данные для переноса'!Z30 -> 0 | AV32: =AA32=F32 -> TRUE | AW32: =AB32=G32 -> TRUE | AX32: =AC32=H32 -> TRUE | AY32: =AD32=I32 -> TRUE | AZ32: =AE32=J32 -> TRUE | BA32: =AF32=K32 -> TRUE | BB32: =AG32=L32 -> TRUE | BC32: =AH32=M32 -> TRUE | ... BP32: =AU32=Z32 -> TRUE | BQ32: =SUM(J32:Z32) -> 0 | BR32: ='[10]Данные для переноса'!AB30 -> 0 | BS32: ='[10]Данные для переноса'!AC30 -> 0 | BT32: ='[10]Данные для переноса'!AD30 -> 0 | BU32: ='[10]Данные для переноса'!AE30 -> 0 | BV32: ='[10]Данные для переноса'!AF30 -> 0 | BW32: ='[10]Данные для переноса'!AG30 -> 0 | BX32: ='[10]Данные для переноса'!AH30 -> 0 | BY32: ='[10]Данные для переноса'!AI30 -> 0 | ... CL32: ='[10]Данные для переноса'!AV30 -> 0 | CM32: 0 | CN32: 0 | CO32: 0 | CP32: 0 | CQ32: 0 | CR32: 0 | CS32: 0 | CT32: 0 | CU32: 124377.91 | CV32: 0 | CW32: 0 | CX32: 0 | CY32: 0.00016393047 | CZ32: 0 | DA32: 124377.91 | DB32: 0 | DC32: 0 | DD32: 0 | DE32: 0 | DF32: 0 | DG32: 0 | DH32: =CM32=BR32 -> TRUE | DI32: =CN32=BS32 -> TRUE | DJ32: =CO32=BT32 -> TRUE | DK32: =CP32=BU32 -> TRUE | DL32: =CQ32=BV32 -> TRUE | DM32: =CR32=BW32 -> TRUE | DN32: =CS32=BX32 -> TRUE | DO32: =CT32=BY32 -> TRUE | ... EB32: =DG32=CL32 -> TRUE | EC32: =SUM(BV32:CL32) -> 248755.81 | ED32: =BR32 -> 0 | EE32: =BS32 -> 0 | EF32: =BT32 -> 0 | EG32: =BU32 -> 0 | EH32: =BV32 -> 0 | EI32: =BW32 -> 0 | EJ32: =BX32 -> 0 | EK32: =BY32 -> 0 | ... EX32: =CL32 -> 0 | EY32: =SUM(EH32:EX32) -> 248755.81
C33: 16 | D33: Доходы (по источникам финансирования) | E33: тыс.руб. | F33: =SUM(F34:F36) -> 10491307 | G33: =SUM(G34:G36) -> 12413481 | H33: =SUM(H34:H36) -> 15281575 | I33: =SUM(I34:I36) -> 16541920 | J33: =SUM(J34:J36) -> 17535322 | K33: =SUM(K34:K36) -> 18604050 | L33: =SUM(L34:L36) -> 19471726 | M33: =SUM(M34:M36) -> 20345931 | ... Z33: =SUM(Z34:Z36) -> 37046659 | AA33: 10491307 | AB33: 12413481 | AC33: 15281575 | AD33: 16541920 | AE33: 17535322 | AF33: 18604050 | AG33: 19471726 | AH33: 20345931 | AI33: 21286763 | AJ33: 22270585 | AK33: 23306537 | AL33: 24394115 | AM33: 25534540 | AN33: 26737601 | AO33: 27996442 | AP33: 29322370 | AQ33: 30714438 | AR33: 32179106 | AS33: 33721727 | AT33: 35342301 | AU33: 37046659 | AV33: =AA33=F33 -> TRUE | AW33: =AB33=G33 -> TRUE | AX33: =AC33=H33 -> TRUE | AY33: =AD33=I33 -> TRUE | AZ33: =AE33=J33 -> TRUE | BA33: =AF33=K33 -> TRUE | BB33: =AG33=L33 -> TRUE | BC33: =AH33=M33 -> TRUE | ... BP33: =AU33=Z33 -> TRUE | BQ33: =SUM(BQ34:BQ36) -> 4.4581021e+08 | BR33: =SUM(BR34:BR36) -> 10491307 | BS33: =SUM(BS34:BS36) -> 12413481 | BT33: =SUM(BT34:BT36) -> 15281575 | BU33: =SUM(BU34:BU36) -> 16798888 | BV33: =SUM(BV34:BV36) -> 18753447 | BW33: =SUM(BW34:BW36) -> 21410712 | BX33: =SUM(BX34:BX36) -> 22186167 | ... CL33: =SUM(CL34:CL36) -> 45147510 | CM33: 10491307 | CN33: 12413481 | CO33: 15281575 | CP33: 16798888 | CQ33: 18753447 | CR33: 22555695 | CS33: 22784137 | CT33: 23185804 | CU33: 30617896 | CV33: 31951038 | CW33: 32825788 | CX33: 34847175 | CY33: 32263298 | CZ33: 34612033 | DA33: 34995670 | DB33: 36520678 | DC33: 38080610 | DD33: 39003424 | DE33: 41442268 | DF33: 43244257 | DG33: 45147510 | DH33: =CM33=BR33 -> TRUE | DI33: =CN33=BS33 -> TRUE | DJ33: =CO33=BT33 -> TRUE | DK33: =CP33=BU33 -> TRUE | DL33: =CQ33=BV33 -> TRUE | DM33: =CR33=BW33 -> FALSE | DN33: =CS33=BX33 -> FALSE | DO33: =CT33=BY33 -> FALSE | ... EB33: =DG33=CL33 -> TRUE | EC33: =SUM(EC34:EC36) -> 5.5493389e+08 | ED33: =BR33-F33 -> 0 | EE33: =BS33-G33 -> 0 | EF33: =BT33-H33 -> 0 | EG33: =BU33-I33 -> 256967.63 | EH33: =BV33-J33 -> 1218124.6 | EI33: =BW33-K33 -> 2806662.3 | EJ33: =BX33-L33 -> 2714441 | EK33: =BY33-M33 -> 2591117.7 | ... EX33: =CL33-Z33 -> 8100851.1 | EY33: =SUM(EY34:EY36) -> 1.0912368e+08
C34: 17 | D34: Приносящая доход деятельность | E34: тыс.руб. | F34: ='[10]Данные для переноса'!F32 -> 3675606.7 | G34: ='[10]Данные для переноса'!G32 -> 4727319.6 | H34: ='[10]Данные для переноса'!H32 -> 6075733.7 | I34: ='[10]Данные для переноса'!I32 -> 6827688.9 | J34: ='[10]Данные для переноса'!J32 -> 7324213.7 | K34: ='[10]Данные для переноса'!K32 -> 7844637 | L34: ='[10]Данные для переноса'!L32 -> 8182466.4 | M34: ='[10]Данные для переноса'!M32 -> 8506790.4 | ... Z34: ='[10]Данные для переноса'!Z32 -> 14164333 | AA34: 3675606.7 | AB34: 4727319.6 | AC34: 6075733.7 | AD34: 6827688.9 | AE34: 7324213.7 | AF34: 7844637 | AG34: 8182466.4 | AH34: 8506790.4 | AI34: 8847056 | AJ34: 9200931.1 | AK34: 9568963.1 | AL34: 9951716.2 | AM34: 10349779 | AN34: 10763764 | AO34: 11194308 | AP34: 11642075 | AQ34: 12107753 | AR34: 12592057 | AS34: 13095732 | AT34: 13619557 | AU34: 14164333 | AV34: =AA34=F34 -> TRUE | AW34: =AB34=G34 -> TRUE | AX34: =AC34=H34 -> TRUE | AY34: =AD34=I34 -> TRUE | AZ34: =AE34=J34 -> TRUE | BA34: =AF34=K34 -> TRUE | BB34: =AG34=L34 -> TRUE | BC34: =AH34=M34 -> TRUE | ... BP34: =AU34=Z34 -> TRUE | BQ34: =SUM(J34:Z34) -> 1.7895613e+08 | BR34: ='[10]Данные для переноса'!AB32 -> 3675606.7 | BS34: ='[10]Данные для переноса'!AC32 -> 4727319.6 | BT34: ='[10]Данные для переноса'!AD32 -> 6075733.7 | BU34: ='[10]Данные для переноса'!AE32 -> 7036844.8 | BV34: ='[10]Данные для переноса'!AF32 -> 8448156.1 | BW34: ='[10]Данные для переноса'!AG32 -> 10560531 | BX34: ='[10]Данные для переноса'!AH32 -> 10810959 | BY34: ='[10]Данные для переноса'!AI32 -> 11017337 | ... CL34: ='[10]Данные для переноса'!AV32 -> 22308078 | CM34: 3675606.7 | CN34: 4727319.6 | CO34: 6075733.7 | CP34: 7036844.8 | CQ34: 8448156.1 | CR34: 10560531 | CS34: 10810959 | CT34: 11017337 | CU34: 11324064 | CV34: 11762484 | CW34: 13154845 | CX34: 13955474 | CY34: 14485614 | CZ34: 16885895 | DA34: 18165670 | DB34: 18822461 | DC34: 19466635 | DD34: 19420449 | DE34: 20832479 | DF34: 21550646 | DG34: 22308078 | DH34: =CM34=BR34 -> TRUE | DI34: =CN34=BS34 -> TRUE | DJ34: =CO34=BT34 -> TRUE | DK34: =CP34=BU34 -> TRUE | DL34: =CQ34=BV34 -> TRUE | DM34: =CR34=BW34 -> TRUE | DN34: =CS34=BX34 -> TRUE | DO34: =CT34=BY34 -> TRUE | ... EB34: =DG34=CL34 -> TRUE | EC34: =SUM(BV34:CL34) -> 2.6297178e+08 | ED34: =BR34-F34 -> 0 | EE34: =BS34-G34 -> 0 | EF34: =BT34-H34 -> 0 | EG34: =BU34-I34 -> 209155.85 | EH34: =BV34-J34 -> 1123942.4 | EI34: =BW34-K34 -> 2715894.3 | EJ34: =BX34-L34 -> 2628492.8 | EK34: =BY34-M34 -> 2510547 | ... EX34: =CL34-Z34 -> 8143744.8 | EY34: =SUM(EH34:EX34) -> 84015646
C35: 18 | D35: Целевые средства | E35: тыс.руб. | F35: ='[10]Данные для переноса'!F33 -> 1059741.5 | G35: ='[10]Данные для переноса'!G33 -> 1247103.4 | H35: ='[10]Данные для переноса'!H33 -> 2051791.8 | I35: ='[10]Данные для переноса'!I33 -> 2144122.4 | J35: ='[10]Данные для переноса'!J33 -> 2229887.3 | K35: ='[10]Данные для переноса'!K33 -> 2319082.8 | L35: ='[10]Данные для переноса'!L33 -> 2411846.1 | M35: ='[10]Данные для переноса'!M33 -> 2508319.9 | ... Z35: ='[10]Данные для переноса'!Z33 -> 4176545.1 | AA35: 1059741.5 | AB35: 1247103.4 | AC35: 2051791.8 | AD35: 2144122.4 | AE35: 2229887.3 | AF35: 2319082.8 | AG35: 2411846.1 | AH35: 2508319.9 | AI35: 2608652.7 | AJ35: 2712998.8 | AK35: 2821518.8 | AL35: 2934379.5 | AM35: 3051754.7 | AN35: 3173825.9 | AO35: 3300779.9 | AP35: 3432812 | AQ35: 3570125.4 | AR35: 3712931.2 | AS35: 3861449.3 | AT35: 4015908 | AU35: 4176545.1 | AV35: =AA35=F35 -> TRUE | AW35: =AB35=G35 -> TRUE | AX35: =AC35=H35 -> TRUE | AY35: =AD35=I35 -> TRUE | AZ35: =AE35=J35 -> TRUE | BA35: =AF35=K35 -> TRUE | BB35: =AG35=L35 -> TRUE | BC35: =AH35=M35 -> TRUE | ... BP35: =AU35=Z35 -> TRUE | BQ35: =SUM(J35:Z35) -> 52842817 | BR35: ='[10]Данные для переноса'!AB33 -> 1059741.5 | BS35: ='[10]Данные для переноса'!AC33 -> 1247103.4 | BT35: ='[10]Данные для переноса'!AD33 -> 2051791.8 | BU35: ='[10]Данные для переноса'!AE33 -> 2144122.4 | BV35: ='[10]Данные для переноса'!AF33 -> 2229887.3 | BW35: ='[10]Данные для переноса'!AG33 -> 2319082.8 | BX35: ='[10]Данные для переноса'!AH33 -> 2411846.1 | BY35: ='[10]Данные для переноса'!AI33 -> 2508319.9 | ... CL35: ='[10]Данные для переноса'!AV33 -> 4176545.1 | CM35: 1059741.5 | CN35: 1247103.4 | CO35: 2051791.8 | CP35: 2144122.4 | CQ35: 2229887.3 | CR35: 2319082.8 | CS35: 2411846.1 | CT35: 2508319.9 | CU35: 2608652.7 | CV35: 2712998.8 | CW35: 2821518.8 | CX35: 2934379.5 | CY35: 4151754.7 | CZ35: 3173825.9 | DA35: 3300779.9 | DB35: 3432812 | DC35: 3570125.4 | DD35: 3712931.2 | DE35: 3861449.3 | DF35: 4015908 | DG35: 4176545.1 | DH35: =CM35=BR35 -> TRUE | DI35: =CN35=BS35 -> TRUE | DJ35: =CO35=BT35 -> TRUE | DK35: =CP35=BU35 -> TRUE | DL35: =CQ35=BV35 -> TRUE | DM35: =CR35=BW35 -> TRUE | DN35: =CS35=BX35 -> TRUE | DO35: =CT35=BY35 -> TRUE | ... EB35: =DG35=CL35 -> TRUE | EC35: =SUM(BV35:CL35) -> 53942817 | ED35: =BR35-F35 -> 0 | EE35: =BS35-G35 -> 0 | EF35: =BT35-H35 -> 0 | EG35: =BU35-I35 -> 0 | EH35: =BV35-J35 -> 0 | EI35: =BW35-K35 -> 0 | EJ35: =BX35-L35 -> 0 | EK35: =BY35-M35 -> 0 | ... EX35: =CL35-Z35 -> 0 | EY35: =SUM(EH35:EX35) -> 1100000
C36: 19 | D36: Субсидии на госзадание | E36: тыс.руб. | F36: ='[10]Данные для переноса'!F34 -> 5755958.8 | G36: ='[10]Данные для переноса'!G34 -> 6439057.7 | H36: ='[10]Данные для переноса'!H34 -> 7154049.9 | I36: ='[10]Данные для переноса'!I34 -> 7570109 | J36: ='[10]Данные для переноса'!J34 -> 7981221.2 | K36: ='[10]Данные для переноса'!K34 -> 8440329.8 | L36: ='[10]Данные для переноса'!L34 -> 8877413.2 | M36: ='[10]Данные для переноса'!M34 -> 9330820.4 | ... Z36: ='[10]Данные для переноса'!Z34 -> 18705780 | AA36: 5755958.8 | AB36: 6439057.7 | AC36: 7154049.9 | AD36: 7570109 | AE36: 7981221.2 | AF36: 8440329.8 | AG36: 8877413.2 | AH36: 9330820.4 | AI36: 9831054.2 | AJ36: 10356655 | AK36: 10916055 | AL36: 11508019 | AM36: 12133005 | AN36: 12800011 | AO36: 13501354 | AP36: 14247483 | AQ36: 15036559 | AR36: 15874118 | AS36: 16764546 | AT36: 17706837 | AU36: 18705780 | AV36: =AA36=F36 -> TRUE | AW36: =AB36=G36 -> TRUE | AX36: =AC36=H36 -> TRUE | AY36: =AD36=I36 -> TRUE | AZ36: =AE36=J36 -> TRUE | BA36: =AF36=K36 -> TRUE | BB36: =AG36=L36 -> TRUE | BC36: =AH36=M36 -> TRUE | ... BP36: =AU36=Z36 -> TRUE | BQ36: =SUM(J36:Z36) -> 2.1401126e+08 | BR36: ='[10]Данные для переноса'!AB34 -> 5755958.8 | BS36: ='[10]Данные для переноса'!AC34 -> 6439057.7 | BT36: ='[10]Данные для переноса'!AD34 -> 7154049.9 | BU36: ='[10]Данные для переноса'!AE34 -> 7617920.8 | BV36: ='[10]Данные для переноса'!AF34 -> 8075403.5 | BW36: ='[10]Данные для переноса'!AG34 -> 8531097.8 | BX36: ='[10]Данные для переноса'!AH34 -> 8963361.4 | BY36: ='[10]Данные для переноса'!AI34 -> 9411391.2 | ... CL36: ='[10]Данные для переноса'!AV34 -> 18662887 | CM36: 5755958.8 | CN36: 6439057.7 | CO36: 7154049.9 | CP36: 7617920.8 | CQ36: 8075403.5 | CR36: 8531097.8 | CS36: 8963361.4 | CT36: 9411391.2 | CU36: 16557652 | CV36: 17342926 | CW36: 15773861 | CX36: 16550212 | CY36: 12178798 | CZ36: 12837148 | DA36: 13529220 | DB36: 14265406 | DC36: 15043849 | DD36: 15870043 | DE36: 16748339 | DF36: 17677704 | DG36: 18662887 | DH36: =CM36=BR36 -> TRUE | DI36: =CN36=BS36 -> TRUE | DJ36: =CO36=BT36 -> TRUE | DK36: =CP36=BU36 -> TRUE | DL36: =CQ36=BV36 -> TRUE | DM36: =CR36=BW36 -> TRUE | DN36: =CS36=BX36 -> TRUE | DO36: =CT36=BY36 -> TRUE | ... EB36: =DG36=CL36 -> TRUE | EC36: =SUM(BV36:CL36) -> 2.380193e+08 | ED36: =BR36-F36 -> 0 | EE36: =BS36-G36 -> 0 | EF36: =BT36-H36 -> 0 | EG36: =BU36-I36 -> 47811.781 | EH36: =BV36-J36 -> 94182.25 | EI36: =BW36-K36 -> 90768.033 | EJ36: =BX36-L36 -> 85948.183 | EK36: =BY36-M36 -> 80570.765 | ... EX36: =CL36-Z36 -> -42893.733 | EY36: =SUM(EH36:EX36) -> 24008036
C37: 20 | D37: Доля внебюжетных доходов в общем объеме доходов | E37: % | F37: =IFERROR(F34/F33,0) -> 0.35034784 | G37: =IFERROR(G34/G33,0) -> 0.38082144 | H37: =IFERROR(H34/H33,0) -> 0.39758556 | I37: =IFERROR(I34/I33,0) -> 0.41275068 | J37: =IFERROR(J34/J33,0) -> 0.41768344 | K37: =IFERROR(K34/K33,0) -> 0.42166288 | L37: =IFERROR(L34/L33,0) -> 0.42022297 | M37: =IFERROR(M34/M33,0) -> 0.4181077 | ... Z37: =IFERROR(Z34/Z33,0) -> 0.38233767 | AA37: 0.35034784 | AB37: 0.38082144 | AC37: 0.39758556 | AD37: 0.41275068 | AE37: 0.41768344 | AF37: 0.42166288 | AG37: 0.42022297 | AH37: 0.4181077 | AI37: 0.41561303 | AJ37: 0.41314276 | AK37: 0.41056992 | AL37: 0.40795561 | AM37: 0.40532469 | AN37: 0.4025703 | AO37: 0.39984754 | AP37: 0.39703733 | AQ37: 0.39420397 | AR37: 0.39131159 | AS37: 0.38834701 | AT37: 0.38536134 | AU37: 0.38233767 | AV37: =AA37=F37 -> TRUE | AW37: =AB37=G37 -> TRUE | AX37: =AC37=H37 -> TRUE | AY37: =AD37=I37 -> FALSE | AZ37: =AE37=J37 -> TRUE | BA37: =AF37=K37 -> TRUE | BB37: =AG37=L37 -> TRUE | BC37: =AH37=M37 -> TRUE | ... BP37: =AU37=Z37 -> TRUE | BQ37: =IFERROR(BQ34/BQ33,0) -> 0.40141775 | BR37: =IFERROR(BR34/BR33,0) -> 0.35034784 | BS37: =IFERROR(BS34/BS33,0) -> 0.38082144 | BT37: =IFERROR(BT34/BT33,0) -> 0.39758556 | BU37: =IFERROR(BU34/BU33,0) -> 0.41888754 | BV37: =IFERROR(BV34/BV33,0) -> 0.45048551 | BW37: =IFERROR(BW34/BW33,0) -> 0.49323588 | BX37: =IFERROR(BX34/BX33,0) -> 0.48728378 | ... CL37: =IFERROR(CL34/CL33,0) -> 0.49411536 | CM37: 0.35034784 | CN37: 0.38082144 | CO37: 0.39758556 | CP37: 0.41888754 | CQ37: 0.45048551 | CR37: 0.468198 | CS37: 0.474495 | CT37: 0.47517598 | CU37: 0.36985114 | CV37: 0.36814091 | CW37: 0.40074729 | CX37: 0.40047649 | CY37: 0.4489812 | CZ37: 0.48786199 | DA37: 0.51908336 | DB37: 0.51539187 | DC37: 0.51119547 | DD37: 0.49791652 | DE37: 0.50268677 | DF37: 0.498347 | DG37: 0.49411536 | DH37: =CM37=BR37 -> TRUE | DI37: =CN37=BS37 -> TRUE | DJ37: =CO37=BT37 -> TRUE | DK37: =CP37=BU37 -> TRUE | DL37: =CQ37=BV37 -> TRUE | DM37: =CR37=BW37 -> FALSE | DN37: =CS37=BX37 -> FALSE | DO37: =CT37=BY37 -> FALSE | ... EB37: =DG37=CL37 -> TRUE | EC37: =IFERROR(EC34/EC33,0) -> 0.47387947 | ED37: =IFERROR(ED34/ED33,0) -> 0 | EE37: =IFERROR(EE34/EE33,0) -> 0 | EF37: =IFERROR(EF34/EF33,0) -> 0 | EG37: =IFERROR(EG34/EG33,0) -> 0.81393851 | EH37: =IFERROR(EH34/EH33,0) -> 0.92268258 | EI37: =IFERROR(EI34/EI33,0) -> 0.9676598 | EJ37: =IFERROR(EJ34/EJ33,0) -> 0.96833669 | ... EY37: =IFERROR(EY34/EY33,0) -> 0.76991212
C38: 21 | D38: Доходы (по видам деятельности) | E38: тыс.руб. | F38: =SUM(F39:F41) -> 10491307 | G38: =SUM(G39:G41) -> 12413481 | H38: =SUM(H39:H41) -> 15281575 | I38: =SUM(I39:I41) -> 16541920 | J38: =SUM(J39:J41) -> 17535322 | K38: =SUM(K39:K41) -> 18604050 | L38: =SUM(L39:L41) -> 19471726 | M38: =SUM(M39:M41) -> 20345931 | ... Z38: =SUM(Z39:Z41) -> 37046659 | AA38: 10491307 | AB38: 12413481 | AC38: 15281575 | AD38: 16541920 | AE38: 17535322 | AF38: 18604050 | AG38: 19471726 | AH38: 20345931 | AI38: 21286763 | AJ38: 22270585 | AK38: 23306537 | AL38: 24394115 | AM38: 25534540 | AN38: 26737601 | AO38: 27996442 | AP38: 29322370 | AQ38: 30714438 | AR38: 32179106 | AS38: 33721727 | AT38: 35342301 | AU38: 37046659 | AV38: =AA38=F38 -> TRUE | AW38: =AB38=G38 -> TRUE | AX38: =AC38=H38 -> TRUE | AY38: =AD38=I38 -> TRUE | AZ38: =AE38=J38 -> TRUE | BA38: =AF38=K38 -> TRUE | BB38: =AG38=L38 -> TRUE | BC38: =AH38=M38 -> TRUE | ... BP38: =AU38=Z38 -> TRUE | BQ38: =SUM(BQ39:BQ41) -> 4.4581021e+08 | BR38: =SUM(BR39:BR41) -> 10491307 | BS38: =SUM(BS39:BS41) -> 12413481 | BT38: =SUM(BT39:BT41) -> 15281575 | BU38: =SUM(BU39:BU41) -> 16798888 | BV38: =SUM(BV39:BV41) -> 18753447 | BW38: =SUM(BW39:BW41) -> 22555695 | BX38: =SUM(BX39:BX41) -> 22784137 | ... CL38: =SUM(CL39:CL41) -> 45147510 | CM38: 10491307 | CN38: 12413481 | CO38: 15281575 | CP38: 16798888 | CQ38: 18753447 | CR38: 22555695 | CS38: 22784137 | CT38: 23185804 | CU38: 30617896 | CV38: 31951038 | CW38: 32825788 | CX38: 34847175 | CY38: 32263298 | CZ38: 34612033 | DA38: 34995670 | DB38: 36520678 | DC38: 38080610 | DD38: 39003424 | DE38: 41442268 | DF38: 43244257 | DG38: 45147510 | DH38: =CM38=BR38 -> TRUE | DI38: =CN38=BS38 -> TRUE | DJ38: =CO38=BT38 -> TRUE | DK38: =CP38=BU38 -> TRUE | DL38: =CQ38=BV38 -> TRUE | DM38: =CR38=BW38 -> TRUE | DN38: =CS38=BX38 -> TRUE | DO38: =CT38=BY38 -> TRUE | ... EB38: =DG38=CL38 -> TRUE | EC38: =SUM(EC39:EC41) -> 5.6283073e+08 | ED38: =BR38-F38 -> 0 | EE38: =BS38-G38 -> 0 | EF38: =BT38-H38 -> 0 | EG38: =BU38-I38 -> 256967.63 | EH38: =BV38-J38 -> 1218124.6 | EI38: =BW38-K38 -> 3951645.4 | EJ38: =BX38-L38 -> 3312411.7 | EK38: =BY38-M38 -> 2839873.6 | ... EX38: =CL38-Z38 -> 8100851.1 | EY38: =SUM(EY39:EY41) -> 1.1702052e+08
C39: 22 | D39: Образование | E39: тыс.руб. | F39: ='[10]Данные для переноса'!F37 -> 8984824.4 | G39: ='[10]Данные для переноса'!G37 -> 10045646 | H39: ='[10]Данные для переноса'!H37 -> 11942291 | I39: ='[10]Данные для переноса'!I37 -> 12450116 | J39: ='[10]Данные для переноса'!J37 -> 13279852 | K39: ='[10]Данные для переноса'!K37 -> 14178366 | L39: ='[10]Данные для переноса'!L37 -> 14869021 | M39: ='[10]Данные для переноса'!M37 -> 15559124 | ... Z39: ='[10]Данные для переноса'!Z37 -> 29076364 | AA39: 8984824.4 | AB39: 10045646 | AC39: 11942291 | AD39: 12450116 | AE39: 13279852 | AF39: 14178366 | AG39: 14869021 | AH39: 15559124 | AI39: 16308490 | AJ39: 17093187 | AK39: 17922049 | AL39: 18794253 | AM39: 19710689 | AN39: 20680802 | AO39: 21697375 | AP39: 22771346 | AQ39: 23901377 | AR39: 25093528 | AS39: 26352732 | AT39: 27678551 | AU39: 29076364 | AV39: =AA39=F39 -> TRUE | AW39: =AB39=G39 -> TRUE | AX39: =AC39=H39 -> TRUE | AY39: =AD39=I39 -> TRUE | AZ39: =AE39=J39 -> TRUE | BA39: =AF39=K39 -> TRUE | BB39: =AG39=L39 -> TRUE | BC39: =AH39=M39 -> TRUE | ... BP39: =AU39=Z39 -> TRUE | BQ39: =SUM(J39:Z39) -> 3.449671e+08 | BR39: ='[10]Данные для переноса'!AB37 -> 8984824.4 | BS39: ='[10]Данные для переноса'!AC37 -> 10045646 | BT39: ='[10]Данные для переноса'!AD37 -> 11942291 | BU39: ='[10]Данные для переноса'!AE37 -> 13217205 | BV39: ='[10]Данные для переноса'!AF37 -> 14560925 | BW39: ='[10]Данные для переноса'!AG37 -> 15940940 | BX39: ='[10]Данные для переноса'!AH37 -> 17053902 | BY39: ='[10]Данные для переноса'!AI37 -> 17983197 | ... CL39: ='[10]Данные для переноса'!AV37 -> 32897557 | CM39: 8984824.4 | CN39: 10045646 | CO39: 11942291 | CP39: 13217205 | CQ39: 14560925 | CR39: 15940940 | CS39: 17053902 | CT39: 17983197 | CU39: 18827670 | CV39: 19698717 | CW39: 20615205 | CX39: 21579163 | CY39: 22592107 | CZ39: 23658905 | DA39: 24775829 | DB39: 25975642 | DC39: 27220943 | DD39: 28528405 | DE39: 29914885 | DF39: 31362727 | DG39: 32897557 | DH39: =CM39=BR39 -> TRUE | DI39: =CN39=BS39 -> TRUE | DJ39: =CO39=BT39 -> TRUE | DK39: =CP39=BU39 -> TRUE | DL39: =CQ39=BV39 -> TRUE | DM39: =CR39=BW39 -> TRUE | DN39: =CS39=BX39 -> TRUE | DO39: =CT39=BY39 -> TRUE | ... EB39: =DG39=CL39 -> TRUE | EC39: =SUM(BV39:CL39) -> 3.9318672e+08 | ED39: =BR39-F39 -> 0 | EE39: =BS39-G39 -> 0 | EF39: =BT39-H39 -> 0 | EG39: =BU39-I39 -> 767088.6 | EH39: =BV39-J39 -> 1281073.5 | EI39: =BW39-K39 -> 1762573.6 | EJ39: =BX39-L39 -> 2184880.8 | EK39: =BY39-M39 -> 2424073.7 | ... EX39: =CL39-Z39 -> 3821193.4 | EY39: =SUM(EH39:EX39) -> 48219616
C40: 23 | D40: Наука | E40: тыс.руб. | F40: ='[10]Данные для переноса'!F38 -> 1171701.4 | G40: ='[10]Данные для переноса'!G38 -> 1960113.9 | H40: ='[10]Данные для переноса'!H38 -> 2636185 | I40: ='[10]Данные для переноса'!I38 -> 2854380.7 | J40: ='[10]Данные для переноса'!J38 -> 2934600.2 | K40: ='[10]Данные для переноса'!K38 -> 3027858.2 | L40: ='[10]Данные для переноса'!L38 -> 3148972.5 | M40: ='[10]Данные для переноса'!M38 -> 3274931.4 | ... Z40: ='[10]Данные для переноса'!Z38 -> 5453001.5 | AA40: 1171701.4 | AB40: 1960113.9 | AC40: 2636185 | AD40: 2854380.7 | AE40: 2934600.2 | AF40: 3027858.2 | AG40: 3148972.5 | AH40: 3274931.4 | AI40: 3405928.7 | AJ40: 3542165.8 | AK40: 3683852.5 | AL40: 3831206.6 | AM40: 3984454.8 | AN40: 4143833 | AO40: 4309586.3 | AP40: 4481969.8 | AQ40: 4661248.6 | AR40: 4847698.5 | AS40: 5041606.5 | AT40: 5243270.7 | AU40: 5453001.5 | AV40: =AA40=F40 -> TRUE | AW40: =AB40=G40 -> TRUE | AX40: =AC40=H40 -> TRUE | AY40: =AD40=I40 -> TRUE | AZ40: =AE40=J40 -> TRUE | BA40: =AF40=K40 -> TRUE | BB40: =AG40=L40 -> TRUE | BC40: =AH40=M40 -> TRUE | ... BP40: =AU40=Z40 -> TRUE | BQ40: =SUM(J40:Z40) -> 69016186 | BR40: ='[10]Данные для переноса'!AB38 -> 1171701.4 | BS40: ='[10]Данные для переноса'!AC38 -> 1960113.9 | BT40: ='[10]Данные для переноса'!AD38 -> 2636185 | BU40: ='[10]Данные для переноса'!AE38 -> 2862034 | BV40: ='[10]Данные для переноса'!AF38 -> 3434058.3 | BW40: ='[10]Данные для переноса'!AG38 -> 3535160.1 | BX40: ='[10]Данные для переноса'!AH38 -> 3711677.7 | BY40: ='[10]Данные для переноса'!AI38 -> 3847520.1 | ... CL40: ='[10]Данные для переноса'!AV38 -> 6167230.9 | CM40: 1171701.4 | CN40: 1960113.9 | CO40: 2636185 | CP40: 2862034 | CQ40: 3434058.3 | CR40: 3535160.1 | CS40: 3711677.7 | CT40: 3847520.1 | CU40: 3988543.7 | CV40: 4134950.7 | CW40: 4286951.3 | CX40: 4444763.9 | CY40: 4608615.8 | CZ40: 4778742.9 | DA40: 4955390.8 | DB40: 5138814.6 | DC40: 5329279.5 | DD40: 5527061.2 | DE40: 5732446.4 | DF40: 5945733 | DG40: 6167230.9 | DH40: =CM40=BR40 -> TRUE | DI40: =CN40=BS40 -> TRUE | DJ40: =CO40=BT40 -> TRUE | DK40: =CP40=BU40 -> TRUE | DL40: =CQ40=BV40 -> TRUE | DM40: =CR40=BW40 -> TRUE | DN40: =CS40=BX40 -> TRUE | DO40: =CT40=BY40 -> TRUE | ... EB40: =DG40=CL40 -> TRUE | EC40: =SUM(BV40:CL40) -> 79566941 | ED40: =BR40-F40 -> 0 | EE40: =BS40-G40 -> 0 | EF40: =BT40-H40 -> 0 | EG40: =BU40-I40 -> 7653.3831 | EH40: =BV40-J40 -> 499458.08 | EI40: =BW40-K40 -> 507301.91 | EJ40: =BX40-L40 -> 562705.22 | EK40: =BY40-M40 -> 572588.71 | ... EX40: =CL40-Z40 -> 714229.39 | EY40: =SUM(EH40:EX40) -> 10550755
C41: 24 | D41: Прочая деятельность | E41: тыс.руб. | F41: ='[10]Данные для переноса'!F39 -> 334781.22 | G41: ='[10]Данные для переноса'!G39 -> 407720.54 | H41: ='[10]Данные для переноса'!H39 -> 703099.42 | I41: ='[10]Данные для переноса'!I39 -> 1237423.6 | J41: ='[10]Данные для переноса'!J39 -> 1320870.3 | K41: ='[10]Данные для переноса'!K39 -> 1397825.2 | L41: ='[10]Данные для переноса'!L39 -> 1453732.3 | M41: ='[10]Данные для переноса'!M39 -> 1511875.6 | ... Z41: ='[10]Данные для переноса'!Z39 -> 2517293.7 | AA41: 334781.22 | AB41: 407720.54 | AC41: 703099.42 | AD41: 1237423.6 | AE41: 1320870.3 | AF41: 1397825.2 | AG41: 1453732.3 | AH41: 1511875.6 | AI41: 1572344.8 | AJ41: 1635232.6 | AK41: 1700636 | AL41: 1768655.5 | AM41: 1839395.8 | AN41: 1912966.7 | AO41: 1989480.5 | AP41: 2069054.7 | AQ41: 2151811.8 | AR41: 2237879.2 | AS41: 2327389.3 | AT41: 2420479.7 | AU41: 2517293.7 | AV41: =AA41=F41 -> TRUE | AW41: =AB41=G41 -> TRUE | AX41: =AC41=H41 -> TRUE | AY41: =AD41=I41 -> TRUE | AZ41: =AE41=J41 -> TRUE | BA41: =AF41=K41 -> TRUE | BB41: =AG41=L41 -> TRUE | BC41: =AH41=M41 -> TRUE | ... BP41: =AU41=Z41 -> TRUE | BQ41: =SUM(J41:Z41) -> 31826924 | BR41: ='[10]Данные для переноса'!AB39 -> 334781.22 | BS41: ='[10]Данные для переноса'!AC39 -> 407720.54 | BT41: ='[10]Данные для переноса'!AD39 -> 703099.42 | BU41: ='[10]Данные для переноса'!AE39 -> 719649.22 | BV41: ='[10]Данные для переноса'!AF39 -> 758463.38 | BW41: ='[10]Данные для переноса'!AG39 -> 3079595.1 | BX41: ='[10]Данные для переноса'!AH39 -> 2018558 | BY41: ='[10]Данные для переноса'!AI39 -> 1355086.8 | ... CL41: ='[10]Данные для переноса'!AV39 -> 6082721.9 | CM41: 334781.22 | CN41: 407720.54 | CO41: 703099.42 | CP41: 719649.22 | CQ41: 758463.38 | CR41: 3079595.1 | CS41: 2018558 | CT41: 1355086.8 | CU41: 7801682 | CV41: 8117370.7 | CW41: 7923631.1 | CX41: 8823248.6 | CY41: 5062575.3 | CZ41: 6174384.3 | DA41: 5264449.6 | DB41: 5406221.6 | DC41: 5530387.5 | DD41: 4947957.2 | DE41: 5794936.1 | DF41: 5935797.8 | DG41: 6082721.9 | DH41: =CM41=BR41 -> TRUE | DI41: =CN41=BS41 -> TRUE | DJ41: =CO41=BT41 -> TRUE | DK41: =CP41=BU41 -> TRUE | DL41: =CQ41=BV41 -> TRUE | DM41: =CR41=BW41 -> TRUE | DN41: =CS41=BX41 -> TRUE | DO41: =CT41=BY41 -> TRUE | ... EB41: =DG41=CL41 -> TRUE | EC41: =SUM(BV41:CL41) -> 90077067 | ED41: =BR41-F41 -> 0 | EE41: =BS41-G41 -> 0 | EF41: =BT41-H41 -> 0 | EG41: =BU41-I41 -> -517774.35 | EH41: =BV41-J41 -> -562406.89 | EI41: =BW41-K41 -> 1681769.9 | EJ41: =BX41-L41 -> 564825.77 | EK41: =BY41-M41 -> -156788.83 | ... EX41: =CL41-Z41 -> 3565428.3 | EY41: =SUM(EH41:EX41) -> 58250144
C42: 25 | D42: Расходы, включая инвестиционные расходы | F42: =F43+F50+F57 -> 10600271 | G42: =G43+G50+G57 -> 12777047 | H42: =H43+H50+H57 -> 15425461 | I42: =I43+I50+I57 -> 16298694 | J42: =J43+J50+J57 -> 17245393 | K42: =K43+K50+K57 -> 18214725 | L42: =L43+L50+L57 -> 18974248 | M42: =M43+M50+M57 -> 19766165 | ... Z42: =Z43+Z50+Z57 -> 34075697 | AA42: 10600271 | AB42: 12777047 | AC42: 15425461 | AD42: 16298694 | AE42: 17245393 | AF42: 18214725 | AG42: 18974248 | AH42: 19766165 | AI42: 20596758 | AJ42: 21464658 | AK42: 22371686 | AL42: 23319765 | AM42: 24310923 | AN42: 25347318 | AO42: 26431209 | AP42: 27564985 | AQ42: 28751169 | AR42: 29992429 | AS42: 31291585 | AT42: 32651621 | AU42: 34075697 | AV42: =AA42=F42 -> TRUE | AW42: =AB42=G42 -> TRUE | AX42: =AC42=H42 -> TRUE | AY42: =AD42=I42 -> TRUE | AZ42: =AE42=J42 -> TRUE | BA42: =AF42=K42 -> TRUE | BB42: =AG42=L42 -> TRUE | BC42: =AH42=M42 -> TRUE | ... BP42: =AU42=Z42 -> TRUE | BQ42: =BQ43+BQ50+BQ57 -> 4.2237033e+08 | BR42: =BR43+BR50+BR57 -> 10600271 | BS42: =BS43+BS50+BS57 -> 12777047 | BT42: =BT43+BT50+BT57 -> 15425461 | BU42: =BU43+BU50+BU57 -> 16701684 | BV42: =BV43+BV50+BV57 -> 18188618 | BW42: =BW43+BW50+BW57 -> 20432080 | BX42: =BX43+BX50+BX57 -> 20790007 | ... CL42: =CL43+CL50+CL57 -> 37817448 | CM42: 10600271 | CN42: 12777047 | CO42: 15425461 | CP42: 16698245 | CQ42: 17970359 | CR42: 20216948 | CS42: 20558942 | CT42: 20962697 | CU42: 28517626 | CV42: 29728946 | CW42: 29534190 | CX42: 31087345 | CY42: 28316983 | CZ42: 29072064 | DA42: 29108695 | DB42: 30389604 | DC42: 31722985 | DD42: 33064685 | DE42: 34577648 | DF42: 36103463 | DG42: 37706735 | DH42: =CM42=BR42 -> TRUE | DI42: =CN42=BS42 -> TRUE | DJ42: =CO42=BT42 -> TRUE | DK42: =CP42=BU42 -> FALSE | DL42: =CQ42=BV42 -> FALSE | DM42: =CR42=BW42 -> FALSE | DN42: =CS42=BX42 -> FALSE | DO42: =CT42=BY42 -> FALSE | ... EB42: =DG42=CL42 -> FALSE | EC42: =EC43+EC50+EC57 -> 4.9182048e+08 | ED42: =BR42-F42 -> 0 | EE42: =BS42-G42 -> 0 | EF42: =BT42-H42 -> 0 | EG42: =BU42-I42 -> 402990.85 | EH42: =BV42-J42 -> 943224.4 | EI42: =BW42-K42 -> 2217355.4 | EJ42: =BX42-L42 -> 1815759.9 | EK42: =BY42-M42 -> 1423654.4 | ... EX42: =CL42-Z42 -> 3741751.2 | EY42: =EY43+EY50+EY57 -> 69450147
C43: 26 | D43: 1. Условно-переменные затраты | E43: тыс.руб. | F43: =SUM(F44:F49) -> 4951617.5 | G43: =SUM(G44:G49) -> 6055653 | H43: =SUM(H44:H49) -> 7717130.8 | I43: =SUM(I44:I49) -> 8437984 | J43: =SUM(J44:J49) -> 9016131.3 | K43: =SUM(K44:K49) -> 9608462.5 | L43: =SUM(L44:L49) -> 9991186.5 | M43: =SUM(M44:M49) -> 10387854 | ... Z43: =SUM(Z44:Z49) -> 17297516 | AA43: 4951617.5 | AB43: 6055653 | AC43: 7717130.8 | AD43: 8437984 | AE43: 9016131.3 | AF43: 9608462.5 | AG43: 9991186.5 | AH43: 10387854 | AI43: 10803405 | AJ43: 11235581 | AK43: 11685047 | AL43: 12152495 | AM43: 12638645 | AN43: 13144245 | AO43: 13670074 | AP43: 14216940 | AQ43: 14785686 | AR43: 15377188 | AS43: 15992356 | AT43: 16632137 | AU43: 17297516 | AV43: =AA43=F43 -> TRUE | AW43: =AB43=G43 -> TRUE | AX43: =AC43=H43 -> TRUE | AY43: =AD43=I43 -> TRUE | AZ43: =AE43=J43 -> TRUE | BA43: =AF43=K43 -> TRUE | BB43: =AG43=L43 -> TRUE | BC43: =AH43=M43 -> TRUE | ... BP43: =AU43=Z43 -> TRUE | BQ43: =SUM(J43:Z43) -> 2.1863495e+08 | BR43: =SUM(BR44:BR49) -> 4951617.5 | BS43: =SUM(BS44:BS49) -> 6055653 | BT43: =SUM(BT44:BT49) -> 7717130.8 | BU43: =SUM(BU44:BU49) -> 8845102 | BV43: =SUM(BV44:BV49) -> 9973992.5 | BW43: =SUM(BW44:BW49) -> 10694734 | BX43: =SUM(BX44:BX49) -> 11223811 | BY43: =SUM(BY44:BY49) -> 11701892 | ... CL43: =SUM(CL44:CL49) -> 19759102 | CM43: 4951617.5 | CN43: 6055653 | CO43: 7717130.8 | CP43: 8845102 | CQ43: 9973992.5 | CR43: 10694734 | CS43: 11223811 | CT43: 11701892 | CU43: 12181994 | CV43: 12681020 | CW43: 13201135 | CX43: 13743251 | CY43: 14308318 | CZ43: 14894287 | DA43: 15504503 | DB43: 16151359 | DC43: 16817276 | DD43: 17507073 | DE43: 18229701 | DF43: 18976502 | DG43: 19759102 | DH43: =CM43=BR43 -> TRUE | DI43: =CN43=BS43 -> TRUE | DJ43: =CO43=BT43 -> TRUE | DK43: =CP43=BU43 -> TRUE | DL43: =CQ43=BV43 -> TRUE | DM43: =CR43=BW43 -> TRUE | DN43: =CS43=BX43 -> TRUE | DO43: =CT43=BY43 -> TRUE | ... EB43: =DG43=CL43 -> TRUE | EC43: =SUM(BV43:CL43) -> 2.4754995e+08 | ED43: =BR43-F43 -> 0 | EE43: =BS43-G43 -> 0 | EF43: =BT43-H43 -> 0 | EG43: =BU43-I43 -> 407117.95 | EH43: =BV43-J43 -> 957861.17 | EI43: =BW43-K43 -> 1086271.1 | EJ43: =BX43-L43 -> 1232624.4 | EK43: =BY43-M43 -> 1314038.1 | ... EX43: =CL43-Z43 -> 2461585.5 | EY43: =SUM(EH43:EX43) -> 28915002
C44: 27 | D44: ФОТ образование | E44: тыс.руб. | F44: ='[10]Данные для переноса'!F42 -> 3174392.8 | G44: ='[10]Данные для переноса'!G42 -> 3740912.4 | H44: ='[10]Данные для переноса'!H42 -> 4371873.1 | I44: ='[10]Данные для переноса'!I42 -> 4823281.4 | J44: ='[10]Данные для переноса'!J42 -> 5284722.5 | K44: ='[10]Данные для переноса'!K42 -> 5747976.1 | L44: ='[10]Данные для переноса'!L42 -> 5976296.8 | M44: ='[10]Данные для переноса'!M42 -> 6212438.5 | ... Z44: ='[10]Данные для переноса'!Z42 -> 10344167 | AA44: 3174392.8 | AB44: 3740912.4 | AC44: 4371873.1 | AD44: 4823281.4 | AE44: 5284722.5 | AF44: 5747976.1 | AG44: 5976296.8 | AH44: 6212438.5 | AI44: 6460936 | AJ44: 6719373.5 | AK44: 6988148.4 | AL44: 7267674.4 | AM44: 7558381.3 | AN44: 7860716.6 | AO44: 8175145.2 | AP44: 8502151.1 | AQ44: 8842237.1 | AR44: 9195926.6 | AS44: 9563763.6 | AT44: 9946314.2 | AU44: 10344167 | AV44: =AA44=F44 -> TRUE | AW44: =AB44=G44 -> TRUE | AX44: =AC44=H44 -> TRUE | AY44: =AD44=I44 -> TRUE | AZ44: =AE44=J44 -> TRUE | BA44: =AF44=K44 -> TRUE | BB44: =AG44=L44 -> TRUE | BC44: =AH44=M44 -> TRUE | ... BP44: =AU44=Z44 -> TRUE | BQ44: =SUM(J44:Z44) -> 1.3064637e+08 | BR44: ='[10]Данные для переноса'!AB42 -> 3174392.8 | BS44: ='[10]Данные для переноса'!AC42 -> 3740912.4 | BT44: ='[10]Данные для переноса'!AD42 -> 4371873.1 | BU44: ='[10]Данные для переноса'!AE42 -> 5223358.3 | BV44: ='[10]Данные для переноса'!AF42 -> 5783082.3 | BW44: ='[10]Данные для переноса'!AG42 -> 6367529.4 | BX44: ='[10]Данные для переноса'!AH42 -> 6691232.4 | BY44: ='[10]Данные для переноса'!AI42 -> 6999695 | ... CL44: ='[10]Данные для переноса'!AV42 -> 12148661 | CM44: 3174392.8 | CN44: 3740912.4 | CO44: 4371873.1 | CP44: 5223358.3 | CQ44: 5783082.3 | CR44: 6367529.4 | CS44: 6691232.4 | CT44: 6999695 | CU44: 7303519.2 | CV44: 7619450.2 | CW44: 7949385.9 | CX44: 8293957.8 | CY44: 8653826.2 | CZ44: 9026641.1 | DA44: 9415435 | DB44: 9832273.1 | DC44: 10259238 | DD44: 10700798 | DE44: 11165536 | DF44: 11644414 | DG44: 12148661 | DH44: =CM44=BR44 -> TRUE | DI44: =CN44=BS44 -> TRUE | DJ44: =CO44=BT44 -> TRUE | DK44: =CP44=BU44 -> TRUE | DL44: =CQ44=BV44 -> TRUE | DM44: =CR44=BW44 -> TRUE | DN44: =CS44=BX44 -> TRUE | DO44: =CT44=BY44 -> TRUE | ... EB44: =DG44=CL44 -> TRUE | EC44: =SUM(BV44:CL44) -> 1.4985468e+08 | ED44: =BR44-F44 -> 0 | EE44: =BS44-G44 -> 0 | EF44: =BT44-H44 -> 0 | EG44: =BU44-I44 -> 400076.84 | EH44: =BV44-J44 -> 498359.74 | EI44: =BW44-K44 -> 619553.31 | EJ44: =BX44-L44 -> 714935.6 | EK44: =BY44-M44 -> 787256.52 | ... EX44: =CL44-Z44 -> 1804494.4 | EY44: =SUM(EH44:EX44) -> 19208307
C45: 28 | D45: ФОТ наука | E45: тыс.руб. | F45: ='[10]Данные для переноса'!F43 -> 954936.66 | G45: ='[10]Данные для переноса'!G43 -> 1347578.3 | H45: ='[10]Данные для переноса'!H43 -> 2148490.8 | I45: ='[10]Данные для переноса'!I43 -> 2169329.3 | J45: ='[10]Данные для переноса'!J43 -> 2230296.2 | K45: ='[10]Данные для переноса'!K43 -> 2301172.2 | L45: ='[10]Данные для переноса'!L43 -> 2393219.1 | M45: ='[10]Данные для переноса'!M43 -> 2488947.9 | ... Z45: ='[10]Данные для переноса'!Z43 -> 4144281.2 | AA45: 954936.66 | AB45: 1347578.3 | AC45: 2148490.8 | AD45: 2169329.3 | AE45: 2230296.2 | AF45: 2301172.2 | AG45: 2393219.1 | AH45: 2488947.9 | AI45: 2588505.8 | AJ45: 2692046 | AK45: 2799727.9 | AL45: 2911717 | AM45: 3028185.7 | AN45: 3149313.1 | AO45: 3275285.6 | AP45: 3406297 | AQ45: 3542548.9 | AR45: 3684250.9 | AS45: 3831620.9 | AT45: 3984885.7 | AU45: 4144281.2 | AV45: =AA45=F45 -> TRUE | AW45: =AB45=G45 -> TRUE | AX45: =AC45=H45 -> TRUE | AY45: =AD45=I45 -> TRUE | AZ45: =AE45=J45 -> TRUE | BA45: =AF45=K45 -> TRUE | BB45: =AG45=L45 -> TRUE | BC45: =AH45=M45 -> TRUE | ... BP45: =AU45=Z45 -> TRUE | BQ45: =SUM(J45:Z45) -> 52452301 | BR45: ='[10]Данные для переноса'!AB43 -> 954936.66 | BS45: ='[10]Данные для переноса'!AC43 -> 1347578.3 | BT45: ='[10]Данные для переноса'!AD43 -> 2148490.8 | BU45: ='[10]Данные для переноса'!AE43 -> 2175145.9 | BV45: ='[10]Данные для переноса'!AF43 -> 2609884.3 | BW45: ='[10]Данные для переноса'!AG43 -> 2686721.7 | BX45: ='[10]Данные для переноса'!AH43 -> 2820875.1 | BY45: ='[10]Данные для переноса'!AI43 -> 2924115.3 | ... CL45: ='[10]Данные для переноса'!AV43 -> 4687095.5 | CM45: 954936.66 | CN45: 1347578.3 | CO45: 2148490.8 | CP45: 2175145.9 | CQ45: 2609884.3 | CR45: 2686721.7 | CS45: 2820875.1 | CT45: 2924115.3 | CU45: 3031293.2 | CV45: 3142562.5 | CW45: 3258083 | CX45: 3378020.6 | CY45: 3502548 | CZ45: 3631844.6 | DA45: 3766097 | DB45: 3905499.1 | DC45: 4050252.4 | DD45: 4200566.5 | DE45: 4356659.2 | DF45: 4518757.1 | DG45: 4687095.5 | DH45: =CM45=BR45 -> TRUE | DI45: =CN45=BS45 -> TRUE | DJ45: =CO45=BT45 -> TRUE | DK45: =CP45=BU45 -> TRUE | DL45: =CQ45=BV45 -> TRUE | DM45: =CR45=BW45 -> TRUE | DN45: =CS45=BX45 -> TRUE | DO45: =CT45=BY45 -> TRUE | ... EB45: =DG45=CL45 -> TRUE | EC45: =SUM(BV45:CL45) -> 60470875 | ED45: =BR45-F45 -> 0 | EE45: =BS45-G45 -> 0 | EF45: =BT45-H45 -> 0 | EG45: =BU45-I45 -> 5816.5711 | EH45: =BV45-J45 -> 379588.14 | EI45: =BW45-K45 -> 385549.45 | EJ45: =BX45-L45 -> 427655.97 | EK45: =BY45-M45 -> 435167.42 | ... EX45: =CL45-Z45 -> 542814.34 | EY45: =SUM(EH45:EX45) -> 8018574.1
C46: 29 | D46: Материальные запасы | E46: тыс.руб. | F46: ='[10]Данные для переноса'!F44 -> 110468.26 | G46: ='[10]Данные для переноса'!G44 -> 134774.98 | H46: ='[10]Данные для переноса'!H44 -> 270177.91 | I46: ='[10]Данные для переноса'!I44 -> 446702.2 | J46: ='[10]Данные для переноса'!J44 -> 464871.55 | K46: ='[10]Данные для переноса'!K44 -> 483312.27 | L46: ='[10]Данные для переноса'!L44 -> 502628.64 | M46: ='[10]Данные для переноса'!M44 -> 522664.08 | ... Z46: ='[10]Данные для переноса'!Z44 -> 871249.79 | AA46: 110468.26 | AB46: 134774.98 | AC46: 270177.91 | AD46: 446702.2 | AE46: 464871.55 | AF46: 483312.27 | AG46: 502628.64 | AH46: 522664.08 | AI46: 543607.3 | AJ46: 565391.23 | AK46: 588049.76 | AL46: 611618.12 | AM46: 636133.01 | AN46: 661632.58 | AO46: 688156.57 | AP46: 715746.3 | AQ46: 744444.8 | AR46: 774296.84 | AS46: 805349.02 | AT46: 837649.85 | AU46: 871249.79 | AV46: =AA46=F46 -> TRUE | AW46: =AB46=G46 -> TRUE | AX46: =AC46=H46 -> TRUE | AY46: =AD46=I46 -> TRUE | AZ46: =AE46=J46 -> TRUE | BA46: =AF46=K46 -> TRUE | BB46: =AG46=L46 -> TRUE | BC46: =AH46=M46 -> TRUE | ... BP46: =AU46=Z46 -> TRUE | BQ46: =SUM(J46:Z46) -> 11016802 | BR46: ='[10]Данные для переноса'!AB44 -> 110468.26 | BS46: ='[10]Данные для переноса'!AC44 -> 134774.98 | BT46: ='[10]Данные для переноса'!AD44 -> 270177.91 | BU46: ='[10]Данные для переноса'!AE44 -> 447391 | BV46: ='[10]Данные для переноса'!AF44 -> 509822.78 | BW46: ='[10]Данные для переноса'!AG44 -> 528969.45 | BX46: ='[10]Данные для переноса'!AH44 -> 553272.11 | BY46: ='[10]Данные для переноса'!AI44 -> 574197.07 | ... CL46: ='[10]Данные для переноса'!AV44 -> 935530.43 | CM46: 110468.26 | CN46: 134774.98 | CO46: 270177.91 | CP46: 447391 | CQ46: 509822.78 | CR46: 528969.45 | CS46: 553272.11 | CT46: 574197.07 | CU46: 596042.65 | CV46: 618741.87 | CW46: 642328.65 | CX46: 666838.29 | CY46: 692307.5 | CZ46: 718774.48 | DA46: 746278.97 | DB46: 774862.33 | DC46: 804567.58 | DD46: 835439.48 | DE46: 867524.62 | DF46: 900871.45 | DG46: 935530.43 | DH46: =CM46=BR46 -> TRUE | DI46: =CN46=BS46 -> TRUE | DJ46: =CO46=BT46 -> TRUE | DK46: =CP46=BU46 -> TRUE | DL46: =CQ46=BV46 -> TRUE | DM46: =CR46=BW46 -> TRUE | DN46: =CS46=BX46 -> TRUE | DO46: =CT46=BY46 -> TRUE | ... EB46: =DG46=CL46 -> TRUE | EC46: =SUM(BV46:CL46) -> 11966370 | ED46: =BR46-F46 -> 0 | EE46: =BS46-G46 -> 0 | EF46: =BT46-H46 -> 0 | EG46: =BU46-I46 -> 688.80447 | EH46: =BV46-J46 -> 44951.227 | EI46: =BW46-K46 -> 45657.172 | EJ46: =BX46-L46 -> 50643.47 | EK46: =BY46-M46 -> 51532.984 | ... EX46: =CL46-Z46 -> 64280.645 | EY46: =SUM(EH46:EX46) -> 949567.99
C47: 30 | D47: Нематериальные активы | E47: тыс.руб. | F47: ='[10]Данные для переноса'!F45 -> 0 | G47: ='[10]Данные для переноса'!G45 -> 0 | H47: ='[10]Данные для переноса'!H45 -> 0 | I47: ='[10]Данные для переноса'!I45 -> 0 | J47: ='[10]Данные для переноса'!J45 -> 0 | K47: ='[10]Данные для переноса'!K45 -> 0 | L47: ='[10]Данные для переноса'!L45 -> 0 | M47: ='[10]Данные для переноса'!M45 -> 0 | ... Z47: ='[10]Данные для переноса'!Z45 -> 0 | AA47: 0 | AB47: 0 | AC47: 0 | AD47: 0 | AE47: 0 | AF47: 0 | AG47: 0 | AH47: 0 | AI47: 0 | AJ47: 0 | AK47: 0 | AL47: 0 | AM47: 0 | AN47: 0 | AO47: 0 | AP47: 0 | AQ47: 0 | AR47: 0 | AS47: 0 | AT47: 0 | AU47: 0 | AV47: =AA47=F47 -> TRUE | AW47: =AB47=G47 -> TRUE | AX47: =AC47=H47 -> TRUE | AY47: =AD47=I47 -> TRUE | AZ47: =AE47=J47 -> TRUE | BA47: =AF47=K47 -> TRUE | BB47: =AG47=L47 -> TRUE | BC47: =AH47=M47 -> TRUE | ... BP47: =AU47=Z47 -> TRUE | BQ47: =SUM(J47:Z47) -> 0 | BR47: ='[10]Данные для переноса'!AB45 -> 0 | BS47: ='[10]Данные для переноса'!AC45 -> 0 | BT47: ='[10]Данные для переноса'!AD45 -> 0 | BU47: ='[10]Данные для переноса'!AE45 -> 0 | BV47: ='[10]Данные для переноса'!AF45 -> 0 | BW47: ='[10]Данные для переноса'!AG45 -> 0 | BX47: ='[10]Данные для переноса'!AH45 -> 0 | BY47: ='[10]Данные для переноса'!AI45 -> 0 | ... CL47: ='[10]Данные для переноса'!AV45 -> 0 | CM47: 0 | CN47: 0 | CO47: 0 | CP47: 0 | CQ47: 0 | CR47: 0 | CS47: 0 | CT47: 0 | CU47: 0 | CV47: 0 | CW47: 0 | CX47: 0 | CY47: 0 | CZ47: 0 | DA47: 0 | DB47: 0 | DC47: 0 | DD47: 0 | DE47: 0 | DF47: 0 | DG47: 0 | DH47: =CM47=BR47 -> TRUE | DI47: =CN47=BS47 -> TRUE | DJ47: =CO47=BT47 -> TRUE | DK47: =CP47=BU47 -> TRUE | DL47: =CQ47=BV47 -> TRUE | DM47: =CR47=BW47 -> TRUE | DN47: =CS47=BX47 -> TRUE | DO47: =CT47=BY47 -> TRUE | ... EB47: =DG47=CL47 -> TRUE | EC47: =SUM(BV47:CL47) -> 0 | ED47: =BR47-F47 -> 0 | EE47: =BS47-G47 -> 0 | EF47: =BT47-H47 -> 0 | EG47: =BU47-I47 -> 0 | EH47: =BV47-J47 -> 0 | EI47: =BW47-K47 -> 0 | EJ47: =BX47-L47 -> 0 | EK47: =BY47-M47 -> 0 | ... EX47: =CL47-Z47 -> 0 | EY47: =SUM(EH47:EX47) -> 0
C48: 31 | D48: Социальное обеспечение (включая стипендию) | E48: тыс.руб. | F48: ='[10]Данные для переноса'!F46 -> 639760.13 | G48: ='[10]Данные для переноса'!G46 -> 700275.63 | H48: ='[10]Данные для переноса'!H46 -> 764463.58 | I48: ='[10]Данные для переноса'!I46 -> 798864.44 | J48: ='[10]Данные для переноса'!J46 -> 830819.02 | K48: ='[10]Данные для переноса'!K46 -> 864051.78 | L48: ='[10]Данные для переноса'!L46 -> 898613.85 | M48: ='[10]Данные для переноса'!M46 -> 934558.4 | ... Z48: ='[10]Данные для переноса'!Z46 -> 1556108.4 | AA48: 639760.13 | AB48: 700275.63 | AC48: 764463.58 | AD48: 798864.44 | AE48: 830819.02 | AF48: 864051.78 | AG48: 898613.85 | AH48: 934558.4 | AI48: 971940.74 | AJ48: 1010818.4 | AK48: 1051251.1 | AL48: 1093301.1 | AM48: 1137033.2 | AN48: 1182514.5 | AO48: 1229815.1 | AP48: 1279007.7 | AQ48: 1330168 | AR48: 1383374.7 | AS48: 1438709.7 | AT48: 1496258.1 | AU48: 1556108.4 | AV48: =AA48=F48 -> TRUE | AW48: =AB48=G48 -> TRUE | AX48: =AC48=H48 -> TRUE | AY48: =AD48=I48 -> TRUE | AZ48: =AE48=J48 -> TRUE | BA48: =AF48=K48 -> TRUE | BB48: =AG48=L48 -> TRUE | BC48: =AH48=M48 -> TRUE | ... BP48: =AU48=Z48 -> TRUE | BQ48: =SUM(J48:Z48) -> 19688344 | BR48: ='[10]Данные для переноса'!AB46 -> 639760.13 | BS48: ='[10]Данные для переноса'!AC46 -> 700275.63 | BT48: ='[10]Данные для переноса'!AD46 -> 764463.58 | BU48: ='[10]Данные для переноса'!AE46 -> 798864.44 | BV48: ='[10]Данные для переноса'!AF46 -> 830819.02 | BW48: ='[10]Данные для переноса'!AG46 -> 864051.78 | BX48: ='[10]Данные для переноса'!AH46 -> 898613.85 | BY48: ='[10]Данные для переноса'!AI46 -> 934558.4 | ... CL48: ='[10]Данные для переноса'!AV46 -> 1556108.4 | CM48: 639760.13 | CN48: 700275.63 | CO48: 764463.58 | CP48: 798864.44 | CQ48: 830819.02 | CR48: 864051.78 | CS48: 898613.85 | CT48: 934558.4 | CU48: 971940.74 | CV48: 1010818.4 | CW48: 1051251.1 | CX48: 1093301.1 | CY48: 1137033.2 | CZ48: 1182514.5 | DA48: 1229815.1 | DB48: 1279007.7 | DC48: 1330168 | DD48: 1383374.7 | DE48: 1438709.7 | DF48: 1496258.1 | DG48: 1556108.4 | DH48: =CM48=BR48 -> TRUE | DI48: =CN48=BS48 -> TRUE | DJ48: =CO48=BT48 -> TRUE | DK48: =CP48=BU48 -> TRUE | DL48: =CQ48=BV48 -> TRUE | DM48: =CR48=BW48 -> TRUE | DN48: =CS48=BX48 -> TRUE | DO48: =CT48=BY48 -> TRUE | ... EB48: =DG48=CL48 -> TRUE | EC48: =SUM(BV48:CL48) -> 19688344 | ED48: =BR48-F48 -> 0 | EE48: =BS48-G48 -> 0 | EF48: =BT48-H48 -> 0 | EG48: =BU48-I48 -> 0 | EH48: =BV48-J48 -> 0 | EI48: =BW48-K48 -> 0 | EJ48: =BX48-L48 -> 0 | EK48: =BY48-M48 -> 0 | ... EX48: =CL48-Z48 -> 0 | EY48: =SUM(EH48:EX48) -> 0
C49: 32 | D49: Прочие прямые расходы (включая соисполнителей) | E49: тыс.руб. | F49: ='[10]Данные для переноса'!F47 -> 72059.637 | G49: ='[10]Данные для переноса'!G47 -> 132111.68 | H49: ='[10]Данные для переноса'!H47 -> 162125.38 | I49: ='[10]Данные для переноса'!I47 -> 199806.65 | J49: ='[10]Данные для переноса'!J47 -> 205422.02 | K49: ='[10]Данные для переноса'!K47 -> 211950.07 | L49: ='[10]Данные для переноса'!L47 -> 220428.08 | M49: ='[10]Данные для переноса'!M47 -> 229245.2 | ... Z49: ='[10]Данные для переноса'!Z47 -> 381710.11 | AA49: 72059.637 | AB49: 132111.68 | AC49: 162125.38 | AD49: 199806.65 | AE49: 205422.02 | AF49: 211950.07 | AG49: 220428.08 | AH49: 229245.2 | AI49: 238415.01 | AJ49: 247951.61 | AK49: 257869.67 | AL49: 268184.46 | AM49: 278911.84 | AN49: 290068.31 | AO49: 301671.04 | AP49: 313737.88 | AQ49: 326287.4 | AR49: 339338.9 | AS49: 352912.45 | AT49: 367028.95 | AU49: 381710.11 | AV49: =AA49=F49 -> TRUE | AW49: =AB49=G49 -> TRUE | AX49: =AC49=H49 -> TRUE | AY49: =AD49=I49 -> TRUE | AZ49: =AE49=J49 -> TRUE | BA49: =AF49=K49 -> TRUE | BB49: =AG49=L49 -> TRUE | BC49: =AH49=M49 -> TRUE | ... BP49: =AU49=Z49 -> TRUE | BQ49: =SUM(J49:Z49) -> 4831133 | BR49: ='[10]Данные для переноса'!AB47 -> 72059.637 | BS49: ='[10]Данные для переноса'!AC47 -> 132111.68 | BT49: ='[10]Данные для переноса'!AD47 -> 162125.38 | BU49: ='[10]Данные для переноса'!AE47 -> 200342.38 | BV49: ='[10]Данные для переноса'!AF47 -> 240384.08 | BW49: ='[10]Данные для переноса'!AG47 -> 247461.21 | BX49: ='[10]Данные для переноса'!AH47 -> 259817.44 | BY49: ='[10]Данные для переноса'!AI47 -> 269326.41 | ... CL49: ='[10]Данные для переноса'!AV47 -> 431706.17 | CM49: 72059.637 | CN49: 132111.68 | CO49: 162125.38 | CP49: 200342.38 | CQ49: 240384.08 | CR49: 247461.21 | CS49: 259817.44 | CT49: 269326.41 | CU49: 279198.06 | CV49: 289446.55 | CW49: 300086.59 | CX49: 311133.48 | CY49: 322603.11 | CZ49: 334512.01 | DA49: 346877.36 | DB49: 359717.02 | DC49: 373049.56 | DD49: 386894.28 | DE49: 401271.25 | DF49: 416201.31 | DG49: 431706.17 | DH49: =CM49=BR49 -> TRUE | DI49: =CN49=BS49 -> TRUE | DJ49: =CO49=BT49 -> TRUE | DK49: =CP49=BU49 -> TRUE | DL49: =CQ49=BV49 -> TRUE | DM49: =CR49=BW49 -> TRUE | DN49: =CS49=BX49 -> TRUE | DO49: =CT49=BY49 -> TRUE | ... EB49: =DG49=CL49 -> TRUE | EC49: =SUM(BV49:CL49) -> 5569685.9 | ED49: =BR49-F49 -> 0 | EE49: =BS49-G49 -> 0 | EF49: =BT49-H49 -> 0 | EG49: =BU49-I49 -> 535.73681 | EH49: =BV49-J49 -> 34962.065 | EI49: =BW49-K49 -> 35511.134 | EJ49: =BX49-L49 -> 39389.365 | EK49: =BY49-M49 -> 40081.21 | ... EX49: =CL49-Z49 -> 49996.057 | EY49: =SUM(EH49:EX49) -> 738552.88
C50: 33 | D50: 2. Условно-постоянные затраты | E50: тыс.руб. | F50: =SUM(F51:F56) -> 4694798.5 | G50: =SUM(G51:G56) -> 5662406.4 | H50: =SUM(H51:H56) -> 6126205.6 | I50: =SUM(I51:I56) -> 6207389.4 | J50: =SUM(J51:J56) -> 6509809.1 | K50: =SUM(K51:K56) -> 6818030.9 | L50: =SUM(L51:L56) -> 7123300.6 | M50: =SUM(M51:M56) -> 7444159.8 | ... Z50: =SUM(Z51:Z56) -> 13557677 | AA50: 4694798.5 | AB50: 5662406.4 | AC50: 6126205.6 | AD50: 6207389.4 | AE50: 6509809.1 | AF50: 6818030.9 | AG50: 7123300.6 | AH50: 7444159.8 | AI50: 7781836.5 | AJ50: 8137099.5 | AK50: 8510982.4 | AL50: 8904586.9 | AM50: 9319088.3 | AN50: 9755755.2 | AO50: 10215925 | AP50: 10701026 | AQ50: 11212583 | AR50: 11752225 | AS50: 12321692 | AT50: 12922847 | AU50: 13557677 | AV50: =AA50=F50 -> TRUE | AW50: =AB50=G50 -> TRUE | AX50: =AC50=H50 -> TRUE | AY50: =AD50=I50 -> TRUE | AZ50: =AE50=J50 -> TRUE | BA50: =AF50=K50 -> TRUE | BB50: =AG50=L50 -> TRUE | BC50: =AH50=M50 -> TRUE | ... BP50: =AU50=Z50 -> TRUE | BQ50: =SUM(J50:Z50) -> 1.6298863e+08 | BR50: =SUM(BR51:BR56) -> 4694798.5 | BS50: =SUM(BS51:BS56) -> 5662406.4 | BT50: =SUM(BT51:BT56) -> 6126205.6 | BU50: =SUM(BU51:BU56) -> 6203262.3 | BV50: =SUM(BV51:BV56) -> 6495172.4 | BW50: =SUM(BW51:BW56) -> 6804132.1 | BX50: =SUM(BX51:BX56) -> 7108465.5 | BY50: =SUM(BY51:BY56) -> 7429398.2 | ... CL50: =SUM(CL51:CL56) -> 14837843 | CM50: 4694798.5 | CN50: 5662406.4 | CO50: 6126205.6 | CP50: 6203262.3 | CQ50: 6495172.4 | CR50: 6804132.1 | CS50: 7108465.5 | CT50: 7429398.2 | CU50: 7767261.1 | CV50: 8122841.3 | CW50: 8497193 | CX50: 8891441.6 | CY50: 9306788.9 | CZ50: 10205932 | DA50: 11241012 | DB50: 11763807 | DC50: 12315043 | DD50: 12845528 | DE50: 13509030 | DF50: 14155558 | DG50: 14837843 | DH50: =CM50=BR50 -> TRUE | DI50: =CN50=BS50 -> TRUE | DJ50: =CO50=BT50 -> TRUE | DK50: =CP50=BU50 -> TRUE | DL50: =CQ50=BV50 -> TRUE | DM50: =CR50=BW50 -> TRUE | DN50: =CS50=BX50 -> TRUE | DO50: =CT50=BY50 -> TRUE | ... EB50: =DG50=CL50 -> TRUE | EC50: =SUM(BV50:CL50) -> 1.7129645e+08 | ED50: =BR50-F50 -> 0 | EE50: =BS50-G50 -> 0 | EF50: =BT50-H50 -> 0 | EG50: =BU50-I50 -> -4127.103 | EH50: =BV50-J50 -> -14636.765 | EI50: =BW50-K50 -> -13898.81 | EJ50: =BX50-L50 -> -14835.18 | EK50: =BY50-M50 -> -14761.623 | ... EX50: =CL50-Z50 -> 1280165.7 | EY50: =SUM(EH50:EX50) -> 8307822.3
C51: 34 | D51: ФОТ персонала | E51: тыс.руб. | F51: ='[10]Данные для переноса'!F49 -> 2202812.2 | G51: ='[10]Данные для переноса'!G49 -> 2615057.5 | H51: ='[10]Данные для переноса'!H49 -> 2979709.1 | I51: ='[10]Данные для переноса'!I49 -> 3245344.9 | J51: ='[10]Данные для переноса'!J49 -> 3426876.7 | K51: ='[10]Данные для переноса'!K49 -> 3613615.6 | L51: ='[10]Данные для переноса'!L49 -> 3800473.5 | M51: ='[10]Данные для переноса'!M49 -> 3998258.5 | ... Z51: ='[10]Данные для переноса'!Z49 -> 7975104.1 | AA51: 2202812.2 | AB51: 2615057.5 | AC51: 2979709.1 | AD51: 3245344.9 | AE51: 3426876.7 | AF51: 3613615.6 | AG51: 3800473.5 | AH51: 3998258.5 | AI51: 4207689.4 | AJ51: 4429536.7 | AK51: 4664626.9 | AL51: 4913845.9 | AM51: 5178144.7 | AN51: 5458543.4 | AO51: 5756137.1 | AP51: 6072101.5 | AQ51: 6407699.2 | AR51: 6764286.2 | AS51: 7143319.5 | AT51: 7546364.5 | AU51: 7975104.1 | AV51: =AA51=F51 -> TRUE | AW51: =AB51=G51 -> TRUE | AX51: =AC51=H51 -> TRUE | AY51: =AD51=I51 -> TRUE | AZ51: =AE51=J51 -> TRUE | BA51: =AF51=K51 -> TRUE | BB51: =AG51=L51 -> TRUE | BC51: =AH51=M51 -> TRUE | ... BP51: =AU51=Z51 -> TRUE | BQ51: =SUM(J51:Z51) -> 91356623 | BR51: ='[10]Данные для переноса'!AB49 -> 2202812.2 | BS51: ='[10]Данные для переноса'!AC49 -> 2615057.5 | BT51: ='[10]Данные для переноса'!AD49 -> 2979709.1 | BU51: ='[10]Данные для переноса'!AE49 -> 3245344.9 | BV51: ='[10]Данные для переноса'!AF49 -> 3426876.7 | BW51: ='[10]Данные для переноса'!AG49 -> 3613615.6 | BX51: ='[10]Данные для переноса'!AH49 -> 3800473.5 | BY51: ='[10]Данные для переноса'!AI49 -> 3998258.5 | ... CL51: ='[10]Данные для переноса'!AV49 -> 8227349.9 | CM51: 2202812.2 | CN51: 2615057.5 | CO51: 2979709.1 | CP51: 3245344.9 | CQ51: 3426876.7 | CR51: 3613615.6 | CS51: 3800473.5 | CT51: 3998258.5 | CU51: 4207689.4 | CV51: 4429536.7 | CW51: 4664626.9 | CX51: 4913845.9 | CY51: 5178144.7 | CZ51: 5543582.8 | DA51: 5936066.4 | DB51: 6262453 | DC51: 6609076.4 | DD51: 6977327.6 | DE51: 7368700.6 | DF51: 7784800 | DG51: 8227349.9 | DH51: =CM51=BR51 -> TRUE | DI51: =CN51=BS51 -> TRUE | DJ51: =CO51=BT51 -> TRUE | DK51: =CP51=BU51 -> TRUE | DL51: =CQ51=BV51 -> TRUE | DM51: =CR51=BW51 -> TRUE | DN51: =CS51=BX51 -> TRUE | DO51: =CT51=BY51 -> TRUE | ... EB51: =DG51=CL51 -> TRUE | EC51: =SUM(BV51:CL51) -> 92942425 | ED51: =BR51-F51 -> 0 | EE51: =BS51-G51 -> 0 | EF51: =BT51-H51 -> 0 | EG51: =BU51-I51 -> 0 | EH51: =BV51-J51 -> 0 | EI51: =BW51-K51 -> 0 | EJ51: =BX51-L51 -> 0 | EK51: =BY51-M51 -> 0 | ... EX51: =CL51-Z51 -> 252245.85 | EY51: =SUM(EH51:EX51) -> 1585801.4
C52: 35 | D52: Оплата работ, услуг (связь, транспортные услуги, прочие услуги) | E52: тыс.руб. | F52: ='[10]Данные для переноса'!F50 -> 401669.92 | G52: ='[10]Данные для переноса'!G50 -> 508416.37 | H52: ='[10]Данные для переноса'!H50 -> 589158.93 | I52: ='[10]Данные для переноса'!I50 -> 585285.45 | J52: ='[10]Данные для переноса'!J50 -> 611073.77 | K52: ='[10]Данные для переноса'!K50 -> 637205.54 | L52: ='[10]Данные для переноса'!L50 -> 662693.76 | M52: ='[10]Данные для переноса'!M50 -> 689201.51 | ... Z52: ='[10]Данные для переноса'!Z50 -> 1147571.2 | AA52: 401669.92 | AB52: 508416.37 | AC52: 589158.93 | AD52: 585285.45 | AE52: 611073.77 | AF52: 637205.54 | AG52: 662693.76 | AH52: 689201.51 | AI52: 716769.57 | AJ52: 745440.36 | AK52: 775257.97 | AL52: 806268.29 | AM52: 838519.02 | AN52: 872059.78 | AO52: 906942.17 | AP52: 943219.86 | AQ52: 980948.66 | AR52: 1020186.6 | AS52: 1060994.1 | AT52: 1103433.8 | AU52: 1147571.2 | AV52: =AA52=F52 -> TRUE | AW52: =AB52=G52 -> TRUE | AX52: =AC52=H52 -> TRUE | AY52: =AD52=I52 -> TRUE | AZ52: =AE52=J52 -> TRUE | BA52: =AF52=K52 -> TRUE | BB52: =AG52=L52 -> TRUE | BC52: =AH52=M52 -> TRUE | ... BP52: =AU52=Z52 -> TRUE | BQ52: =SUM(J52:Z52) -> 14517786 | BR52: ='[10]Данные для переноса'!AB50 -> 401669.92 | BS52: ='[10]Данные для переноса'!AC50 -> 508416.37 | BT52: ='[10]Данные для переноса'!AD50 -> 589158.93 | BU52: ='[10]Данные для переноса'!AE50 -> 585821.19 | BV52: ='[10]Данные для переноса'!AF50 -> 646035.83 | BW52: ='[10]Данные для переноса'!AG50 -> 672716.68 | BX52: ='[10]Данные для переноса'!AH50 -> 702083.13 | BY52: ='[10]Данные для переноса'!AI50 -> 729282.72 | ... CL52: ='[10]Данные для переноса'!AV50 -> 1197567.2 | CM52: 401669.92 | CN52: 508416.37 | CO52: 589158.93 | CP52: 585821.19 | CQ52: 646035.83 | CR52: 672716.68 | CS52: 702083.13 | CT52: 729282.72 | CU52: 757552.63 | CV52: 786935.3 | CW52: 817474.89 | CX52: 849217.31 | CY52: 882210.29 | CZ52: 916503.48 | DA52: 952148.49 | DB52: 989199 | DC52: 1027710.8 | DD52: 1067742 | DE52: 1109352.9 | DF52: 1152606.2 | DG52: 1197567.2 | DH52: =CM52=BR52 -> TRUE | DI52: =CN52=BS52 -> TRUE | DJ52: =CO52=BT52 -> TRUE | DK52: =CP52=BU52 -> TRUE | DL52: =CQ52=BV52 -> TRUE | DM52: =CR52=BW52 -> TRUE | DN52: =CS52=BX52 -> TRUE | DO52: =CT52=BY52 -> TRUE | ... EB52: =DG52=CL52 -> TRUE | EC52: =SUM(BV52:CL52) -> 15256339 | ED52: =BR52-F52 -> 0 | EE52: =BS52-G52 -> 0 | EF52: =BT52-H52 -> 0 | EG52: =BU52-I52 -> 535.73681 | EH52: =BV52-J52 -> 34962.065 | EI52: =BW52-K52 -> 35511.134 | EJ52: =BX52-L52 -> 39389.365 | EK52: =BY52-M52 -> 40081.21 | ... EX52: =CL52-Z52 -> 49996.057 | EY52: =SUM(EH52:EX52) -> 738552.88
C53: 36 | D53: Коммунальные услуги и содержание имущества | E53: тыс.руб. | F53: ='[10]Данные для переноса'!F51 -> 1192318 | G53: ='[10]Данные для переноса'!G51 -> 1406586.5 | H53: ='[10]Данные для переноса'!H51 -> 1386087.5 | I53: ='[10]Данные для переноса'!I51 -> 1448461.4 | J53: ='[10]Данные для переноса'!J51 -> 1506399.9 | K53: ='[10]Данные для переноса'!K51 -> 1566655.9 | L53: ='[10]Данные для переноса'!L51 -> 1629322.1 | M53: ='[10]Данные для переноса'!M51 -> 1694495 | ... Z53: ='[10]Данные для переноса'!Z51 -> 2821458.8 | AA53: 1192318 | AB53: 1406586.5 | AC53: 1386087.5 | AD53: 1448461.4 | AE53: 1506399.9 | AF53: 1566655.9 | AG53: 1629322.1 | AH53: 1694495 | AI53: 1762274.8 | AJ53: 1832765.8 | AK53: 1906076.4 | AL53: 1982319.5 | AM53: 2061612.3 | AN53: 2144076.8 | AO53: 2229839.8 | AP53: 2319033.4 | AQ53: 2411794.8 | AR53: 2508266.6 | AS53: 2608597.2 | AT53: 2712941.1 | AU53: 2821458.8 | AV53: =AA53=F53 -> TRUE | AW53: =AB53=G53 -> TRUE | AX53: =AC53=H53 -> TRUE | AY53: =AD53=I53 -> TRUE | AZ53: =AE53=J53 -> TRUE | BA53: =AF53=K53 -> TRUE | BB53: =AG53=L53 -> TRUE | BC53: =AH53=M53 -> TRUE | ... BP53: =AU53=Z53 -> TRUE | BQ53: =SUM(J53:Z53) -> 35697930 | BR53: ='[10]Данные для переноса'!AB51 -> 1192318 | BS53: ='[10]Данные для переноса'!AC51 -> 1406586.5 | BT53: ='[10]Данные для переноса'!AD51 -> 1386087.5 | BU53: ='[10]Данные для переноса'!AE51 -> 1448461.4 | BV53: ='[10]Данные для переноса'!AF51 -> 1506399.9 | BW53: ='[10]Данные для переноса'!AG51 -> 1566655.9 | BX53: ='[10]Данные для переноса'!AH51 -> 1629322.1 | BY53: ='[10]Данные для переноса'!AI51 -> 1694495 | ... CL53: ='[10]Данные для переноса'!AV51 -> 3444937.6 | CM53: 1192318 | CN53: 1406586.5 | CO53: 1386087.5 | CP53: 1448461.4 | CQ53: 1506399.9 | CR53: 1566655.9 | CS53: 1629322.1 | CT53: 1694495 | CU53: 1762274.8 | CV53: 1832765.8 | CW53: 1906076.4 | CX53: 1982319.5 | CY53: 2061612.3 | CZ53: 2369647.3 | DA53: 2723153.2 | DB53: 2831980.6 | DC53: 2945157.3 | DD53: 3062856.9 | DE53: 3185260.3 | DF53: 3312555.3 | DG53: 3444937.6 | DH53: =CM53=BR53 -> TRUE | DI53: =CN53=BS53 -> TRUE | DJ53: =CO53=BT53 -> TRUE | DK53: =CP53=BU53 -> TRUE | DL53: =CQ53=BV53 -> TRUE | DM53: =CR53=BW53 -> TRUE | DN53: =CS53=BX53 -> TRUE | DO53: =CT53=BY53 -> TRUE | ... EB53: =DG53=CL53 -> TRUE | EC53: =SUM(BV53:CL53) -> 39817470 | ED53: =BR53-F53 -> 0 | EE53: =BS53-G53 -> 0 | EF53: =BT53-H53 -> 0 | EG53: =BU53-I53 -> 0 | EH53: =BV53-J53 -> 0 | EI53: =BW53-K53 -> 0 | EJ53: =BX53-L53 -> 0 | EK53: =BY53-M53 -> 0 | ... EX53: =CL53-Z53 -> 623478.87 | EY53: =SUM(EH53:EX53) -> 4119540.1
C54: 37 | D54: Аренда имущества | E54: тыс.руб. | F54: ='[10]Данные для переноса'!F52 -> 15626.9 | G54: ='[10]Данные для переноса'!G52 -> 32891.6 | H54: ='[10]Данные для переноса'!H52 -> 31208.9 | I54: ='[10]Данные для переноса'!I52 -> 32613.3 | J54: ='[10]Данные для переноса'!J52 -> 33917.833 | K54: ='[10]Данные для переноса'!K52 -> 35274.546 | L54: ='[10]Данные для переноса'!L52 -> 36685.528 | M54: ='[10]Данные для переноса'!M52 -> 38152.949 | ... Z54: ='[10]Данные для переноса'!Z52 -> 63527.464 | AA54: 15626.9 | AB54: 32891.6 | AC54: 31208.9 | AD54: 32613.3 | AE54: 33917.833 | AF54: 35274.546 | AG54: 36685.528 | AH54: 38152.949 | AI54: 39679.067 | AJ54: 41266.229 | AK54: 42916.879 | AL54: 44633.554 | AM54: 46418.896 | AN54: 48275.652 | AO54: 50206.678 | AP54: 52214.945 | AQ54: 54303.543 | AR54: 56475.684 | AS54: 58734.712 | AT54: 61084.1 | AU54: 63527.464 | AV54: =AA54=F54 -> TRUE | AW54: =AB54=G54 -> TRUE | AX54: =AC54=H54 -> TRUE | AY54: =AD54=I54 -> TRUE | AZ54: =AE54=J54 -> TRUE | BA54: =AF54=K54 -> TRUE | BB54: =AG54=L54 -> TRUE | BC54: =AH54=M54 -> TRUE | ... BP54: =AU54=Z54 -> TRUE | BQ54: =SUM(J54:Z54) -> 803768.26 | BR54: ='[10]Данные для переноса'!AB52 -> 15626.9 | BS54: ='[10]Данные для переноса'!AC52 -> 32891.6 | BT54: ='[10]Данные для переноса'!AD52 -> 31208.9 | BU54: ='[10]Данные для переноса'!AE52 -> 32613.3 | BV54: ='[10]Данные для переноса'!AF52 -> 33917.833 | BW54: ='[10]Данные для переноса'!AG52 -> 35274.546 | BX54: ='[10]Данные для переноса'!AH52 -> 36685.528 | BY54: ='[10]Данные для переноса'!AI52 -> 38152.949 | ... CL54: ='[10]Данные для переноса'!AV52 -> 63527.464 | CM54: 15626.9 | CN54: 32891.6 | CO54: 31208.9 | CP54: 32613.3 | CQ54: 33917.833 | CR54: 35274.546 | CS54: 36685.528 | CT54: 38152.949 | CU54: 39679.067 | CV54: 41266.229 | CW54: 42916.879 | CX54: 44633.554 | CY54: 46418.896 | CZ54: 48275.652 | DA54: 50206.678 | DB54: 52214.945 | DC54: 54303.543 | DD54: 56475.684 | DE54: 58734.712 | DF54: 61084.1 | DG54: 63527.464 | DH54: =CM54=BR54 -> TRUE | DI54: =CN54=BS54 -> TRUE | DJ54: =CO54=BT54 -> TRUE | DK54: =CP54=BU54 -> TRUE | DL54: =CQ54=BV54 -> TRUE | DM54: =CR54=BW54 -> TRUE | DN54: =CS54=BX54 -> TRUE | DO54: =CT54=BY54 -> TRUE | ... EB54: =DG54=CL54 -> TRUE | EC54: =SUM(BV54:CL54) -> 803768.26 | ED54: =BR54-F54 -> 0 | EE54: =BS54-G54 -> 0 | EF54: =BT54-H54 -> 0 | EG54: =BU54-I54 -> 0 | EH54: =BV54-J54 -> 0 | EI54: =BW54-K54 -> 0 | EJ54: =BX54-L54 -> 0 | EK54: =BY54-M54 -> 0 | ... EX54: =CL54-Z54 -> 0 | EY54: =SUM(EH54:EX54) -> 0
C55: 38 | D55: Налоги | E55: тыс.руб. | F55: ='[10]Данные для переноса'!F53 -> 745023 | G55: ='[10]Данные для переноса'!G53 -> 804128.8 | H55: ='[10]Данные для переноса'!H53 -> 879574.7 | I55: ='[10]Данные для переноса'!I53 -> 769467.86 | J55: ='[10]Данные для переноса'!J53 -> 790443.51 | K55: ='[10]Данные для переноса'!K53 -> 812295.06 | L55: ='[10]Данные для переноса'!L53 -> 835054.66 | M55: ='[10]Данные для переноса'!M53 -> 858758.62 | ... Z55: ='[10]Данные для переноса'!Z53 -> 1272821.1 | AA55: 745023 | AB55: 804128.8 | AC55: 879574.7 | AD55: 769467.86 | AE55: 790443.51 | AF55: 812295.06 | AG55: 835054.66 | AH55: 858758.62 | AI55: 883444.71 | AJ55: 909152.24 | AK55: 935922.04 | AL55: 963796.62 | AM55: 992820.16 | AN55: 1023054 | AO55: 1054545.6 | AP55: 1087344.4 | AQ55: 1121501.9 | AR55: 1157071.5 | AS55: 1194108.9 | AT55: 1232672 | AU55: 1272821.1 | AV55: =AA55=F55 -> TRUE | AW55: =AB55=G55 -> TRUE | AX55: =AC55=H55 -> TRUE | AY55: =AD55=I55 -> TRUE | AZ55: =AE55=J55 -> TRUE | BA55: =AF55=K55 -> TRUE | BB55: =AG55=L55 -> TRUE | BC55: =AH55=M55 -> TRUE | ... BP55: =AU55=Z55 -> TRUE | BQ55: =SUM(J55:Z55) -> 17124807 | BR55: ='[10]Данные для переноса'!AB53 -> 745023 | BS55: ='[10]Данные для переноса'!AC53 -> 804128.8 | BT55: ='[10]Данные для переноса'!AD53 -> 879574.7 | BU55: ='[10]Данные для переноса'!AE53 -> 765493.82 | BV55: ='[10]Данные для переноса'!AF53 -> 785795.91 | BW55: ='[10]Данные для переноса'!AG53 -> 808542.29 | BX55: ='[10]Данные для переноса'!AH53 -> 831473.58 | BY55: ='[10]Данные для переноса'!AI53 -> 855448.77 | ... CL55: ='[10]Данные для переноса'!AV53 -> 1605277.9 | CM55: 745023 | CN55: 804128.8 | CO55: 879574.7 | CP55: 765493.82 | CQ55: 785795.91 | CR55: 808542.29 | CS55: 831473.58 | CT55: 855448.77 | CU55: 880521.65 | CV55: 906749.76 | CW55: 934194.68 | CX55: 962922.46 | CY55: 993004.06 | CZ55: 1142496.4 | DA55: 1351047.9 | DB55: 1388988.7 | DC55: 1428782.8 | DD55: 1419593.3 | DE55: 1513428 | DF55: 1558416.3 | DG55: 1605277.9 | DH55: =CM55=BR55 -> TRUE | DI55: =CN55=BS55 -> TRUE | DJ55: =CO55=BT55 -> TRUE | DK55: =CP55=BU55 -> TRUE | DL55: =CQ55=BV55 -> TRUE | DM55: =CR55=BW55 -> TRUE | DN55: =CS55=BX55 -> TRUE | DO55: =CT55=BY55 -> TRUE | ... EB55: =DG55=CL55 -> TRUE | EC55: =SUM(BV55:CL55) -> 19366684 | ED55: =BR55-F55 -> 0 | EE55: =BS55-G55 -> 0 | EF55: =BT55-H55 -> 0 | EG55: =BU55-I55 -> -3974.0353 | EH55: =BV55-J55 -> -4647.6035 | EI55: =BW55-K55 -> -3752.7712 | EJ55: =BX55-L55 -> -3581.0761 | EK55: =BY55-M55 -> -3309.8486 | ... EX55: =CL55-Z55 -> 332456.85 | EY55: =SUM(EH55:EX55) -> 2241877.5
C56: 39 | D56: Поступление нефинансовых активов (НМА, матзапасы) | E56: тыс.руб. | F56: ='[10]Данные для переноса'!F54 -> 137348.54 | G56: ='[10]Данные для переноса'!G54 -> 295325.62 | H56: ='[10]Данные для переноса'!H54 -> 260466.49 | I56: ='[10]Данные для переноса'!I54 -> 126216.41 | J56: ='[10]Данные для переноса'!J54 -> 141097.46 | K56: ='[10]Данные для переноса'!K54 -> 152984.24 | L56: ='[10]Данные для переноса'!L54 -> 159071.08 | M56: ='[10]Данные для переноса'!M54 -> 165293.22 | ... Z56: ='[10]Данные для переноса'!Z54 -> 277194.67 | AA56: 137348.54 | AB56: 295325.62 | AC56: 260466.49 | AD56: 126216.41 | AE56: 141097.46 | AF56: 152984.24 | AG56: 159071.08 | AH56: 165293.22 | AI56: 171978.93 | AJ56: 178938.1 | AK56: 186182.17 | AL56: 193723.06 | AM56: 201573.23 | AN56: 209745.66 | AO56: 218253.93 | AP56: 227112.19 | AQ56: 236335.24 | AR56: 245938.52 | AS56: 255938.15 | AT56: 266351 | AU56: 277194.67 | AV56: =AA56=F56 -> TRUE | AW56: =AB56=G56 -> TRUE | AX56: =AC56=H56 -> TRUE | AY56: =AD56=I56 -> TRUE | AZ56: =AE56=J56 -> TRUE | BA56: =AF56=K56 -> TRUE | BB56: =AG56=L56 -> TRUE | BC56: =AH56=M56 -> TRUE | ... BP56: =AU56=Z56 -> TRUE | BQ56: =SUM(J56:Z56) -> 3487710.8 | BR56: ='[10]Данные для переноса'!AB54 -> 137348.54 | BS56: ='[10]Данные для переноса'!AC54 -> 295325.62 | BT56: ='[10]Данные для переноса'!AD54 -> 260466.49 | BU56: ='[10]Данные для переноса'!AE54 -> 125527.61 | BV56: ='[10]Данные для переноса'!AF54 -> 96146.229 | BW56: ='[10]Данные для переноса'!AG54 -> 107327.07 | BX56: ='[10]Данные для переноса'!AH54 -> 108427.61 | BY56: ='[10]Данные для переноса'!AI54 -> 113760.24 | ... CL56: ='[10]Данные для переноса'!AV54 -> 299182.74 | CM56: 137348.54 | CN56: 295325.62 | CO56: 260466.49 | CP56: 125527.61 | CQ56: 96146.229 | CR56: 107327.07 | CS56: 108427.61 | CT56: 113760.24 | CU56: 119543.57 | CV56: 125587.46 | CW56: 131903.27 | CX56: 138502.89 | CY56: 145398.74 | CZ56: 185426.49 | DA56: 228389.66 | DB56: 238970.97 | DC56: 250012.07 | DD56: 261532.71 | DE56: 273553.52 | DF56: 286096.03 | DG56: 299182.74 | DH56: =CM56=BR56 -> TRUE | DI56: =CN56=BS56 -> TRUE | DJ56: =CO56=BT56 -> TRUE | DK56: =CP56=BU56 -> TRUE | DL56: =CQ56=BV56 -> TRUE | DM56: =CR56=BW56 -> TRUE | DN56: =CS56=BX56 -> TRUE | DO56: =CT56=BY56 -> TRUE | ... EB56: =DG56=CL56 -> TRUE | EC56: =SUM(BV56:CL56) -> 3109761.3 | ED56: =BR56-F56 -> 0 | EE56: =BS56-G56 -> 0 | EF56: =BT56-H56 -> 0 | EG56: =BU56-I56 -> -688.80447 | EH56: =BV56-J56 -> -44951.227 | EI56: =BW56-K56 -> -45657.172 | EJ56: =BX56-L56 -> -50643.47 | EK56: =BY56-M56 -> -51532.984 | ... EX56: =CL56-Z56 -> 21988.064 | EY56: =SUM(EH56:EX56) -> -377949.58
C57: 40 | D57: 3. Инвестиционные расходы (приобритение нефинансовых активов, включая основные средства) | E57: тыс.руб. | F57: ='[10]Данные для переноса'!F55 -> 953855.12 | G57: ='[10]Данные для переноса'!G55 -> 1058987.3 | H57: ='[10]Данные для переноса'!H55 -> 1582124.6 | I57: ='[10]Данные для переноса'!I55 -> 1653320.2 | J57: ='[10]Данные для переноса'!J55 -> 1719453 | K57: ='[10]Данные для переноса'!K55 -> 1788231.1 | L57: ='[10]Данные для переноса'!L55 -> 1859760.4 | M57: ='[10]Данные для переноса'!M55 -> 1934150.8 | ... Z57: ='[10]Данные для переноса'!Z55 -> 3220503.3 | AA57: 953855.12 | AB57: 1058987.3 | AC57: 1582124.6 | AD57: 1653320.2 | AE57: 1719453 | AF57: 1788231.1 | AG57: 1859760.4 | AH57: 1934150.8 | AI57: 2011516.8 | AJ57: 2091977.5 | AK57: 2175656.6 | AL57: 2262682.9 | AM57: 2353190.2 | AN57: 2447317.8 | AO57: 2545210.5 | AP57: 2647018.9 | AQ57: 2752899.7 | AR57: 2863015.7 | AS57: 2977536.3 | AT57: 3096637.8 | AU57: 3220503.3 | AV57: =AA57=F57 -> TRUE | AW57: =AB57=G57 -> TRUE | AX57: =AC57=H57 -> TRUE | AY57: =AD57=I57 -> TRUE | AZ57: =AE57=J57 -> TRUE | BA57: =AF57=K57 -> TRUE | BB57: =AG57=L57 -> TRUE | BC57: =AH57=M57 -> TRUE | ... BP57: =AU57=Z57 -> TRUE | BQ57: =SUM(J57:Z57) -> 40746759 | BR57: ='[10]Данные для переноса'!AB55 -> 953855.12 | BS57: ='[10]Данные для переноса'!AC55 -> 1058987.3 | BT57: ='[10]Данные для переноса'!AD55 -> 1582124.6 | BU57: ='[10]Данные для переноса'!AE55 -> 1653320.2 | BV57: ='[10]Данные для переноса'!AF55 -> 1719453 | BW57: ='[10]Данные для переноса'!AG55 -> 2933214.2 | BX57: ='[10]Данные для переноса'!AH55 -> 2457731.1 | BY57: ='[10]Данные для переноса'!AI55 -> 2058528.7 | ... CL57: ='[10]Данные для переноса'!AV55 -> 3220503.3 | CM57: 953855.12 | CN57: 1058987.3 | CO57: 1582124.6 | CP57: 1653320.2 | CQ57: 1719453 | CR57: 2933214.2 | CS57: 2457731.1 | CT57: 2058528.7 | CU57: 8791003.2 | CV57: 9142643.3 | CW57: 8047724.8 | CX57: 8658158.4 | CY57: 4900321.3 | CZ57: 4162481.7 | DA57: 2545210.5 | DB57: 2647018.9 | DC57: 2752899.7 | DD57: 2863015.7 | DE57: 2977536.3 | DF57: 3096637.8 | DG57: 3220503.3 | DH57: =CM57=BR57 -> TRUE | DI57: =CN57=BS57 -> TRUE | DJ57: =CO57=BT57 -> TRUE | DK57: =CP57=BU57 -> TRUE | DL57: =CQ57=BV57 -> TRUE | DM57: =CR57=BW57 -> TRUE | DN57: =CS57=BX57 -> TRUE | DO57: =CT57=BY57 -> TRUE | ... EB57: =DG57=CL57 -> TRUE | EC57: =SUM(BV57:CL57) -> 72974082 | ED57: =BR57-F57 -> 0 | EE57: =BS57-G57 -> 0 | EF57: =BT57-H57 -> 0 | EG57: =BU57-I57 -> 0 | EH57: =BV57-J57 -> 0 | EI57: =BW57-K57 -> 1144983.1 | EJ57: =BX57-L57 -> 597970.71 | EK57: =BY57-M57 -> 124377.91 | ... EX57: =CL57-Z57 -> 0 | EY57: =SUM(EH57:EX57) -> 32227323
D58: Налоги | F58: =F59+F63+F67+F71+F75+F79+F80 -> 2705822.3 | G58: =G59+G63+G67+G71+G75+G79+G80 -> 3211463 | H58: =H59+H63+H67+H71+H75+H79+H80 -> 3847800.7 | I58: =I59+I63+I67+I71+I75+I79+I80 -> 3968248.3 | J58: =J59+J63+J67+J71+J75+J79+J80 -> 4209173.2 | K58: =K59+K63+K67+K71+K75+K79+K80 -> 4456263.3 | L58: =L59+L63+L67+L71+L75+L79+L80 -> 4637503.8 | M58: =M59+M63+M67+M71+M75+M79+M80 -> 4826696.9 | ... Z58: =Z59+Z63+Z67+Z71+Z75+Z79+Z80 -> 8291475.3 | AV58: =AA58=F58 -> FALSE | AW58: =AB58=G58 -> FALSE | AX58: =AC58=H58 -> FALSE | AY58: =AD58=I58 -> FALSE | AZ58: =AE58=J58 -> FALSE | BA58: =AF58=K58 -> FALSE | BB58: =AG58=L58 -> FALSE | BC58: =AH58=M58 -> FALSE | ... BP58: =AU58=Z58 -> FALSE | BQ58: =BQ59+BQ63+BQ67+BQ71+BQ75+BQ79+BQ80 -> 1.0287712e+08 | BR58: =BR59+BR63+BR67+BR71+BR75+BR79+BR80 -> 2705822.3 | BS58: =BS59+BS63+BS67+BS71+BS75+BS79+BS80 -> 3211463 | BT58: =BT59+BT63+BT67+BT71+BT75+BT79+BT80 -> 3847800.7 | BU58: =BU59+BU63+BU67+BU71+BU75+BU79+BU80 -> 4090750.6 | BV58: =BV59+BV63+BV67+BV71+BV75+BV79+BV80 -> 4456435.6 | BW58: =BW59+BW63+BW67+BW71+BW75+BW79+BW80 -> 4744473.9 | BX58: =BX59+BX63+BX67+BX71+BX75+BX79+BX80 -> 4967210.4 | ... CL58: =CL59+CL63+CL67+CL71+CL75+CL79+CL80 -> 9424826.5 | DH58: =CM58=BR58 -> FALSE | DI58: =CN58=BS58 -> FALSE | DJ58: =CO58=BT58 -> FALSE | DK58: =CP58=BU58 -> FALSE | DL58: =CQ58=BV58 -> FALSE | DM58: =CR58=BW58 -> FALSE | DN58: =CS58=BX58 -> FALSE | DO58: =CT58=BY58 -> FALSE | ... EB58: =DG58=CL58 -> FALSE | EC58: =EC59+EC63+EC67+EC71+EC75+EC79+EC80 -> 1.1379526e+08 | ED58: =BR58-F58 -> 0 | EE58: =BS58-G58 -> 0 | EF58: =BT58-H58 -> 0 | EG58: =BU58-I58 -> 122502.27 | EH58: =BV58-J58 -> 247262.43 | EI58: =BW58-K58 -> 288210.63 | EJ58: =BX58-L58 -> 329706.56 | EK58: =BY58-M58 -> 355328.14 | ... EX58: =CL58-Z58 -> 1133351.2 | EY58: =EY59+EY63+EY67+EY71+EY75+EY79+EY80 -> 10918137
C59: =C57+1 -> 41 | D59: Налог на землю | E59: тыс.руб. | F59: ='[10]Данные для переноса'!F60 -> 116339.86 | G59: ='[10]Данные для переноса'!G60 -> 109330.08 | H59: ='[10]Данные для переноса'!H60 -> 104057.33 | I59: ='[10]Данные для переноса'!I60 -> 137242.74 | J59: ='[10]Данные для переноса'!J60 -> 137242.74 | K59: ='[10]Данные для переноса'!K60 -> 137242.74 | L59: ='[10]Данные для переноса'!L60 -> 137242.74 | M59: ='[10]Данные для переноса'!M60 -> 137242.74 | ... Z59: ='[10]Данные для переноса'!Z60 -> 137242.74 | AA59: 116339.86 | AB59: 109330.08 | AC59: 104057.33 | AD59: 137242.74 | AE59: 137242.74 | AF59: 137242.74 | AG59: 137242.74 | AH59: 137242.74 | AI59: 137242.74 | AJ59: 137242.74 | AK59: 137242.74 | AL59: 137242.74 | AM59: 137242.74 | AN59: 137242.74 | AO59: 137242.74 | AP59: 137242.74 | AQ59: 137242.74 | AR59: 137242.74 | AS59: 137242.74 | AT59: 137242.74 | AU59: 137242.74 | AV59: =AA59=F59 -> TRUE | AW59: =AB59=G59 -> TRUE | AX59: =AC59=H59 -> TRUE | AY59: =AD59=I59 -> TRUE | AZ59: =AE59=J59 -> TRUE | BA59: =AF59=K59 -> TRUE | BB59: =AG59=L59 -> TRUE | BC59: =AH59=M59 -> TRUE | ... BP59: =AU59=Z59 -> TRUE | BQ59: =SUM(J59:Z59) -> 2333126.5 | BR59: ='[10]Данные для переноса'!AB60 -> 116339.86 | BS59: ='[10]Данные для переноса'!AC60 -> 109330.08 | BT59: ='[10]Данные для переноса'!AD60 -> 104057.33 | BU59: ='[10]Данные для переноса'!AE60 -> 135414.74 | BV59: ='[10]Данные для переноса'!AF60 -> 133399.34 | BW59: ='[10]Данные для переноса'!AG60 -> 134207.84 | BX59: ='[10]Данные для переноса'!AH60 -> 134207.84 | BY59: ='[10]Данные для переноса'!AI60 -> 134207.84 | ... CL59: ='[10]Данные для переноса'!AV60 -> 134207.84 | CM59: 116339.86 | CN59: 109330.08 | CO59: 104057.33 | CP59: 135414.74 | CQ59: 133399.34 | CR59: 134207.84 | CS59: 134207.84 | CT59: 134207.84 | CU59: 134207.84 | CV59: 134207.84 | CW59: 134207.84 | CX59: 134207.84 | CY59: 134207.84 | CZ59: 134207.84 | DA59: 134207.84 | DB59: 134207.84 | DC59: 134207.84 | DD59: 134207.84 | DE59: 134207.84 | DF59: 134207.84 | DG59: 134207.84 | DH59: =CM59=BR59 -> TRUE | DI59: =CN59=BS59 -> TRUE | DJ59: =CO59=BT59 -> TRUE | DK59: =CP59=BU59 -> TRUE | DL59: =CQ59=BV59 -> TRUE | DM59: =CR59=BW59 -> TRUE | DN59: =CS59=BX59 -> TRUE | DO59: =CT59=BY59 -> TRUE | ... EB59: =DG59=CL59 -> TRUE | EC59: =SUM(BV59:CL59) -> 2280724.8 | ED59: =BR59-F59 -> 0 | EE59: =BS59-G59 -> 0 | EF59: =BT59-H59 -> 0 | EG59: =BU59-I59 -> -1827.996 | EH59: =BV59-J59 -> -3843.394 | EI59: =BW59-K59 -> -3034.894 | EJ59: =BX59-L59 -> -3034.894 | EK59: =BY59-M59 -> -3034.894 | ... EX59: =CL59-Z59 -> -3034.894 | EY59: =SUM(EH59:EX59) -> -52401.698
D60: в том числе по уровням бюджета: федеральный бюджет | E60: тыс.руб. | F60: ='[10]Данные для переноса'!F61 -> 0 | G60: ='[10]Данные для переноса'!G61 -> 0 | H60: ='[10]Данные для переноса'!H61 -> 0 | I60: ='[10]Данные для переноса'!I61 -> 0 | J60: ='[10]Данные для переноса'!J61 -> 0 | K60: ='[10]Данные для переноса'!K61 -> 0 | L60: ='[10]Данные для переноса'!L61 -> 0 | M60: ='[10]Данные для переноса'!M61 -> 0 | ... Z60: ='[10]Данные для переноса'!Z61 -> 0 | AV60: =AA60=F60 -> TRUE | AW60: =AB60=G60 -> TRUE | AX60: =AC60=H60 -> TRUE | AY60: =AD60=I60 -> TRUE | AZ60: =AE60=J60 -> TRUE | BA60: =AF60=K60 -> TRUE | BB60: =AG60=L60 -> TRUE | BC60: =AH60=M60 -> TRUE | ... BP60: =AU60=Z60 -> TRUE | BQ60: =SUM(J60:Z60) -> 0 | BR60: ='[10]Данные для переноса'!AB61 -> 0 | BS60: ='[10]Данные для переноса'!AC61 -> 0 | BT60: ='[10]Данные для переноса'!AD61 -> 0 | BU60: ='[10]Данные для переноса'!AE61 -> 0 | BV60: ='[10]Данные для переноса'!AF61 -> 0 | BW60: ='[10]Данные для переноса'!AG61 -> 0 | BX60: ='[10]Данные для переноса'!AH61 -> 0 | BY60: ='[10]Данные для переноса'!AI61 -> 0 | ... CL60: ='[10]Данные для переноса'!AV61 -> 0 | DH60: =CM60=BR60 -> TRUE | DI60: =CN60=BS60 -> TRUE | DJ60: =CO60=BT60 -> TRUE | DK60: =CP60=BU60 -> TRUE | DL60: =CQ60=BV60 -> TRUE | DM60: =CR60=BW60 -> TRUE | DN60: =CS60=BX60 -> TRUE | DO60: =CT60=BY60 -> TRUE | ... EB60: =DG60=CL60 -> TRUE | EC60: =SUM(BV60:CL60) -> 0 | ED60: =BR60-F60 -> 0 | EE60: =BS60-G60 -> 0 | EF60: =BT60-H60 -> 0 | EG60: =BU60-I60 -> 0 | EH60: =BV60-J60 -> 0 | EI60: =BW60-K60 -> 0 | EJ60: =BX60-L60 -> 0 | EK60: =BY60-M60 -> 0 | ... EX60: =CL60-Z60 -> 0 | EY60: =SUM(EH60:EX60) -> 0
D61: региональный бюджет | E61: тыс.руб. | F61: ='[10]Данные для переноса'!F62 -> 0 | G61: ='[10]Данные для переноса'!G62 -> 0 | H61: ='[10]Данные для переноса'!H62 -> 0 | I61: ='[10]Данные для переноса'!I62 -> 0 | J61: ='[10]Данные для переноса'!J62 -> 0 | K61: ='[10]Данные для переноса'!K62 -> 0 | L61: ='[10]Данные для переноса'!L62 -> 0 | M61: ='[10]Данные для переноса'!M62 -> 0 | ... Z61: ='[10]Данные для переноса'!Z62 -> 0 | AV61: =AA61=F61 -> TRUE | AW61: =AB61=G61 -> TRUE | AX61: =AC61=H61 -> TRUE | AY61: =AD61=I61 -> TRUE | AZ61: =AE61=J61 -> TRUE | BA61: =AF61=K61 -> TRUE | BB61: =AG61=L61 -> TRUE | BC61: =AH61=M61 -> TRUE | ... BP61: =AU61=Z61 -> TRUE | BQ61: =SUM(J61:Z61) -> 0 | BR61: ='[10]Данные для переноса'!AB62 -> 0 | BS61: ='[10]Данные для переноса'!AC62 -> 0 | BT61: ='[10]Данные для переноса'!AD62 -> 0 | BU61: ='[10]Данные для переноса'!AE62 -> 0 | BV61: ='[10]Данные для переноса'!AF62 -> 0 | BW61: ='[10]Данные для переноса'!AG62 -> 0 | BX61: ='[10]Данные для переноса'!AH62 -> 0 | BY61: ='[10]Данные для переноса'!AI62 -> 0 | ... CL61: ='[10]Данные для переноса'!AV62 -> 0 | DH61: =CM61=BR61 -> TRUE | DI61: =CN61=BS61 -> TRUE | DJ61: =CO61=BT61 -> TRUE | DK61: =CP61=BU61 -> TRUE | DL61: =CQ61=BV61 -> TRUE | DM61: =CR61=BW61 -> TRUE | DN61: =CS61=BX61 -> TRUE | DO61: =CT61=BY61 -> TRUE | ... EB61: =DG61=CL61 -> TRUE | EC61: =SUM(BV61:CL61) -> 0 | ED61: =BR61-F61 -> 0 | EE61: =BS61-G61 -> 0 | EF61: =BT61-H61 -> 0 | EG61: =BU61-I61 -> 0 | EH61: =BV61-J61 -> 0 | EI61: =BW61-K61 -> 0 | EJ61: =BX61-L61 -> 0 | EK61: =BY61-M61 -> 0 | ... EX61: =CL61-Z61 -> 0 | EY61: =SUM(EH61:EX61) -> 0
D62: местный бюджет | E62: тыс.руб. | F62: ='[10]Данные для переноса'!F63 -> 116339.86 | G62: ='[10]Данные для переноса'!G63 -> 109330.08 | H62: ='[10]Данные для переноса'!H63 -> 104057.33 | I62: ='[10]Данные для переноса'!I63 -> 137242.74 | J62: ='[10]Данные для переноса'!J63 -> 137242.74 | K62: ='[10]Данные для переноса'!K63 -> 137242.74 | L62: ='[10]Данные для переноса'!L63 -> 137242.74 | M62: ='[10]Данные для переноса'!M63 -> 137242.74 | ... Z62: ='[10]Данные для переноса'!Z63 -> 137242.74 | AA62: 116339.86 | AB62: 109330.08 | AC62: 104057.33 | AD62: 137242.74 | AE62: 137242.74 | AF62: 137242.74 | AG62: 137242.74 | AH62: 137242.74 | AI62: 137242.74 | AJ62: 137242.74 | AK62: 137242.74 | AL62: 137242.74 | AM62: 137242.74 | AN62: 137242.74 | AO62: 137242.74 | AP62: 137242.74 | AQ62: 137242.74 | AR62: 137242.74 | AS62: 137242.74 | AT62: 137242.74 | AU62: 137242.74 | AV62: =AA62=F62 -> TRUE | AW62: =AB62=G62 -> TRUE | AX62: =AC62=H62 -> TRUE | AY62: =AD62=I62 -> TRUE | AZ62: =AE62=J62 -> TRUE | BA62: =AF62=K62 -> TRUE | BB62: =AG62=L62 -> TRUE | BC62: =AH62=M62 -> TRUE | ... BP62: =AU62=Z62 -> TRUE | BQ62: =SUM(J62:Z62) -> 2333126.5 | BR62: ='[10]Данные для переноса'!AB63 -> 116339.86 | BS62: ='[10]Данные для переноса'!AC63 -> 109330.08 | BT62: ='[10]Данные для переноса'!AD63 -> 104057.33 | BU62: ='[10]Данные для переноса'!AE63 -> 135414.74 | BV62: ='[10]Данные для переноса'!AF63 -> 133399.34 | BW62: ='[10]Данные для переноса'!AG63 -> 134207.84 | BX62: ='[10]Данные для переноса'!AH63 -> 134207.84 | BY62: ='[10]Данные для переноса'!AI63 -> 134207.84 | ... CL62: ='[10]Данные для переноса'!AV63 -> 134207.84 | CM62: 116339.86 | CN62: 109330.08 | CO62: 104057.33 | CP62: 135414.74 | CQ62: 133399.34 | CR62: 134207.84 | CS62: 134207.84 | CT62: 134207.84 | CU62: 134207.84 | CV62: 134207.84 | CW62: 134207.84 | CX62: 134207.84 | CY62: 134207.84 | CZ62: 134207.84 | DA62: 134207.84 | DB62: 134207.84 | DC62: 134207.84 | DD62: 134207.84 | DE62: 134207.84 | DF62: 134207.84 | DG62: 134207.84 | DH62: =CM62=BR62 -> TRUE | DI62: =CN62=BS62 -> TRUE | DJ62: =CO62=BT62 -> TRUE | DK62: =CP62=BU62 -> TRUE | DL62: =CQ62=BV62 -> TRUE | DM62: =CR62=BW62 -> TRUE | DN62: =CS62=BX62 -> TRUE | DO62: =CT62=BY62 -> TRUE | ... EB62: =DG62=CL62 -> TRUE | EC62: =SUM(BV62:CL62) -> 2280724.8 | ED62: =BR62-F62 -> 0 | EE62: =BS62-G62 -> 0 | EF62: =BT62-H62 -> 0 | EG62: =BU62-I62 -> -1827.996 | EH62: =BV62-J62 -> -3843.394 | EI62: =BW62-K62 -> -3034.894 | EJ62: =BX62-L62 -> -3034.894 | EK62: =BY62-M62 -> -3034.894 | ... EX62: =CL62-Z62 -> -3034.894 | EY62: =SUM(EH62:EX62) -> -52401.698
C63: =C59+1 -> 42 | D63: Налог на имущество | E63: тыс.руб. | F63: ='[10]Данные для переноса'!F64 -> 46159.791 | G63: ='[10]Данные для переноса'!G64 -> 45073.411 | H63: ='[10]Данные для переноса'!H64 -> 43159.023 | I63: ='[10]Данные для переноса'!I64 -> 54048.764 | J63: ='[10]Данные для переноса'!J64 -> 53196.462 | K63: ='[10]Данные для переноса'!K64 -> 52346.932 | L63: ='[10]Данные для переноса'!L64 -> 51497.402 | M63: ='[10]Данные для переноса'!M64 -> 50647.872 | ... Z63: ='[10]Данные для переноса'!Z64 -> 40133.608 | AA63: 46159.791 | AB63: 45073.411 | AC63: 43159.023 | AD63: 54048.764 | AE63: 53196.462 | AF63: 52346.932 | AG63: 51497.402 | AH63: 50647.872 | AI63: 49798.342 | AJ63: 48948.812 | AK63: 48099.282 | AL63: 47249.752 | AM63: 46400.222 | AN63: 45566.037 | AO63: 44746.918 | AP63: 43942.591 | AQ63: 43152.788 | AR63: 42377.245 | AS63: 41615.703 | AT63: 40867.907 | AU63: 40133.608 | AV63: =AA63=F63 -> TRUE | AW63: =AB63=G63 -> TRUE | AX63: =AC63=H63 -> TRUE | AY63: =AD63=I63 -> TRUE | AZ63: =AE63=J63 -> TRUE | BA63: =AF63=K63 -> TRUE | BB63: =AG63=L63 -> TRUE | BC63: =AH63=M63 -> TRUE | ... BP63: =AU63=Z63 -> TRUE | BQ63: =SUM(J63:Z63) -> 790587.87 | BR63: ='[10]Данные для переноса'!AB64 -> 46159.791 | BS63: ='[10]Данные для переноса'!AC64 -> 45073.411 | BT63: ='[10]Данные для переноса'!AD64 -> 43159.023 | BU63: ='[10]Данные для переноса'!AE64 -> 54048.764 | BV63: ='[10]Данные для переноса'!AF64 -> 53196.462 | BW63: ='[10]Данные для переноса'!AG64 -> 52346.932 | BX63: ='[10]Данные для переноса'!AH64 -> 51497.402 | BY63: ='[10]Данные для переноса'!AI64 -> 50647.872 | ... CL63: ='[10]Данные для переноса'!AV64 -> 40133.608 | CM63: 46159.791 | CN63: 45073.411 | CO63: 43159.023 | CP63: 54048.764 | CQ63: 53196.462 | CR63: 52346.932 | CS63: 51497.402 | CT63: 50647.872 | CU63: 49798.342 | CV63: 48948.812 | CW63: 48099.282 | CX63: 47249.752 | CY63: 46400.222 | CZ63: 45566.037 | DA63: 44746.918 | DB63: 43942.591 | DC63: 43152.788 | DD63: 42377.245 | DE63: 41615.703 | DF63: 40867.907 | DG63: 40133.608 | DH63: =CM63=BR63 -> TRUE | DI63: =CN63=BS63 -> TRUE | DJ63: =CO63=BT63 -> TRUE | DK63: =CP63=BU63 -> TRUE | DL63: =CQ63=BV63 -> TRUE | DM63: =CR63=BW63 -> TRUE | DN63: =CS63=BX63 -> TRUE | DO63: =CT63=BY63 -> TRUE | ... EB63: =DG63=CL63 -> TRUE | EC63: =SUM(BV63:CL63) -> 790587.87 | ED63: =BR63-F63 -> 0 | EE63: =BS63-G63 -> 0 | EF63: =BT63-H63 -> 0 | EG63: =BU63-I63 -> 0 | EH63: =BV63-J63 -> 0 | EI63: =BW63-K63 -> 0 | EJ63: =BX63-L63 -> 0 | EK63: =BY63-M63 -> 0 | ... EX63: =CL63-Z63 -> 0 | EY63: =SUM(EH63:EX63) -> 0
D64: в том числе по уровням бюджета: федеральный бюджет | E64: тыс.руб. | F64: ='[10]Данные для переноса'!F65 -> 0 | G64: ='[10]Данные для переноса'!G65 -> 0 | H64: ='[10]Данные для переноса'!H65 -> 0 | I64: ='[10]Данные для переноса'!I65 -> 0 | J64: ='[10]Данные для переноса'!J65 -> 0 | K64: ='[10]Данные для переноса'!K65 -> 0 | L64: ='[10]Данные для переноса'!L65 -> 0 | M64: ='[10]Данные для переноса'!M65 -> 0 | ... Z64: ='[10]Данные для переноса'!Z65 -> 0 | AV64: =AA64=F64 -> TRUE | AW64: =AB64=G64 -> TRUE | AX64: =AC64=H64 -> TRUE | AY64: =AD64=I64 -> TRUE | AZ64: =AE64=J64 -> TRUE | BA64: =AF64=K64 -> TRUE | BB64: =AG64=L64 -> TRUE | BC64: =AH64=M64 -> TRUE | ... BP64: =AU64=Z64 -> TRUE | BQ64: =SUM(J64:Z64) -> 0 | BR64: ='[10]Данные для переноса'!AB65 -> 0 | BS64: ='[10]Данные для переноса'!AC65 -> 0 | BT64: ='[10]Данные для переноса'!AD65 -> 0 | BU64: ='[10]Данные для переноса'!AE65 -> 0 | BV64: ='[10]Данные для переноса'!AF65 -> 0 | BW64: ='[10]Данные для переноса'!AG65 -> 0 | BX64: ='[10]Данные для переноса'!AH65 -> 0 | BY64: ='[10]Данные для переноса'!AI65 -> 0 | ... CL64: ='[10]Данные для переноса'!AV65 -> 0 | DH64: =CM64=BR64 -> TRUE | DI64: =CN64=BS64 -> TRUE | DJ64: =CO64=BT64 -> TRUE | DK64: =CP64=BU64 -> TRUE | DL64: =CQ64=BV64 -> TRUE | DM64: =CR64=BW64 -> TRUE | DN64: =CS64=BX64 -> TRUE | DO64: =CT64=BY64 -> TRUE | ... EB64: =DG64=CL64 -> TRUE | EC64: =SUM(BV64:CL64) -> 0 | ED64: =BR64-F64 -> 0 | EE64: =BS64-G64 -> 0 | EF64: =BT64-H64 -> 0 | EG64: =BU64-I64 -> 0 | EH64: =BV64-J64 -> 0 | EI64: =BW64-K64 -> 0 | EJ64: =BX64-L64 -> 0 | EK64: =BY64-M64 -> 0 | ... EX64: =CL64-Z64 -> 0 | EY64: =SUM(EH64:EX64) -> 0
D65: региональный бюджет | E65: тыс.руб. | F65: ='[10]Данные для переноса'!F66 -> 46159.791 | G65: ='[10]Данные для переноса'!G66 -> 45073.411 | H65: ='[10]Данные для переноса'!H66 -> 43159.023 | I65: ='[10]Данные для переноса'!I66 -> 54048.764 | J65: ='[10]Данные для переноса'!J66 -> 53196.462 | K65: ='[10]Данные для переноса'!K66 -> 52346.932 | L65: ='[10]Данные для переноса'!L66 -> 51497.402 | M65: ='[10]Данные для переноса'!M66 -> 50647.872 | ... Z65: ='[10]Данные для переноса'!Z66 -> 40133.608 | AA65: 46159.791 | AB65: 45073.411 | AC65: 43159.023 | AD65: 54048.764 | AE65: 53196.462 | AF65: 52346.932 | AG65: 51497.402 | AH65: 50647.872 | AI65: 49798.342 | AJ65: 48948.812 | AK65: 48099.282 | AL65: 47249.752 | AM65: 46400.222 | AN65: 45566.037 | AO65: 44746.918 | AP65: 43942.591 | AQ65: 43152.788 | AR65: 42377.245 | AS65: 41615.703 | AT65: 40867.907 | AU65: 40133.608 | AV65: =AA65=F65 -> TRUE | AW65: =AB65=G65 -> TRUE | AX65: =AC65=H65 -> TRUE | AY65: =AD65=I65 -> TRUE | AZ65: =AE65=J65 -> TRUE | BA65: =AF65=K65 -> TRUE | BB65: =AG65=L65 -> TRUE | BC65: =AH65=M65 -> TRUE | ... BP65: =AU65=Z65 -> TRUE | BQ65: =SUM(J65:Z65) -> 790587.87 | BR65: ='[10]Данные для переноса'!AB66 -> 46159.791 | BS65: ='[10]Данные для переноса'!AC66 -> 45073.411 | BT65: ='[10]Данные для переноса'!AD66 -> 43159.023 | BU65: ='[10]Данные для переноса'!AE66 -> 54048.764 | BV65: ='[10]Данные для переноса'!AF66 -> 53196.462 | BW65: ='[10]Данные для переноса'!AG66 -> 52346.932 | BX65: ='[10]Данные для переноса'!AH66 -> 51497.402 | BY65: ='[10]Данные для переноса'!AI66 -> 50647.872 | ... CL65: ='[10]Данные для переноса'!AV66 -> 40133.608 | CM65: 46159.791 | CN65: 45073.411 | CO65: 43159.023 | CP65: 54048.764 | CQ65: 53196.462 | CR65: 52346.932 | CS65: 51497.402 | CT65: 50647.872 | CU65: 49798.342 | CV65: 48948.812 | CW65: 48099.282 | CX65: 47249.752 | CY65: 46400.222 | CZ65: 45566.037 | DA65: 44746.918 | DB65: 43942.591 | DC65: 43152.788 | DD65: 42377.245 | DE65: 41615.703 | DF65: 40867.907 | DG65: 40133.608 | DH65: =CM65=BR65 -> TRUE | DI65: =CN65=BS65 -> TRUE | DJ65: =CO65=BT65 -> TRUE | DK65: =CP65=BU65 -> TRUE | DL65: =CQ65=BV65 -> TRUE | DM65: =CR65=BW65 -> TRUE | DN65: =CS65=BX65 -> TRUE | DO65: =CT65=BY65 -> TRUE | ... EB65: =DG65=CL65 -> TRUE | EC65: =SUM(BV65:CL65) -> 790587.87 | ED65: =BR65-F65 -> 0 | EE65: =BS65-G65 -> 0 | EF65: =BT65-H65 -> 0 | EG65: =BU65-I65 -> 0 | EH65: =BV65-J65 -> 0 | EI65: =BW65-K65 -> 0 | EJ65: =BX65-L65 -> 0 | EK65: =BY65-M65 -> 0 | ... EX65: =CL65-Z65 -> 0 | EY65: =SUM(EH65:EX65) -> 0
D66: местный бюджет | E66: тыс.руб. | F66: ='[10]Данные для переноса'!F67 -> 0 | G66: ='[10]Данные для переноса'!G67 -> 0 | H66: ='[10]Данные для переноса'!H67 -> 0 | I66: ='[10]Данные для переноса'!I67 -> 0 | J66: ='[10]Данные для переноса'!J67 -> 0 | K66: ='[10]Данные для переноса'!K67 -> 0 | L66: ='[10]Данные для переноса'!L67 -> 0 | M66: ='[10]Данные для переноса'!M67 -> 0 | ... Z66: ='[10]Данные для переноса'!Z67 -> 0 | AV66: =AA66=F66 -> TRUE | AW66: =AB66=G66 -> TRUE | AX66: =AC66=H66 -> TRUE | AY66: =AD66=I66 -> TRUE | AZ66: =AE66=J66 -> TRUE | BA66: =AF66=K66 -> TRUE | BB66: =AG66=L66 -> TRUE | BC66: =AH66=M66 -> TRUE | ... BP66: =AU66=Z66 -> TRUE | BQ66: =SUM(J66:Z66) -> 0 | BR66: ='[10]Данные для переноса'!AB67 -> 0 | BS66: ='[10]Данные для переноса'!AC67 -> 0 | BT66: ='[10]Данные для переноса'!AD67 -> 0 | BU66: ='[10]Данные для переноса'!AE67 -> 0 | BV66: ='[10]Данные для переноса'!AF67 -> 0 | BW66: ='[10]Данные для переноса'!AG67 -> 0 | BX66: ='[10]Данные для переноса'!AH67 -> 0 | BY66: ='[10]Данные для переноса'!AI67 -> 0 | ... CL66: ='[10]Данные для переноса'!AV67 -> 0 | DH66: =CM66=BR66 -> TRUE | DI66: =CN66=BS66 -> TRUE | DJ66: =CO66=BT66 -> TRUE | DK66: =CP66=BU66 -> TRUE | DL66: =CQ66=BV66 -> TRUE | DM66: =CR66=BW66 -> TRUE | DN66: =CS66=BX66 -> TRUE | DO66: =CT66=BY66 -> TRUE | ... EB66: =DG66=CL66 -> TRUE | EC66: =SUM(BV66:CL66) -> 0 | ED66: =BR66-F66 -> 0 | EE66: =BS66-G66 -> 0 | EF66: =BT66-H66 -> 0 | EG66: =BU66-I66 -> 0 | EH66: =BV66-J66 -> 0 | EI66: =BW66-K66 -> 0 | EJ66: =BX66-L66 -> 0 | EK66: =BY66-M66 -> 0 | ... EX66: =CL66-Z66 -> 0 | EY66: =SUM(EH66:EX66) -> 0
C67: =C63+1 -> 43 | D67: НДС | E67: тыс.руб. | F67: ='[10]Данные для переноса'!F68 -> 26583.78 | G67: ='[10]Данные для переноса'!G68 -> 37540.566 | H67: ='[10]Данные для переноса'!H68 -> 27036.308 | I67: ='[10]Данные для переноса'!I68 -> 36153.541 | J67: ='[10]Данные для переноса'!J68 -> 37598.841 | K67: ='[10]Данные для переноса'!K68 -> 39101.952 | L67: ='[10]Данные для переноса'!L68 -> 40665.188 | M67: ='[10]Данные для переноса'!M68 -> 42290.953 | ... Z67: ='[10]Данные для переноса'!Z68 -> 70403.541 | AA67: 26583.78 | AB67: 37540.566 | AC67: 27036.308 | AD67: 36153.541 | AE67: 37598.841 | AF67: 39101.952 | AG67: 40665.188 | AH67: 42290.953 | AI67: 43981.749 | AJ67: 45740.176 | AK67: 47568.941 | AL67: 49470.857 | AM67: 51448.849 | AN67: 53505.96 | AO67: 55645.356 | AP67: 57870.328 | AQ67: 60184.299 | AR67: 62590.829 | AS67: 65093.62 | AT67: 67696.522 | AU67: 70403.541 | AV67: =AA67=F67 -> TRUE | AW67: =AB67=G67 -> TRUE | AX67: =AC67=H67 -> TRUE | AY67: =AD67=I67 -> TRUE | AZ67: =AE67=J67 -> TRUE | BA67: =AF67=K67 -> TRUE | BB67: =AG67=L67 -> TRUE | BC67: =AH67=M67 -> TRUE | ... BP67: =AU67=Z67 -> TRUE | BQ67: =SUM(J67:Z67) -> 890857.96 | BR67: ='[10]Данные для переноса'!AB68 -> 26583.78 | BS67: ='[10]Данные для переноса'!AC68 -> 37540.566 | BT67: ='[10]Данные для переноса'!AD68 -> 27036.308 | BU67: ='[10]Данные для переноса'!AE68 -> 34007.502 | BV67: ='[10]Данные для переноса'!AF68 -> 36794.631 | BW67: ='[10]Данные для переноса'!AG68 -> 38384.075 | BX67: ='[10]Данные для переноса'!AH68 -> 40119.006 | BY67: ='[10]Данные для переноса'!AI68 -> 42015.998 | ... CL67: ='[10]Данные для переноса'!AV68 -> 405895.29 | CM67: 26583.78 | CN67: 37540.566 | CO67: 27036.308 | CP67: 34007.502 | CQ67: 36794.631 | CR67: 38384.075 | CS67: 40119.006 | CT67: 42015.998 | CU67: 44093.582 | CV67: 46372.592 | CW67: 48876.468 | CX67: 51631.586 | CY67: 54667.637 | CZ67: 174113.15 | DA67: 353312.48 | DB67: 362549.54 | DC67: 370500.13 | DD67: 328147.5 | DE67: 387447.59 | DF67: 396475.66 | DG67: 405895.29 | DH67: =CM67=BR67 -> TRUE | DI67: =CN67=BS67 -> TRUE | DJ67: =CO67=BT67 -> TRUE | DK67: =CP67=BU67 -> TRUE | DL67: =CQ67=BV67 -> TRUE | DM67: =CR67=BW67 -> TRUE | DN67: =CS67=BX67 -> TRUE | DO67: =CT67=BY67 -> TRUE | ... EB67: =DG67=CL67 -> TRUE | EC67: =SUM(BV67:CL67) -> 3181396.9 | ED67: =BR67-F67 -> 0 | EE67: =BS67-G67 -> 0 | EF67: =BT67-H67 -> 0 | EG67: =BU67-I67 -> -2146.0393 | EH67: =BV67-J67 -> -804.20954 | EI67: =BW67-K67 -> -717.87723 | EJ67: =BX67-L67 -> -546.18211 | EK67: =BY67-M67 -> -274.95463 | ... EX67: =CL67-Z67 -> 335491.75 | EY67: =SUM(EH67:EX67) -> 2290539
D68: в том числе по уровням бюджета: федеральный бюджет | E68: тыс.руб. | F68: ='[10]Данные для переноса'!F69 -> 26583.78 | G68: ='[10]Данные для переноса'!G69 -> 37540.566 | H68: ='[10]Данные для переноса'!H69 -> 27036.308 | I68: ='[10]Данные для переноса'!I69 -> 36153.541 | J68: ='[10]Данные для переноса'!J69 -> 37598.841 | K68: ='[10]Данные для переноса'!K69 -> 39101.952 | L68: ='[10]Данные для переноса'!L69 -> 40665.188 | M68: ='[10]Данные для переноса'!M69 -> 42290.953 | ... Z68: ='[10]Данные для переноса'!Z69 -> 70403.541 | AA68: 26583.78 | AB68: 37540.566 | AC68: 27036.308 | AD68: 36153.541 | AE68: 37598.841 | AF68: 39101.952 | AG68: 40665.188 | AH68: 42290.953 | AI68: 43981.749 | AJ68: 45740.176 | AK68: 47568.941 | AL68: 49470.857 | AM68: 51448.849 | AN68: 53505.96 | AO68: 55645.356 | AP68: 57870.328 | AQ68: 60184.299 | AR68: 62590.829 | AS68: 65093.62 | AT68: 67696.522 | AU68: 70403.541 | AV68: =AA68=F68 -> TRUE | AW68: =AB68=G68 -> TRUE | AX68: =AC68=H68 -> TRUE | AY68: =AD68=I68 -> TRUE | AZ68: =AE68=J68 -> TRUE | BA68: =AF68=K68 -> TRUE | BB68: =AG68=L68 -> TRUE | BC68: =AH68=M68 -> TRUE | ... BP68: =AU68=Z68 -> TRUE | BQ68: =SUM(J68:Z68) -> 890857.96 | BR68: ='[10]Данные для переноса'!AB69 -> 26583.78 | BS68: ='[10]Данные для переноса'!AC69 -> 37540.566 | BT68: ='[10]Данные для переноса'!AD69 -> 27036.308 | BU68: ='[10]Данные для переноса'!AE69 -> 34007.502 | BV68: ='[10]Данные для переноса'!AF69 -> 36794.631 | BW68: ='[10]Данные для переноса'!AG69 -> 38384.075 | BX68: ='[10]Данные для переноса'!AH69 -> 40119.006 | BY68: ='[10]Данные для переноса'!AI69 -> 42015.998 | ... CL68: ='[10]Данные для переноса'!AV69 -> 405895.29 | CM68: 26583.78 | CN68: 37540.566 | CO68: 27036.308 | CP68: 34007.502 | CQ68: 36794.631 | CR68: 38384.075 | CS68: 40119.006 | CT68: 42015.998 | CU68: 44093.582 | CV68: 46372.592 | CW68: 48876.468 | CX68: 51631.586 | CY68: 54667.637 | CZ68: 174113.15 | DA68: 353312.48 | DB68: 362549.54 | DC68: 370500.13 | DD68: 328147.5 | DE68: 387447.59 | DF68: 396475.66 | DG68: 405895.29 | DH68: =CM68=BR68 -> TRUE | DI68: =CN68=BS68 -> TRUE | DJ68: =CO68=BT68 -> TRUE | DK68: =CP68=BU68 -> TRUE | DL68: =CQ68=BV68 -> TRUE | DM68: =CR68=BW68 -> TRUE | DN68: =CS68=BX68 -> TRUE | DO68: =CT68=BY68 -> TRUE | ... EB68: =DG68=CL68 -> TRUE | EC68: =SUM(BV68:CL68) -> 3181396.9 | ED68: =BR68-F68 -> 0 | EE68: =BS68-G68 -> 0 | EF68: =BT68-H68 -> 0 | EG68: =BU68-I68 -> -2146.0393 | EH68: =BV68-J68 -> -804.20954 | EI68: =BW68-K68 -> -717.87723 | EJ68: =BX68-L68 -> -546.18211 | EK68: =BY68-M68 -> -274.95463 | ... EX68: =CL68-Z68 -> 335491.75 | EY68: =SUM(EH68:EX68) -> 2290539
D69: региональный бюджет | E69: тыс.руб. | F69: ='[10]Данные для переноса'!F70 -> 0 | G69: ='[10]Данные для переноса'!G70 -> 0 | H69: ='[10]Данные для переноса'!H70 -> 0 | I69: ='[10]Данные для переноса'!I70 -> 0 | J69: ='[10]Данные для переноса'!J70 -> 0 | K69: ='[10]Данные для переноса'!K70 -> 0 | L69: ='[10]Данные для переноса'!L70 -> 0 | M69: ='[10]Данные для переноса'!M70 -> 0 | ... Z69: ='[10]Данные для переноса'!Z70 -> 0 | AV69: =AA69=F69 -> TRUE | AW69: =AB69=G69 -> TRUE | AX69: =AC69=H69 -> TRUE | AY69: =AD69=I69 -> TRUE | AZ69: =AE69=J69 -> TRUE | BA69: =AF69=K69 -> TRUE | BB69: =AG69=L69 -> TRUE | BC69: =AH69=M69 -> TRUE | ... BP69: =AU69=Z69 -> TRUE | BQ69: =SUM(J69:Z69) -> 0 | BR69: ='[10]Данные для переноса'!AB70 -> 0 | BS69: ='[10]Данные для переноса'!AC70 -> 0 | BT69: ='[10]Данные для переноса'!AD70 -> 0 | BU69: ='[10]Данные для переноса'!AE70 -> 0 | BV69: ='[10]Данные для переноса'!AF70 -> 0 | BW69: ='[10]Данные для переноса'!AG70 -> 0 | BX69: ='[10]Данные для переноса'!AH70 -> 0 | BY69: ='[10]Данные для переноса'!AI70 -> 0 | ... CL69: ='[10]Данные для переноса'!AV70 -> 0 | DH69: =CM69=BR69 -> TRUE | DI69: =CN69=BS69 -> TRUE | DJ69: =CO69=BT69 -> TRUE | DK69: =CP69=BU69 -> TRUE | DL69: =CQ69=BV69 -> TRUE | DM69: =CR69=BW69 -> TRUE | DN69: =CS69=BX69 -> TRUE | DO69: =CT69=BY69 -> TRUE | ... EB69: =DG69=CL69 -> TRUE | EC69: =SUM(BV69:CL69) -> 0 | ED69: =BR69-F69 -> 0 | EE69: =BS69-G69 -> 0 | EF69: =BT69-H69 -> 0 | EG69: =BU69-I69 -> 0 | EH69: =BV69-J69 -> 0 | EI69: =BW69-K69 -> 0 | EJ69: =BX69-L69 -> 0 | EK69: =BY69-M69 -> 0 | ... EX69: =CL69-Z69 -> 0 | EY69: =SUM(EH69:EX69) -> 0
D70: местный бюджет | E70: тыс.руб. | F70: ='[10]Данные для переноса'!F71 -> 0 | G70: ='[10]Данные для переноса'!G71 -> 0 | H70: ='[10]Данные для переноса'!H71 -> 0 | I70: ='[10]Данные для переноса'!I71 -> 0 | J70: ='[10]Данные для переноса'!J71 -> 0 | K70: ='[10]Данные для переноса'!K71 -> 0 | L70: ='[10]Данные для переноса'!L71 -> 0 | M70: ='[10]Данные для переноса'!M71 -> 0 | ... Z70: ='[10]Данные для переноса'!Z71 -> 0 | AV70: =AA70=F70 -> TRUE | AW70: =AB70=G70 -> TRUE | AX70: =AC70=H70 -> TRUE | AY70: =AD70=I70 -> TRUE | AZ70: =AE70=J70 -> TRUE | BA70: =AF70=K70 -> TRUE | BB70: =AG70=L70 -> TRUE | BC70: =AH70=M70 -> TRUE | ... BP70: =AU70=Z70 -> TRUE | BQ70: =SUM(J70:Z70) -> 0 | BR70: ='[10]Данные для переноса'!AB71 -> 0 | BS70: ='[10]Данные для переноса'!AC71 -> 0 | BT70: ='[10]Данные для переноса'!AD71 -> 0 | BU70: ='[10]Данные для переноса'!AE71 -> 0 | BV70: ='[10]Данные для переноса'!AF71 -> 0 | BW70: ='[10]Данные для переноса'!AG71 -> 0 | BX70: ='[10]Данные для переноса'!AH71 -> 0 | BY70: ='[10]Данные для переноса'!AI71 -> 0 | ... CL70: ='[10]Данные для переноса'!AV71 -> 0 | DH70: =CM70=BR70 -> TRUE | DI70: =CN70=BS70 -> TRUE | DJ70: =CO70=BT70 -> TRUE | DK70: =CP70=BU70 -> TRUE | DL70: =CQ70=BV70 -> TRUE | DM70: =CR70=BW70 -> TRUE | DN70: =CS70=BX70 -> TRUE | DO70: =CT70=BY70 -> TRUE | ... EB70: =DG70=CL70 -> TRUE | EC70: =SUM(BV70:CL70) -> 0 | ED70: =BR70-F70 -> 0 | EE70: =BS70-G70 -> 0 | EF70: =BT70-H70 -> 0 | EG70: =BU70-I70 -> 0 | EH70: =BV70-J70 -> 0 | EI70: =BW70-K70 -> 0 | EJ70: =BX70-L70 -> 0 | EK70: =BY70-M70 -> 0 | ... EX70: =CL70-Z70 -> 0 | EY70: =SUM(EH70:EX70) -> 0
C71: =C67+1 -> 44 | D71: Налог на прибыль | E71: тыс.руб. | F71: ='[10]Данные для переноса'!F72 -> 111941.94 | G71: ='[10]Данные для переноса'!G72 -> 128805.59 | H71: ='[10]Данные для переноса'!H72 -> 185242.29 | I71: ='[10]Данные для переноса'!I72 -> 0 | J71: ='[10]Данные для переноса'!J72 -> 0 | K71: ='[10]Данные для переноса'!K72 -> 0 | L71: ='[10]Данные для переноса'!L72 -> 0 | M71: ='[10]Данные для переноса'!M72 -> 0 | ... Z71: ='[10]Данные для переноса'!Z72 -> 0 | AA71: 111941.94 | AB71: 128805.59 | AC71: 185242.29 | AD71: 0 | AE71: 0 | AF71: 0 | AG71: 0 | AH71: 0 | AI71: 0 | AJ71: 0 | AK71: 0 | AL71: 0 | AM71: 0 | AN71: 0 | AO71: 0 | AP71: 0 | AQ71: 0 | AR71: 0 | AS71: 0 | AT71: 0 | AU71: 0 | AV71: =AA71=F71 -> TRUE | AW71: =AB71=G71 -> TRUE | AX71: =AC71=H71 -> TRUE | AY71: =AD71=I71 -> TRUE | AZ71: =AE71=J71 -> TRUE | BA71: =AF71=K71 -> TRUE | BB71: =AG71=L71 -> TRUE | BC71: =AH71=M71 -> TRUE | ... BP71: =AU71=Z71 -> TRUE | BQ71: =SUM(J71:Z71) -> 0 | BR71: ='[10]Данные для переноса'!AB72 -> 111941.94 | BS71: ='[10]Данные для переноса'!AC72 -> 128805.59 | BT71: ='[10]Данные для переноса'!AD72 -> 185242.29 | BU71: ='[10]Данные для переноса'!AE72 -> 0 | BV71: ='[10]Данные для переноса'!AF72 -> 0 | BW71: ='[10]Данные для переноса'!AG72 -> 0 | BX71: ='[10]Данные для переноса'!AH72 -> 0 | BY71: ='[10]Данные для переноса'!AI72 -> 0 | ... CL71: ='[10]Данные для переноса'!AV72 -> 0 | CM71: 111941.94 | CN71: 128805.59 | CO71: 185242.29 | CP71: 0 | CQ71: 0 | CR71: 0 | CS71: 0 | CT71: 0 | CU71: 0 | CV71: 0 | CW71: 0 | CX71: 0 | CY71: 0 | CZ71: 1870.098 | DA71: 1870.098 | DB71: 0 | DC71: 0 | DD71: 0 | DE71: 0 | DF71: 0 | DG71: 0 | DH71: =CM71=BR71 -> TRUE | DI71: =CN71=BS71 -> TRUE | DJ71: =CO71=BT71 -> TRUE | DK71: =CP71=BU71 -> TRUE | DL71: =CQ71=BV71 -> TRUE | DM71: =CR71=BW71 -> TRUE | DN71: =CS71=BX71 -> TRUE | DO71: =CT71=BY71 -> TRUE | ... EB71: =DG71=CL71 -> TRUE | EC71: =SUM(BV71:CL71) -> 3740.196 | ED71: =BR71-F71 -> 0 | EE71: =BS71-G71 -> 0 | EF71: =BT71-H71 -> 0 | EG71: =BU71-I71 -> 0 | EH71: =BV71-J71 -> 0 | EI71: =BW71-K71 -> 0 | EJ71: =BX71-L71 -> 0 | EK71: =BY71-M71 -> 0 | ... EX71: =CL71-Z71 -> 0 | EY71: =SUM(EH71:EX71) -> 3740.196
D72: в том числе по уровням бюджета: федеральный бюджет | E72: тыс.руб. | F72: ='[10]Данные для переноса'!F73 -> 31343.744 | G72: ='[10]Данные для переноса'!G73 -> 36065.564 | H72: ='[10]Данные для переноса'!H73 -> 51867.84 | I72: ='[10]Данные для переноса'!I73 -> 0 | J72: ='[10]Данные для переноса'!J73 -> 0 | K72: ='[10]Данные для переноса'!K73 -> 0 | L72: ='[10]Данные для переноса'!L73 -> 0 | M72: ='[10]Данные для переноса'!M73 -> 0 | ... Z72: ='[10]Данные для переноса'!Z73 -> 0 | AA72: 31343.744 | AB72: 36065.564 | AC72: 51867.84 | AD72: 0 | AE72: 0 | AF72: 0 | AG72: 0 | AH72: 0 | AI72: 0 | AJ72: 0 | AK72: 0 | AL72: 0 | AM72: 0 | AN72: 0 | AO72: 0 | AP72: 0 | AQ72: 0 | AR72: 0 | AS72: 0 | AT72: 0 | AU72: 0 | AV72: =AA72=F72 -> TRUE | AW72: =AB72=G72 -> TRUE | AX72: =AC72=H72 -> TRUE | AY72: =AD72=I72 -> TRUE | AZ72: =AE72=J72 -> TRUE | BA72: =AF72=K72 -> TRUE | BB72: =AG72=L72 -> TRUE | BC72: =AH72=M72 -> TRUE | ... BP72: =AU72=Z72 -> TRUE | BQ72: =SUM(J72:Z72) -> 0 | BR72: ='[10]Данные для переноса'!AB73 -> 31343.744 | BS72: ='[10]Данные для переноса'!AC73 -> 36065.564 | BT72: ='[10]Данные для переноса'!AD73 -> 51867.84 | BU72: ='[10]Данные для переноса'!AE73 -> 0 | BV72: ='[10]Данные для переноса'!AF73 -> 0 | BW72: ='[10]Данные для переноса'!AG73 -> 0 | BX72: ='[10]Данные для переноса'!AH73 -> 0 | BY72: ='[10]Данные для переноса'!AI73 -> 0 | ... CL72: ='[10]Данные для переноса'!AV73 -> 0 | CM72: 31343.744 | CN72: 36065.564 | CO72: 51867.84 | CP72: 0 | CQ72: 0 | CR72: 0 | CS72: 0 | CT72: 0 | CU72: 0 | CV72: 0 | CW72: 0 | CX72: 0 | CY72: 0 | CZ72: 598.43136 | DA72: 598.43136 | DB72: 0 | DC72: 0 | DD72: 0 | DE72: 0 | DF72: 0 | DG72: 0 | DH72: =CM72=BR72 -> TRUE | DI72: =CN72=BS72 -> TRUE | DJ72: =CO72=BT72 -> TRUE | DK72: =CP72=BU72 -> TRUE | DL72: =CQ72=BV72 -> TRUE | DM72: =CR72=BW72 -> TRUE | DN72: =CS72=BX72 -> TRUE | DO72: =CT72=BY72 -> TRUE | ... EB72: =DG72=CL72 -> TRUE | EC72: =SUM(BV72:CL72) -> 1196.8627 | ED72: =BR72-F72 -> 0 | EE72: =BS72-G72 -> 0 | EF72: =BT72-H72 -> 0 | EG72: =BU72-I72 -> 0 | EH72: =BV72-J72 -> 0 | EI72: =BW72-K72 -> 0 | EJ72: =BX72-L72 -> 0 | EK72: =BY72-M72 -> 0 | ... EX72: =CL72-Z72 -> 0 | EY72: =SUM(EH72:EX72) -> 1196.8627
D73: региональный бюджет | E73: тыс.руб. | F73: ='[10]Данные для переноса'!F74 -> 80598.199 | G73: ='[10]Данные для переноса'!G74 -> 92740.022 | H73: ='[10]Данные для переноса'!H74 -> 133374.45 | I73: ='[10]Данные для переноса'!I74 -> 0 | J73: ='[10]Данные для переноса'!J74 -> 0 | K73: ='[10]Данные для переноса'!K74 -> 0 | L73: ='[10]Данные для переноса'!L74 -> 0 | M73: ='[10]Данные для переноса'!M74 -> 0 | ... Z73: ='[10]Данные для переноса'!Z74 -> 0 | AA73: 80598.199 | AB73: 92740.022 | AC73: 133374.45 | AD73: 0 | AE73: 0 | AF73: 0 | AG73: 0 | AH73: 0 | AI73: 0 | AJ73: 0 | AK73: 0 | AL73: 0 | AM73: 0 | AN73: 0 | AO73: 0 | AP73: 0 | AQ73: 0 | AR73: 0 | AS73: 0 | AT73: 0 | AU73: 0 | AV73: =AA73=F73 -> TRUE | AW73: =AB73=G73 -> TRUE | AX73: =AC73=H73 -> TRUE | AY73: =AD73=I73 -> TRUE | AZ73: =AE73=J73 -> TRUE | BA73: =AF73=K73 -> TRUE | BB73: =AG73=L73 -> TRUE | BC73: =AH73=M73 -> TRUE | ... BP73: =AU73=Z73 -> TRUE | BQ73: =SUM(J73:Z73) -> 0 | BR73: ='[10]Данные для переноса'!AB74 -> 80598.199 | BS73: ='[10]Данные для переноса'!AC74 -> 92740.022 | BT73: ='[10]Данные для переноса'!AD74 -> 133374.45 | BU73: ='[10]Данные для переноса'!AE74 -> 0 | BV73: ='[10]Данные для переноса'!AF74 -> 0 | BW73: ='[10]Данные для переноса'!AG74 -> 0 | BX73: ='[10]Данные для переноса'!AH74 -> 0 | BY73: ='[10]Данные для переноса'!AI74 -> 0 | ... CL73: ='[10]Данные для переноса'!AV74 -> 0 | CM73: 80598.199 | CN73: 92740.022 | CO73: 133374.45 | CP73: 0 | CQ73: 0 | CR73: 0 | CS73: 0 | CT73: 0 | CU73: 0 | CV73: 0 | CW73: 0 | CX73: 0 | CY73: 0 | CZ73: 1271.6666 | DA73: 1271.6666 | DB73: 0 | DC73: 0 | DD73: 0 | DE73: 0 | DF73: 0 | DG73: 0 | DH73: =CM73=BR73 -> TRUE | DI73: =CN73=BS73 -> TRUE | DJ73: =CO73=BT73 -> TRUE | DK73: =CP73=BU73 -> TRUE | DL73: =CQ73=BV73 -> TRUE | DM73: =CR73=BW73 -> TRUE | DN73: =CS73=BX73 -> TRUE | DO73: =CT73=BY73 -> TRUE | ... EB73: =DG73=CL73 -> TRUE | EC73: =SUM(BV73:CL73) -> 2543.3333 | ED73: =BR73-F73 -> 0 | EE73: =BS73-G73 -> 0 | EF73: =BT73-H73 -> 0 | EG73: =BU73-I73 -> 0 | EH73: =BV73-J73 -> 0 | EI73: =BW73-K73 -> 0 | EJ73: =BX73-L73 -> 0 | EK73: =BY73-M73 -> 0 | ... EX73: =CL73-Z73 -> 0 | EY73: =SUM(EH73:EX73) -> 2543.3333
D74: местный бюджет | E74: тыс.руб. | F74: ='[10]Данные для переноса'!F75 -> 0 | G74: ='[10]Данные для переноса'!G75 -> 0 | H74: ='[10]Данные для переноса'!H75 -> 0 | I74: ='[10]Данные для переноса'!I75 -> 0 | J74: ='[10]Данные для переноса'!J75 -> 0 | K74: ='[10]Данные для переноса'!K75 -> 0 | L74: ='[10]Данные для переноса'!L75 -> 0 | M74: ='[10]Данные для переноса'!M75 -> 0 | ... Z74: ='[10]Данные для переноса'!Z75 -> 0 | AV74: =AA74=F74 -> TRUE | AW74: =AB74=G74 -> TRUE | AX74: =AC74=H74 -> TRUE | AY74: =AD74=I74 -> TRUE | AZ74: =AE74=J74 -> TRUE | BA74: =AF74=K74 -> TRUE | BB74: =AG74=L74 -> TRUE | BC74: =AH74=M74 -> TRUE | ... BP74: =AU74=Z74 -> TRUE | BQ74: =SUM(J74:Z74) -> 0 | BR74: ='[10]Данные для переноса'!AB75 -> 0 | BS74: ='[10]Данные для переноса'!AC75 -> 0 | BT74: ='[10]Данные для переноса'!AD75 -> 0 | BU74: ='[10]Данные для переноса'!AE75 -> 0 | BV74: ='[10]Данные для переноса'!AF75 -> 0 | BW74: ='[10]Данные для переноса'!AG75 -> 0 | BX74: ='[10]Данные для переноса'!AH75 -> 0 | BY74: ='[10]Данные для переноса'!AI75 -> 0 | ... CL74: ='[10]Данные для переноса'!AV75 -> 0 | DH74: =CM74=BR74 -> TRUE | DI74: =CN74=BS74 -> TRUE | DJ74: =CO74=BT74 -> TRUE | DK74: =CP74=BU74 -> TRUE | DL74: =CQ74=BV74 -> TRUE | DM74: =CR74=BW74 -> TRUE | DN74: =CS74=BX74 -> TRUE | DO74: =CT74=BY74 -> TRUE | ... EB74: =DG74=CL74 -> TRUE | EC74: =SUM(BV74:CL74) -> 0 | ED74: =BR74-F74 -> 0 | EE74: =BS74-G74 -> 0 | EF74: =BT74-H74 -> 0 | EG74: =BU74-I74 -> 0 | EH74: =BV74-J74 -> 0 | EI74: =BW74-K74 -> 0 | EJ74: =BX74-L74 -> 0 | EK74: =BY74-M74 -> 0 | ... EX74: =CL74-Z74 -> 0 | EY74: =SUM(EH74:EX74) -> 0
C75: =C71+1 -> 45 | D75: Налог на доходы физических лиц | E75: тыс.руб. | F75: ='[10]Данные для переноса'!F76 -> 652970.67 | G75: ='[10]Данные для переноса'!G76 -> 791141.35 | H75: ='[10]Данные для переноса'!H76 -> 975718.16 | I75: ='[10]Данные для переноса'!I76 -> 1051512.1 | J75: ='[10]Данные для переноса'!J76 -> 1123819.8 | K75: ='[10]Данные для переноса'!K76 -> 1197866.2 | L75: ='[10]Данные для переноса'!L76 -> 1249963.6 | M75: ='[10]Данные для переноса'!M76 -> 1304364.9 | ... Z75: ='[10]Данные для переноса'!Z76 -> 2307237.5 | AA75: 652970.67 | AB75: 791141.35 | AC75: 975718.16 | AD75: 1051512.1 | AE75: 1123819.8 | AF75: 1197866.2 | AG75: 1249963.6 | AH75: 1304364.9 | AI75: 1361624.9 | AJ75: 1421590.3 | AK75: 1484403.1 | AL75: 1550213.9 | AM75: 1619182.2 | AN75: 1691477.1 | AO75: 1767278.1 | AP75: 1846775.5 | AQ75: 1930171.4 | AR75: 2017680.4 | AS75: 2109530.3 | AT75: 2205963.5 | AU75: 2307237.5 | AV75: =AA75=F75 -> TRUE | AW75: =AB75=G75 -> TRUE | AX75: =AC75=H75 -> TRUE | AY75: =AD75=I75 -> TRUE | AZ75: =AE75=J75 -> TRUE | BA75: =AF75=K75 -> TRUE | BB75: =AG75=L75 -> TRUE | BC75: =AH75=M75 -> TRUE | ... BP75: =AU75=Z75 -> TRUE | BQ75: =SUM(J75:Z75) -> 28189143 | BR75: ='[10]Данные для переноса'!AB76 -> 652970.67 | BS75: ='[10]Данные для переноса'!AC76 -> 791141.35 | BT75: ='[10]Данные для переноса'!AD76 -> 975718.16 | BU75: ='[10]Данные для переноса'!AE76 -> 1092857.9 | BV75: ='[10]Данные для переноса'!AF76 -> 1191592.5 | BW75: ='[10]Данные для переноса'!AG76 -> 1279023.3 | BX75: ='[10]Данные для переноса'!AH76 -> 1343608.6 | BY75: ='[10]Данные для переноса'!AI76 -> 1406616.6 | ... CL75: ='[10]Данные для переноса'!AV76 -> 2562911.5 | CM75: 652970.67 | CN75: 791141.35 | CO75: 975718.16 | CP75: 1092857.9 | CQ75: 1191592.5 | CR75: 1279023.3 | CS75: 1343608.6 | CT75: 1406616.6 | CU75: 1470804.7 | CV75: 1537991.9 | CW75: 1608478.4 | CX75: 1682441.3 | CY75: 1760068.1 | CZ75: 1849976.5 | DA75: 1944894.6 | DB75: 2036523.8 | DC75: 2131913.7 | DD75: 2231693.4 | DE75: 2336926.4 | DF75: 2446878.6 | DG75: 2562911.5 | DH75: =CM75=BR75 -> TRUE | DI75: =CN75=BS75 -> TRUE | DJ75: =CO75=BT75 -> TRUE | DK75: =CP75=BU75 -> TRUE | DL75: =CQ75=BV75 -> TRUE | DM75: =CR75=BW75 -> TRUE | DN75: =CS75=BX75 -> TRUE | DO75: =CT75=BY75 -> TRUE | ... EB75: =DG75=CL75 -> TRUE | EC75: =SUM(BV75:CL75) -> 30822344 | ED75: =BR75-F75 -> 0 | EE75: =BS75-G75 -> 0 | EF75: =BT75-H75 -> 0 | EG75: =BU75-I75 -> 41345.822 | EH75: =BV75-J75 -> 67772.711 | EI75: =BW75-K75 -> 81157.115 | EJ75: =BX75-L75 -> 93644.988 | EK75: =BY75-M75 -> 102251.62 | ... EX75: =CL75-Z75 -> 255673.99 | EY75: =SUM(EH75:EX75) -> 2633201
D76: в том числе по уровням бюджета: федеральный бюджет | E76: тыс.руб. | F76: ='[10]Данные для переноса'!F77 -> 0 | G76: ='[10]Данные для переноса'!G77 -> 0 | H76: ='[10]Данные для переноса'!H77 -> 0 | I76: ='[10]Данные для переноса'!I77 -> 0 | J76: ='[10]Данные для переноса'!J77 -> 0 | K76: ='[10]Данные для переноса'!K77 -> 0 | L76: ='[10]Данные для переноса'!L77 -> 0 | M76: ='[10]Данные для переноса'!M77 -> 0 | ... Z76: ='[10]Данные для переноса'!Z77 -> 0 | AV76: =AA76=F76 -> TRUE | AW76: =AB76=G76 -> TRUE | AX76: =AC76=H76 -> TRUE | AY76: =AD76=I76 -> TRUE | AZ76: =AE76=J76 -> TRUE | BA76: =AF76=K76 -> TRUE | BB76: =AG76=L76 -> TRUE | BC76: =AH76=M76 -> TRUE | ... BP76: =AU76=Z76 -> TRUE | BQ76: =SUM(J76:Z76) -> 0 | BR76: ='[10]Данные для переноса'!AB77 -> 0 | BS76: ='[10]Данные для переноса'!AC77 -> 0 | BT76: ='[10]Данные для переноса'!AD77 -> 0 | BU76: ='[10]Данные для переноса'!AE77 -> 0 | BV76: ='[10]Данные для переноса'!AF77 -> 0 | BW76: ='[10]Данные для переноса'!AG77 -> 0 | BX76: ='[10]Данные для переноса'!AH77 -> 0 | BY76: ='[10]Данные для переноса'!AI77 -> 0 | ... CL76: ='[10]Данные для переноса'!AV77 -> 0 | DH76: =CM76=BR76 -> TRUE | DI76: =CN76=BS76 -> TRUE | DJ76: =CO76=BT76 -> TRUE | DK76: =CP76=BU76 -> TRUE | DL76: =CQ76=BV76 -> TRUE | DM76: =CR76=BW76 -> TRUE | DN76: =CS76=BX76 -> TRUE | DO76: =CT76=BY76 -> TRUE | ... EB76: =DG76=CL76 -> TRUE | EC76: =SUM(BV76:CL76) -> 0 | ED76: =BR76-F76 -> 0 | EE76: =BS76-G76 -> 0 | EF76: =BT76-H76 -> 0 | EG76: =BU76-I76 -> 0 | EH76: =BV76-J76 -> 0 | EI76: =BW76-K76 -> 0 | EJ76: =BX76-L76 -> 0 | EK76: =BY76-M76 -> 0 | ... EX76: =CL76-Z76 -> 0 | EY76: =SUM(EH76:EX76) -> 0
D77: региональный бюджет | E77: тыс.руб. | F77: ='[10]Данные для переноса'!F78 -> 555025.07 | G77: ='[10]Данные для переноса'!G78 -> 672470.15 | H77: ='[10]Данные для переноса'!H78 -> 829360.44 | I77: ='[10]Данные для переноса'!I78 -> 893785.27 | J77: ='[10]Данные для переноса'!J78 -> 955246.8 | K77: ='[10]Данные для переноса'!K78 -> 1018186.2 | L77: ='[10]Данные для переноса'!L78 -> 1062469.1 | M77: ='[10]Данные для переноса'!M78 -> 1108710.2 | ... Z77: ='[10]Данные для переноса'!Z78 -> 1961151.9 | AA77: 555025.07 | AB77: 672470.15 | AC77: 829360.44 | AD77: 893785.27 | AE77: 955246.8 | AF77: 1018186.2 | AG77: 1062469.1 | AH77: 1108710.2 | AI77: 1157381.2 | AJ77: 1208351.8 | AK77: 1261742.7 | AL77: 1317681.8 | AM77: 1376304.9 | AN77: 1437755.6 | AO77: 1502186.4 | AP77: 1569759.2 | AQ77: 1640645.7 | AR77: 1715028.3 | AS77: 1793100.8 | AT77: 1875069 | AU77: 1961151.9 | AV77: =AA77=F77 -> TRUE | AW77: =AB77=G77 -> TRUE | AX77: =AC77=H77 -> TRUE | AY77: =AD77=I77 -> TRUE | AZ77: =AE77=J77 -> TRUE | BA77: =AF77=K77 -> TRUE | BB77: =AG77=L77 -> TRUE | BC77: =AH77=M77 -> TRUE | ... BP77: =AU77=Z77 -> TRUE | BQ77: =SUM(J77:Z77) -> 23960772 | BR77: ='[10]Данные для переноса'!AB78 -> 555025.07 | BS77: ='[10]Данные для переноса'!AC78 -> 672470.15 | BT77: ='[10]Данные для переноса'!AD78 -> 829360.44 | BU77: ='[10]Данные для переноса'!AE78 -> 928929.22 | BV77: ='[10]Данные для переноса'!AF78 -> 1012853.6 | BW77: ='[10]Данные для переноса'!AG78 -> 1087169.8 | BX77: ='[10]Данные для переноса'!AH78 -> 1142067.3 | BY77: ='[10]Данные для переноса'!AI78 -> 1195624.1 | ... CL77: ='[10]Данные для переноса'!AV78 -> 2178474.8 | CM77: 555025.07 | CN77: 672470.15 | CO77: 829360.44 | CP77: 928929.22 | CQ77: 1012853.6 | CR77: 1087169.8 | CS77: 1142067.3 | CT77: 1195624.1 | CU77: 1250184 | CV77: 1307293.1 | CW77: 1367206.6 | CX77: 1430075.1 | CY77: 1496057.9 | CZ77: 1572480 | DA77: 1653160.4 | DB77: 1731045.3 | DC77: 1812126.7 | DD77: 1896939.4 | DE77: 1986387.5 | DF77: 2079846.8 | DG77: 2178474.8 | DH77: =CM77=BR77 -> TRUE | DI77: =CN77=BS77 -> TRUE | DJ77: =CO77=BT77 -> TRUE | DK77: =CP77=BU77 -> TRUE | DL77: =CQ77=BV77 -> TRUE | DM77: =CR77=BW77 -> TRUE | DN77: =CS77=BX77 -> TRUE | DO77: =CT77=BY77 -> TRUE | ... EB77: =DG77=CL77 -> TRUE | EC77: =SUM(BV77:CL77) -> 26198992 | ED77: =BR77-F77 -> 0 | EE77: =BS77-G77 -> 0 | EF77: =BT77-H77 -> 0 | EG77: =BU77-I77 -> 35143.948 | EH77: =BV77-J77 -> 57606.804 | EI77: =BW77-K77 -> 68983.548 | EJ77: =BX77-L77 -> 79598.24 | EK77: =BY77-M77 -> 86913.876 | ... EX77: =CL77-Z77 -> 217322.89 | EY77: =SUM(EH77:EX77) -> 2238220.8
D78: местный бюджет | E78: тыс.руб. | F78: ='[10]Данные для переноса'!F79 -> 97945.6 | G78: ='[10]Данные для переноса'!G79 -> 118671.2 | H78: ='[10]Данные для переноса'!H79 -> 146357.72 | I78: ='[10]Данные для переноса'!I79 -> 157726.81 | J78: ='[10]Данные для переноса'!J79 -> 168572.96 | K78: ='[10]Данные для переноса'!K79 -> 179679.92 | L78: ='[10]Данные для переноса'!L79 -> 187494.54 | M78: ='[10]Данные для переноса'!M79 -> 195654.74 | ... Z78: ='[10]Данные для переноса'!Z79 -> 346085.63 | AA78: 97945.6 | AB78: 118671.2 | AC78: 146357.72 | AD78: 157726.81 | AE78: 168572.96 | AF78: 179679.92 | AG78: 187494.54 | AH78: 195654.74 | AI78: 204243.74 | AJ78: 213238.55 | AK78: 222660.47 | AL78: 232532.09 | AM78: 242877.33 | AN78: 253721.57 | AO78: 265091.72 | AP78: 277016.33 | AQ78: 289525.71 | AR78: 302652.05 | AS78: 316429.55 | AT78: 330894.53 | AU78: 346085.63 | AV78: =AA78=F78 -> TRUE | AW78: =AB78=G78 -> TRUE | AX78: =AC78=H78 -> TRUE | AY78: =AD78=I78 -> TRUE | AZ78: =AE78=J78 -> TRUE | BA78: =AF78=K78 -> TRUE | BB78: =AG78=L78 -> TRUE | BC78: =AH78=M78 -> TRUE | ... BP78: =AU78=Z78 -> TRUE | BQ78: =SUM(J78:Z78) -> 4228371.4 | BR78: ='[10]Данные для переноса'!AB79 -> 97945.6 | BS78: ='[10]Данные для переноса'!AC79 -> 118671.2 | BT78: ='[10]Данные для переноса'!AD79 -> 146357.72 | BU78: ='[10]Данные для переноса'!AE79 -> 163928.69 | BV78: ='[10]Данные для переноса'!AF79 -> 178738.87 | BW78: ='[10]Данные для переноса'!AG79 -> 191853.49 | BX78: ='[10]Данные для переноса'!AH79 -> 201541.29 | BY78: ='[10]Данные для переноса'!AI79 -> 210992.48 | ... CL78: ='[10]Данные для переноса'!AV79 -> 384436.73 | CM78: 97945.6 | CN78: 118671.2 | CO78: 146357.72 | CP78: 163928.69 | CQ78: 178738.87 | CR78: 191853.49 | CS78: 201541.29 | CT78: 210992.48 | CU78: 220620.7 | CV78: 230698.79 | CW78: 241271.76 | CX78: 252366.19 | CY78: 264010.21 | CZ78: 277496.47 | DA78: 291734.19 | DB78: 305478.58 | DC78: 319787.06 | DD78: 334754.01 | DE78: 350538.97 | DF78: 367031.79 | DG78: 384436.73 | DH78: =CM78=BR78 -> TRUE | DI78: =CN78=BS78 -> TRUE | DJ78: =CO78=BT78 -> TRUE | DK78: =CP78=BU78 -> TRUE | DL78: =CQ78=BV78 -> TRUE | DM78: =CR78=BW78 -> TRUE | DN78: =CS78=BX78 -> TRUE | DO78: =CT78=BY78 -> TRUE | ... EB78: =DG78=CL78 -> TRUE | EC78: =SUM(BV78:CL78) -> 4623351.6 | ED78: =BR78-F78 -> 0 | EE78: =BS78-G78 -> 0 | EF78: =BT78-H78 -> 0 | EG78: =BU78-I78 -> 6201.8733 | EH78: =BV78-J78 -> 10165.907 | EI78: =BW78-K78 -> 12173.567 | EJ78: =BX78-L78 -> 14046.748 | EK78: =BY78-M78 -> 15337.743 | ... EX78: =CL78-Z78 -> 38351.099 | EY78: =SUM(EH78:EX78) -> 394980.14
C79: =C75+1 -> 46 | D79: Страховые взносы | E79: тыс.руб. | F79: ='[10]Данные для переноса'!F80 -> 1307828.7 | G79: ='[10]Данные для переноса'!G80 -> 1616192.9 | H79: ='[10]Данные для переноса'!H80 -> 1992507.8 | I79: ='[10]Данные для переноса'!I80 -> 2147268.4 | J79: ='[10]Данные для переноса'!J80 -> 2294909.9 | K79: ='[10]Данные для переноса'!K80 -> 2446102.1 | L79: ='[10]Данные для переноса'!L80 -> 2552485.5 | M79: ='[10]Данные для переноса'!M80 -> 2663573.4 | ... Z79: ='[10]Данные для переноса'!Z80 -> 4711416.7 | AA79: 1307828.7 | AB79: 1616192.9 | AC79: 1992507.8 | AD79: 2147268.4 | AE79: 2294909.9 | AF79: 2446102.1 | AG79: 2552485.5 | AH79: 2663573.4 | AI79: 2780498.4 | AJ79: 2902947.5 | AK79: 3031210.9 | AL79: 3165596 | AM79: 3306428.4 | AN79: 3454053.5 | AO79: 3608837.6 | AP79: 3771169.5 | AQ79: 3941461.7 | AR79: 4120152.2 | AS79: 4307706.7 | AT79: 4504619.6 | AU79: 4711416.7 | AV79: =AA79=F79 -> TRUE | AW79: =AB79=G79 -> TRUE | AX79: =AC79=H79 -> TRUE | AY79: =AD79=I79 -> TRUE | AZ79: =AE79=J79 -> TRUE | BA79: =AF79=K79 -> TRUE | BB79: =AG79=L79 -> TRUE | BC79: =AH79=M79 -> TRUE | ... BP79: =AU79=Z79 -> TRUE | BQ79: =SUM(J79:Z79) -> 57563170 | BR79: ='[10]Данные для переноса'!AB80 -> 1307828.7 | BS79: ='[10]Данные для переноса'!AC80 -> 1616192.9 | BT79: ='[10]Данные для переноса'!AD80 -> 1992507.8 | BU79: ='[10]Данные для переноса'!AE80 -> 2232398.9 | BV79: ='[10]Данные для переноса'!AF80 -> 2479047.3 | BW79: ='[10]Данные для переноса'!AG80 -> 2656908.3 | BX79: ='[10]Данные для переноса'!AH80 -> 2792128.2 | BY79: ='[10]Данные для переноса'!AI80 -> 2919959.7 | ... CL79: ='[10]Данные для переноса'!AV80 -> 5256637 | CM79: 1307828.7 | CN79: 1616192.9 | CO79: 1992507.8 | CP79: 2232398.9 | CQ79: 2479047.3 | CR79: 2656908.3 | CS79: 2792128.2 | CT79: 2919959.7 | CU79: 3050086.9 | CV79: 3186215.6 | CW79: 3328950.7 | CX79: 3478645.3 | CY79: 3635673.5 | CZ79: 3817630 | DA79: 4009649.6 | DB79: 4194768.3 | DC79: 4387377.6 | DD79: 4588750.5 | DE79: 4801046.2 | DF79: 5022752.9 | DG79: 5256637 | DH79: =CM79=BR79 -> TRUE | DI79: =CN79=BS79 -> TRUE | DJ79: =CO79=BT79 -> TRUE | DK79: =CP79=BU79 -> TRUE | DL79: =CQ79=BV79 -> TRUE | DM79: =CR79=BW79 -> TRUE | DN79: =CS79=BX79 -> TRUE | DO79: =CT79=BY79 -> TRUE | ... EB79: =DG79=CL79 -> TRUE | EC79: =SUM(BV79:CL79) -> 63606228 | ED79: =BR79-F79 -> 0 | EE79: =BS79-G79 -> 0 | EF79: =BT79-H79 -> 0 | EG79: =BU79-I79 -> 85130.481 | EH79: =BV79-J79 -> 184137.32 | EI79: =BW79-K79 -> 210806.29 | EJ79: =BX79-L79 -> 239642.64 | EK79: =BY79-M79 -> 256386.37 | ... EX79: =CL79-Z79 -> 545220.32 | EY79: =SUM(EH79:EX79) -> 6043058.2
C80: =C79+1 -> 47 | D80: Прочие налоги, отчисления | E80: тыс.руб. | F80: ='[10]Данные для переноса'!F81 -> 443997.63 | G80: ='[10]Данные для переноса'!G81 -> 483379.16 | H80: ='[10]Данные для переноса'!H81 -> 520079.75 | I80: ='[10]Данные для переноса'!I81 -> 542022.81 | J80: ='[10]Данные для переноса'!J81 -> 562405.47 | K80: ='[10]Данные для переноса'!K81 -> 583603.44 | L80: ='[10]Данные для переноса'!L81 -> 605649.33 | M80: ='[10]Данные для переноса'!M81 -> 628577.05 | ... Z80: ='[10]Данные для переноса'!Z81 -> 1025041.2 | AA80: 443997.63 | AB80: 483379.16 | AC80: 520079.75 | AD80: 542022.81 | AE80: 562405.47 | AF80: 583603.44 | AG80: 605649.33 | AH80: 628577.05 | AI80: 652421.89 | AJ80: 677220.51 | AK80: 703011.08 | AL80: 729833.27 | AM80: 757728.36 | AN80: 786739.24 | AO80: 816910.56 | AP80: 848288.73 | AQ80: 880922.03 | AR80: 914860.66 | AS80: 950156.84 | AT80: 986864.86 | AU80: 1025041.2 | AV80: =AA80=F80 -> TRUE | AW80: =AB80=G80 -> TRUE | AX80: =AC80=H80 -> TRUE | AY80: =AD80=I80 -> TRUE | AZ80: =AE80=J80 -> TRUE | BA80: =AF80=K80 -> TRUE | BB80: =AG80=L80 -> TRUE | BC80: =AH80=M80 -> TRUE | ... BP80: =AU80=Z80 -> TRUE | BQ80: =SUM(J80:Z80) -> 13110235 | BR80: ='[10]Данные для переноса'!AB81 -> 443997.63 | BS80: ='[10]Данные для переноса'!AC81 -> 483379.16 | BT80: ='[10]Данные для переноса'!AD81 -> 520079.75 | BU80: ='[10]Данные для переноса'!AE81 -> 542022.81 | BV80: ='[10]Данные для переноса'!AF81 -> 562405.47 | BW80: ='[10]Данные для переноса'!AG81 -> 583603.44 | BX80: ='[10]Данные для переноса'!AH81 -> 605649.33 | BY80: ='[10]Данные для переноса'!AI81 -> 628577.05 | ... CL80: ='[10]Данные для переноса'!AV81 -> 1025041.2 | CM80: 443997.63 | CN80: 483379.16 | CO80: 520079.75 | CP80: 542022.81 | CQ80: 562405.47 | CR80: 583603.44 | CS80: 605649.33 | CT80: 628577.05 | CU80: 652421.89 | CV80: 677220.51 | CW80: 703011.08 | CX80: 729833.27 | CY80: 757728.36 | CZ80: 786739.24 | DA80: 816910.56 | DB80: 848288.73 | DC80: 880922.03 | DD80: 914860.66 | DE80: 950156.84 | DF80: 986864.86 | DG80: 1025041.2 | DH80: =CM80=BR80 -> TRUE | DI80: =CN80=BS80 -> TRUE | DJ80: =CO80=BT80 -> TRUE | DK80: =CP80=BU80 -> TRUE | DL80: =CQ80=BV80 -> TRUE | DM80: =CR80=BW80 -> TRUE | DN80: =CS80=BX80 -> TRUE | DO80: =CT80=BY80 -> TRUE | ... EB80: =DG80=CL80 -> TRUE | EC80: =SUM(BV80:CL80) -> 13110235 | ED80: =BR80-F80 -> 0 | EE80: =BS80-G80 -> 0 | EF80: =BT80-H80 -> 0 | EG80: =BU80-I80 -> 0 | EH80: =BV80-J80 -> 0 | EI80: =BW80-K80 -> 0 | EJ80: =BX80-L80 -> 0 | EK80: =BY80-M80 -> 0 | ... EX80: =CL80-Z80 -> 0 | EY80: =SUM(EH80:EX80) -> 0
D81: Среднемесячная зарплата | AV81: =AA81=F81 -> TRUE | AW81: =AB81=G81 -> TRUE | AX81: =AC81=H81 -> TRUE | AY81: =AD81=I81 -> TRUE | AZ81: =AE81=J81 -> TRUE | BA81: =AF81=K81 -> TRUE | BB81: =AG81=L81 -> TRUE | BC81: =AH81=M81 -> TRUE | ... BP81: =AU81=Z81 -> TRUE | DH81: =CM81=BR81 -> TRUE | DI81: =CN81=BS81 -> TRUE | DJ81: =CO81=BT81 -> TRUE | DK81: =CP81=BU81 -> TRUE | DL81: =CQ81=BV81 -> TRUE | DM81: =CR81=BW81 -> TRUE | DN81: =CS81=BX81 -> TRUE | DO81: =CT81=BY81 -> TRUE | ... EB81: =DG81=CL81 -> TRUE
C82: 48 | D82: Среднемесячная зарплата НПР | E82: руб. | F82: ='[10]Данные для переноса'!F83 -> 193508.95 | G82: ='[10]Данные для переноса'!G83 -> 219384.22 | H82: ='[10]Данные для переноса'!H83 -> 239757.31 | I82: ='[10]Данные для переноса'!I83 -> 259822.63 | J82: ='[10]Данные для переноса'!J83 -> 279129.21 | K82: ='[10]Данные для переноса'!K83 -> 300093.23 | L82: ='[10]Данные для переноса'!L83 -> 312822.12 | M82: ='[10]Данные для переноса'!M83 -> 326118.52 | ... Z82: ='[10]Данные для переноса'!Z83 -> 563804.38 | AA82: 193508.95 | AB82: 219384.22 | AC82: 239757.31 | AD82: 259822.63 | AE82: 279129.21 | AF82: 300093.23 | AG82: 312822.12 | AH82: 326118.52 | AI82: 339993.99 | AJ82: 354484.84 | AK82: 369619.8 | AL82: 385428.98 | AM82: 401943.96 | AN82: 419197.86 | AO82: 437225.41 | AP82: 456063.01 | AQ82: 475748.84 | AR82: 496322.92 | AS82: 517827.19 | AT82: 540305.65 | AU82: 563804.38 | AV82: =AA82=F82 -> TRUE | AW82: =AB82=G82 -> TRUE | AX82: =AC82=H82 -> TRUE | AY82: =AD82=I82 -> TRUE | AZ82: =AE82=J82 -> TRUE | BA82: =AF82=K82 -> TRUE | BB82: =AG82=L82 -> TRUE | BC82: =AH82=M82 -> TRUE | ... BP82: =AU82=Z82 -> TRUE | BQ82: =IFERROR(AVERAGE(J82:Z82),0) -> 410360.58 | BR82: ='[10]Данные для переноса'!AB83 -> 193508.95 | BS82: ='[10]Данные для переноса'!AC83 -> 219384.22 | BT82: ='[10]Данные для переноса'!AD83 -> 239757.31 | BU82: ='[10]Данные для переноса'!AE83 -> 277206.15 | BV82: ='[10]Данные для переноса'!AF83 -> 300256.49 | BW82: ='[10]Данные для переноса'!AG83 -> 322423.85 | BX82: ='[10]Данные для переноса'!AH83 -> 336008.33 | BY82: ='[10]Данные для переноса'!AI83 -> 350030.57 | ... CL82: ='[10]Данные для переноса'!AV83 -> 599277.18 | CM82: 193508.95 | CN82: 219384.22 | CO82: 239757.31 | CP82: 277206.15 | CQ82: 300256.49 | CR82: 322423.85 | CS82: 336008.33 | CT82: 350030.57 | CU82: 364703.72 | CV82: 380012.75 | CW82: 395982.15 | CX82: 412641.31 | CY82: 430021.02 | CZ82: 448163.27 | DA82: 467094.69 | DB82: 486812.56 | DC82: 507415.75 | DD82: 528931.64 | DE82: 551373.83 | DF82: 574819.94 | DG82: 599277.18 | DH82: =CM82=BR82 -> TRUE | DI82: =CN82=BS82 -> TRUE | DJ82: =CO82=BT82 -> TRUE | DK82: =CP82=BU82 -> TRUE | DL82: =CQ82=BV82 -> TRUE | DM82: =CR82=BW82 -> TRUE | DN82: =CS82=BX82 -> TRUE | DO82: =CT82=BY82 -> TRUE | ... EB82: =DG82=CL82 -> TRUE | EC82: =IFERROR(AVERAGE(BV82:CL82),0) -> 438586.41 | ED82: =BR82-F82 -> 0 | EE82: =BS82-G82 -> 0 | EF82: =BT82-H82 -> 0 | EG82: =BU82-I82 -> 17383.514 | EH82: =BV82-J82 -> 21127.276 | EI82: =BW82-K82 -> 22330.615 | EJ82: =BX82-L82 -> 23186.204 | EK82: =BY82-M82 -> 23912.051 | ... EX82: =CL82-Z82 -> 35472.801 | EY82: =IFERROR(AVERAGE(EH82:EX82),0) -> 28225.83
C83: 49 | D83: Среднемесячная зарплата ППС | E83: руб. | F83: ='[10]Данные для переноса'!F84 -> 182280.09 | G83: ='[10]Данные для переноса'!G84 -> 203106.51 | H83: ='[10]Данные для переноса'!H84 -> 221637.23 | I83: ='[10]Данные для переноса'!I84 -> 240800 | J83: ='[10]Данные для переноса'!J84 -> 260064 | K83: ='[10]Данные для переноса'!K84 -> 280870 | L83: ='[10]Данные для переноса'!L84 -> 292104.8 | M83: ='[10]Данные для переноса'!M84 -> 303788.99 | ... Z83: ='[10]Данные для переноса'!Z84 -> 505831 | AA83: 182280.09 | AB83: 203106.51 | AC83: 221637.23 | AD83: 240800 | AE83: 260064 | AF83: 280870 | AG83: 292104.8 | AH83: 303788.99 | AI83: 315940.55 | AJ83: 328578.17 | AK83: 341721.3 | AL83: 355390.15 | AM83: 369605.76 | AN83: 384389.99 | AO83: 399765.59 | AP83: 415756.21 | AQ83: 432386.46 | AR83: 449681.92 | AS83: 467669.2 | AT83: 486375.96 | AU83: 505831 | AV83: =AA83=F83 -> TRUE | AW83: =AB83=G83 -> TRUE | AX83: =AC83=H83 -> TRUE | AY83: =AD83=I83 -> TRUE | AZ83: =AE83=J83 -> TRUE | BA83: =AF83=K83 -> TRUE | BB83: =AG83=L83 -> TRUE | BC83: =AH83=M83 -> TRUE | ... BP83: =AU83=Z83 -> TRUE | BQ83: =IFERROR(AVERAGE(J83:Z83),0) -> 375877.65 | BR83: ='[10]Данные для переноса'!AB84 -> 182280.09 | BS83: ='[10]Данные для переноса'!AC84 -> 203106.51 | BT83: ='[10]Данные для переноса'!AD84 -> 221637.23 | BU83: ='[10]Данные для переноса'!AE84 -> 260000 | BV83: ='[10]Данные для переноса'!AF84 -> 280800 | BW83: ='[10]Данные для переноса'!AG84 -> 303264.95 | BX83: ='[10]Данные для переноса'!AH84 -> 315395.55 | BY83: ='[10]Данные для переноса'!AI84 -> 328011.37 | ... CL83: ='[10]Данные для переноса'!AV84 -> 546163.04 | CM83: 182280.09 | CN83: 203106.51 | CO83: 221637.23 | CP83: 260000 | CQ83: 280800 | CR83: 303264.95 | CS83: 315395.55 | CT83: 328011.37 | CU83: 341131.82 | CV83: 354777.1 | CW83: 368968.18 | CX83: 383726.91 | CY83: 399075.99 | CZ83: 415039.02 | DA83: 431640.59 | DB83: 448906.21 | DC83: 466862.46 | DD83: 485536.96 | DE83: 504958.43 | DF83: 525156.77 | DG83: 546163.04 | DH83: =CM83=BR83 -> TRUE | DI83: =CN83=BS83 -> TRUE | DJ83: =CO83=BT83 -> TRUE | DK83: =CP83=BU83 -> TRUE | DL83: =CQ83=BV83 -> TRUE | DM83: =CR83=BW83 -> TRUE | DN83: =CS83=BX83 -> TRUE | DO83: =CT83=BY83 -> TRUE | ... EB83: =DG83=CL83 -> TRUE | EC83: =IFERROR(AVERAGE(BV83:CL83),0) -> 405847.96 | ED83: =BR83-F83 -> 0 | EE83: =BS83-G83 -> 0 | EF83: =BT83-H83 -> 0 | EG83: =BU83-I83 -> 19200 | EH83: =BV83-J83 -> 20736 | EI83: =BW83-K83 -> 22394.95 | EJ83: =BX83-L83 -> 23290.748 | EK83: =BY83-M83 -> 24222.378 | ... EX83: =CL83-Z83 -> 40332.04 | EY83: =IFERROR(AVERAGE(EH83:EX83),0) -> 29970.311
C84: 50 | D84: Среднемесячная зарплата НР | E84: руб. | F84: ='[10]Данные для переноса'!F85 -> 320064.08 | G84: ='[10]Данные для переноса'!G85 -> 390095.25 | H84: ='[10]Данные для переноса'!H85 -> 427488.47 | I84: ='[10]Данные для переноса'!I85 -> 446725.45 | J84: ='[10]Данные для переноса'!J85 -> 464594.47 | K84: ='[10]Данные для переноса'!K85 -> 483178.25 | L84: ='[10]Данные для переноса'!L85 -> 502505.38 | M84: ='[10]Данные для переноса'!M85 -> 522605.59 | ... Z84: ='[10]Данные для переноса'!Z85 -> 870176.73 | AA84: 320064.08 | AB84: 390095.25 | AC84: 427488.47 | AD84: 446725.45 | AE84: 464594.47 | AF84: 483178.25 | AG84: 502505.38 | AH84: 522605.59 | AI84: 543509.82 | AJ84: 565250.21 | AK84: 587860.22 | AL84: 611374.63 | AM84: 635829.61 | AN84: 661262.8 | AO84: 687713.31 | AP84: 715221.84 | AQ84: 743830.71 | AR84: 773583.94 | AS84: 804527.3 | AT84: 836708.39 | AU84: 870176.73 | AV84: =AA84=F84 -> TRUE | AW84: =AB84=G84 -> TRUE | AX84: =AC84=H84 -> TRUE | AY84: =AD84=I84 -> TRUE | AZ84: =AE84=J84 -> TRUE | BA84: =AF84=K84 -> TRUE | BB84: =AG84=L84 -> TRUE | BC84: =AH84=M84 -> TRUE | ... BP84: =AU84=Z84 -> TRUE | BQ84: =IFERROR(AVERAGE(J84:Z84),0) -> 647631.36 | BR84: ='[10]Данные для переноса'!AB85 -> 320064.08 | BS84: ='[10]Данные для переноса'!AC85 -> 390095.25 | BT84: ='[10]Данные для переноса'!AD85 -> 427488.47 | BU84: ='[10]Данные для переноса'!AE85 -> 446725.45 | BV84: ='[10]Данные для переноса'!AF85 -> 464594.47 | BW84: ='[10]Данные для переноса'!AG85 -> 483178.25 | BX84: ='[10]Данные для переноса'!AH85 -> 502505.38 | BY84: ='[10]Данные для переноса'!AI85 -> 522605.59 | ... CL84: ='[10]Данные для переноса'!AV85 -> 870176.73 | CM84: 320064.08 | CN84: 390095.25 | CO84: 427488.47 | CP84: 446725.45 | CQ84: 464594.47 | CR84: 483178.25 | CS84: 502505.38 | CT84: 522605.59 | CU84: 543509.82 | CV84: 565250.21 | CW84: 587860.22 | CX84: 611374.63 | CY84: 635829.61 | CZ84: 661262.8 | DA84: 687713.31 | DB84: 715221.84 | DC84: 743830.71 | DD84: 773583.94 | DE84: 804527.3 | DF84: 836708.39 | DG84: 870176.73 | DH84: =CM84=BR84 -> TRUE | DI84: =CN84=BS84 -> TRUE | DJ84: =CO84=BT84 -> TRUE | DK84: =CP84=BU84 -> TRUE | DL84: =CQ84=BV84 -> TRUE | DM84: =CR84=BW84 -> TRUE | DN84: =CS84=BX84 -> TRUE | DO84: =CT84=BY84 -> TRUE | ... EB84: =DG84=CL84 -> TRUE | EC84: =IFERROR(AVERAGE(BV84:CL84),0) -> 647631.36 | ED84: =BR84-F84 -> 0 | EE84: =BS84-G84 -> 0 | EF84: =BT84-H84 -> 0 | EG84: =BU84-I84 -> 0 | EH84: =BV84-J84 -> 0 | EI84: =BW84-K84 -> 0 | EJ84: =BX84-L84 -> 0 | EK84: =BY84-M84 -> 0 | ... EX84: =CL84-Z84 -> 0 | EY84: =IFERROR(AVERAGE(EH84:EX84),0) -> 0
C85: 51 | D85: Фонд оплаты труда ППС | E85: тыс.руб. | F85: ='[10]Данные для переноса'!F86 -> 2433220.4 | G85: ='[10]Данные для переноса'!G86 -> 2842353.7 | H85: ='[10]Данные для переноса'!H86 -> 3325888.3 | I85: ='[10]Данные для переноса'!I86 -> 3710447 | J85: ='[10]Данные для переноса'!J86 -> 4079085.4 | K85: ='[10]Данные для переноса'!K86 -> 4450203.2 | L85: ='[10]Данные для переноса'!L86 -> 4627170.7 | M85: ='[10]Данные для переноса'!M86 -> 4809957.8 | ... Z85: ='[10]Данные для переноса'!Z86 -> 8008933.2 | AA85: 2433220.4 | AB85: 2842353.7 | AC85: 3325888.3 | AD85: 3710447 | AE85: 4079085.4 | AF85: 4450203.2 | AG85: 4627170.7 | AH85: 4809957.8 | AI85: 5002356.1 | AJ85: 5202450.3 | AK85: 5410548.3 | AL85: 5626970.3 | AM85: 5852049.1 | AN85: 6086131 | AO85: 6329576.3 | AP85: 6582759.3 | AQ85: 6846069.7 | AR85: 7119912.5 | AS85: 7404709 | AT85: 7700897.3 | AU85: 8008933.2 | AV85: =AA85=F85 -> TRUE | AW85: =AB85=G85 -> TRUE | AX85: =AC85=H85 -> TRUE | AY85: =AD85=I85 -> TRUE | AZ85: =AE85=J85 -> TRUE | BA85: =AF85=K85 -> TRUE | BB85: =AG85=L85 -> TRUE | BC85: =AH85=M85 -> TRUE | ... BP85: =AU85=Z85 -> TRUE | BQ85: =IFERROR(AVERAGE(J85:Z85),0) -> 5949398.8 | BR85: ='[10]Данные для переноса'!AB86 -> 2433220.4 | BS85: ='[10]Данные для переноса'!AC86 -> 2842353.7 | BT85: ='[10]Данные для переноса'!AD86 -> 3325888.3 | BU85: ='[10]Данные для переноса'!AE86 -> 4028063.6 | BV85: ='[10]Данные для переноса'!AF86 -> 4474978.4 | BW85: ='[10]Данные для переноса'!AG86 -> 4942381.3 | BX85: ='[10]Данные для переноса'!AH86 -> 5195273.8 | BY85: ='[10]Данные для переноса'!AI86 -> 5434489.5 | ... CL85: ='[10]Данные для переноса'!AV86 -> 9438941.8 | CM85: 2433220.4 | CN85: 2842353.7 | CO85: 3325888.3 | CP85: 4028063.6 | CQ85: 4474978.4 | CR85: 4942381.3 | CS85: 5195273.8 | CT85: 5434489.5 | CU85: 5670706.1 | CV85: 5916334.9 | CW85: 6172869.5 | CX85: 6440802.5 | CY85: 6720649 | CZ85: 7010544.9 | DA85: 7312879.3 | DB85: 7637179.4 | DC85: 7969278 | DD85: 8312697.9 | DE85: 8674213.6 | DF85: 9046673 | DG85: 9438941.8 | DH85: =CM85=BR85 -> TRUE | DI85: =CN85=BS85 -> TRUE | DJ85: =CO85=BT85 -> TRUE | DK85: =CP85=BU85 -> TRUE | DL85: =CQ85=BV85 -> TRUE | DM85: =CR85=BW85 -> TRUE | DN85: =CS85=BX85 -> TRUE | DO85: =CT85=BY85 -> TRUE | ... EB85: =DG85=CL85 -> TRUE | EC85: =IFERROR(AVERAGE(BV85:CL85),0) -> 6845346.6 | ED85: =BR85-F85 -> 0 | EE85: =BS85-G85 -> 0 | EF85: =BT85-H85 -> 0 | EG85: =BU85-I85 -> 317616.65 | EH85: =BV85-J85 -> 395893 | EI85: =BW85-K85 -> 492178.12 | EJ85: =BX85-L85 -> 568103.03 | EK85: =BY85-M85 -> 624531.74 | ... EX85: =CL85-Z85 -> 1430008.6 | EY85: =IFERROR(AVERAGE(EH85:EX85),0) -> 895947.86
C86: 52 | D86: Фонд оплаты труда НР | E86: тыс.руб. | F86: ='[10]Данные для переноса'!F87 -> 379083.9 | G86: ='[10]Данные для переноса'!G87 -> 520543.1 | H86: ='[10]Данные для переноса'!H87 -> 619174.3 | I86: ='[10]Данные для переноса'!I87 -> 700592.06 | J86: ='[10]Данные для переноса'!J87 -> 749092.77 | K86: ='[10]Данные для переноса'!K87 -> 803813.94 | L86: ='[10]Данные для переноса'!L87 -> 869405.16 | M86: ='[10]Данные для переноса'!M87 -> 940348.62 | ... Z86: ='[10]Данные для переноса'!Z87 -> 2607088.1 | AA86: 379083.9 | AB86: 520543.1 | AC86: 619174.3 | AD86: 700592.06 | AE86: 749092.77 | AF86: 803813.94 | AG86: 869405.16 | AH86: 940348.62 | AI86: 1017081.1 | AJ86: 1100074.9 | AK86: 1189841 | AL86: 1286932 | AM86: 1391945.7 | AN86: 1505528.4 | AO86: 1628379.6 | AP86: 1761255.3 | AQ86: 1904973.8 | AR86: 2060419.6 | AS86: 2228549.9 | AT86: 2410399.5 | AU86: 2607088.1 | AV86: =AA86=F86 -> TRUE | AW86: =AB86=G86 -> TRUE | AX86: =AC86=H86 -> TRUE | AY86: =AD86=I86 -> TRUE | AZ86: =AE86=J86 -> TRUE | BA86: =AF86=K86 -> TRUE | BB86: =AG86=L86 -> TRUE | BC86: =AH86=M86 -> TRUE | ... BP86: =AU86=Z86 -> TRUE | BQ86: =IFERROR(AVERAGE(J86:Z86),0) -> 1497360.5 | BR86: ='[10]Данные для переноса'!AB87 -> 379083.9 | BS86: ='[10]Данные для переноса'!AC87 -> 520543.1 | BT86: ='[10]Данные для переноса'!AD87 -> 619174.3 | BU86: ='[10]Данные для переноса'!AE87 -> 702470.55 | BV86: ='[10]Данные для переноса'!AF87 -> 876585.59 | BW86: ='[10]Данные для переноса'!AG87 -> 938488.79 | BX86: ='[10]Данные для переноса'!AH87 -> 1024763.4 | BY86: ='[10]Данные для переноса'!AI87 -> 1104759.1 | ... CL86: ='[10]Данные для переноса'!AV87 -> 2948562.3 | CM86: 379083.9 | CN86: 520543.1 | CO86: 619174.3 | CP86: 702470.55 | CQ86: 876585.59 | CR86: 938488.79 | CS86: 1024763.4 | CT86: 1104759.1 | CU86: 1191062 | CV86: 1284173.5 | CW86: 1384634.8 | CX86: 1493030.7 | CY86: 1609992.6 | CZ86: 1736202.5 | DA86: 1872397.1 | DB86: 2019372.1 | DC86: 2177986.7 | DD86: 2349169.5 | DE86: 2533923 | DF86: 2733330.6 | DG86: 2948562.3 | DH86: =CM86=BR86 -> TRUE | DI86: =CN86=BS86 -> TRUE | DJ86: =CO86=BT86 -> TRUE | DK86: =CP86=BU86 -> TRUE | DL86: =CQ86=BV86 -> TRUE | DM86: =CR86=BW86 -> TRUE | DN86: =CS86=BX86 -> TRUE | DO86: =CT86=BY86 -> TRUE | ... EB86: =DG86=CL86 -> TRUE | EC86: =IFERROR(AVERAGE(BV86:CL86),0) -> 1722260.8 | ED86: =BR86-F86 -> 0 | EE86: =BS86-G86 -> 0 | EF86: =BT86-H86 -> 0 | EG86: =BU86-I86 -> 1878.4809 | EH86: =BV86-J86 -> 127492.81 | EI86: =BW86-K86 -> 134674.85 | EJ86: =BX86-L86 -> 155358.24 | EK86: =BY86-M86 -> 164410.47 | ... EX86: =CL86-Z86 -> 341474.13 | EY86: =IFERROR(AVERAGE(EH86:EX86),0) -> 224900.29
C87: 53 | D87: Среднесписочная численность ППС | E87: чел. | F87: ='[10]Данные для переноса'!F88 -> 1112.4 | G87: ='[10]Данные для переноса'!G88 -> 1166.2 | H87: ='[10]Данные для переноса'!H88 -> 1250.5 | I87: ='[10]Данные для переноса'!I88 -> 1284.0694 | J87: ='[10]Данные для переноса'!J88 -> 1307.0774 | K87: ='[10]Данные для переноса'!K88 -> 1320.3627 | L87: ='[10]Данные для переноса'!L88 -> 1320.0658 | M87: ='[10]Данные для переноса'!M88 -> 1319.4349 | ... Z87: ='[10]Данные для переноса'!Z88 -> 1319.4349 | AA87: 1112.4 | AB87: 1166.2 | AC87: 1250.5 | AD87: 1284.0694 | AE87: 1307.0774 | AF87: 1320.3627 | AG87: 1320.0658 | AH87: 1319.4349 | AI87: 1319.4349 | AJ87: 1319.4349 | AK87: 1319.4349 | AL87: 1319.4349 | AM87: 1319.4349 | AN87: 1319.4349 | AO87: 1319.4349 | AP87: 1319.4349 | AQ87: 1319.4349 | AR87: 1319.4349 | AS87: 1319.4349 | AT87: 1319.4349 | AU87: 1319.4349 | AV87: =AA87=F87 -> TRUE | AW87: =AB87=G87 -> TRUE | AX87: =AC87=H87 -> TRUE | AY87: =AD87=I87 -> TRUE | AZ87: =AE87=J87 -> TRUE | BA87: =AF87=K87 -> TRUE | BB87: =AG87=L87 -> TRUE | BC87: =AH87=M87 -> TRUE | ... BP87: =AU87=Z87 -> TRUE | BQ87: =IFERROR(AVERAGE(J87:Z87),0) -> 1318.7997 | BR87: ='[10]Данные для переноса'!AB88 -> 1112.4 | BS87: ='[10]Данные для переноса'!AC88 -> 1166.2 | BT87: ='[10]Данные для переноса'!AD88 -> 1250.5 | BU87: ='[10]Данные для переноса'!AE88 -> 1291.046 | BV87: ='[10]Данные для переноса'!AF88 -> 1328.0444 | BW87: ='[10]Данные для переноса'!AG88 -> 1358.1032 | BX87: ='[10]Данные для переноса'!AH88 -> 1372.6873 | BY87: ='[10]Данные для переноса'!AI88 -> 1380.6659 | ... CL87: ='[10]Данные для переноса'!AV88 -> 1440.1899 | CM87: 1112.4 | CN87: 1166.2 | CO87: 1250.5 | CP87: 1291.046 | CQ87: 1328.0444 | CR87: 1358.1032 | CS87: 1372.6873 | CT87: 1380.6659 | CU87: 1385.2675 | CV87: 1389.6836 | CW87: 1394.1739 | CX87: 1398.7384 | CY87: 1403.3771 | CZ87: 1407.6076 | DA87: 1411.8381 | DB87: 1417.7385 | DC87: 1422.4886 | DD87: 1426.7191 | DE87: 1431.5062 | DF87: 1435.5512 | DG87: 1440.1899 | DH87: =CM87=BR87 -> TRUE | DI87: =CN87=BS87 -> TRUE | DJ87: =CO87=BT87 -> TRUE | DK87: =CP87=BU87 -> TRUE | DL87: =CQ87=BV87 -> TRUE | DM87: =CR87=BW87 -> TRUE | DN87: =CS87=BX87 -> TRUE | DO87: =CT87=BY87 -> TRUE | ... EB87: =DG87=CL87 -> TRUE | EC87: =IFERROR(AVERAGE(BV87:CL87),0) -> 1400.2577 | ED87: =BR87-F87 -> 0 | EE87: =BS87-G87 -> 0 | EF87: =BT87-H87 -> 0 | EG87: =BU87-I87 -> 6.9766213 | EH87: =BV87-J87 -> 20.966974 | EI87: =BW87-K87 -> 37.740552 | EJ87: =BX87-L87 -> 52.621537 | EK87: =BY87-M87 -> 61.230985 | ... EX87: =CL87-Z87 -> 120.75492 | EY87: =IFERROR(AVERAGE(EH87:EX87),0) -> 81.457948
C88: 54 | D88: Расчетный НР исходя из выроботки на 1 ед. | E88: чел. | F88: ='[10]Данные для переноса'!F89 -> 98.7 | G88: ='[10]Данные для переноса'!G89 -> 111.2 | H88: ='[10]Данные для переноса'!H89 -> 120.7 | I88: ='[10]Данные для переноса'!I89 -> 130.69028 | J88: ='[10]Данные для переноса'!J89 -> 134.3632 | K88: ='[10]Данные для переноса'!K89 -> 138.63309 | L88: ='[10]Данные для переноса'!L89 -> 144.17842 | M88: ='[10]Данные для переноса'!M89 -> 149.94555 | ... Z88: ='[10]Данные для переноса'!Z89 -> 249.67037 | AA88: 98.7 | AB88: 111.2 | AC88: 120.7 | AD88: 130.69028 | AE88: 134.3632 | AF88: 138.63309 | AG88: 144.17842 | AH88: 149.94555 | AI88: 155.94338 | AJ88: 162.18111 | AK88: 168.66835 | AL88: 175.41509 | AM88: 182.43169 | AN88: 189.72896 | AO88: 197.31812 | AP88: 205.21084 | AQ88: 213.41928 | AR88: 221.95605 | AS88: 230.83429 | AT88: 240.06766 | AU88: 249.67037 | AV88: =AA88=F88 -> TRUE | AW88: =AB88=G88 -> TRUE | AX88: =AC88=H88 -> TRUE | AY88: =AD88=I88 -> TRUE | AZ88: =AE88=J88 -> TRUE | BA88: =AF88=K88 -> TRUE | BB88: =AG88=L88 -> TRUE | BC88: =AH88=M88 -> TRUE | ... BP88: =AU88=Z88 -> TRUE | BQ88: =IFERROR(AVERAGE(J88:Z88),0) -> 185.88032 | BR88: ='[10]Данные для переноса'!AB89 -> 98.7 | BS88: ='[10]Данные для переноса'!AC89 -> 111.2 | BT88: ='[10]Данные для переноса'!AD89 -> 120.7 | BU88: ='[10]Данные для переноса'!AE89 -> 131.04069 | BV88: ='[10]Данные для переноса'!AF89 -> 157.23131 | BW88: ='[10]Данные для переноса'!AG89 -> 161.86035 | BX88: ='[10]Данные для переноса'!AH89 -> 169.94236 | BY88: ='[10]Данные для переноса'!AI89 -> 176.16202 | ... CL88: ='[10]Данные для переноса'!AV89 -> 282.37198 | CM88: 98.7 | CN88: 111.2 | CO88: 120.7 | CP88: 131.04069 | CQ88: 157.23131 | CR88: 161.86035 | CS88: 169.94236 | CT88: 176.16202 | CU88: 182.61891 | CV88: 189.32228 | CW88: 196.28175 | CX88: 203.50734 | CY88: 211.00944 | CZ88: 218.79886 | DA88: 226.88683 | DB88: 235.28505 | DC88: 244.00565 | DD88: 253.06125 | DE88: 262.46499 | DF88: 272.2305 | DG88: 282.37198 | DH88: =CM88=BR88 -> TRUE | DI88: =CN88=BS88 -> TRUE | DJ88: =CO88=BT88 -> TRUE | DK88: =CP88=BU88 -> TRUE | DL88: =CQ88=BV88 -> TRUE | DM88: =CR88=BW88 -> TRUE | DN88: =CS88=BX88 -> TRUE | DO88: =CT88=BY88 -> TRUE | ... EB88: =DG88=CL88 -> TRUE | EC88: =IFERROR(AVERAGE(BV88:CL88),0) -> 214.29652 | ED88: =BR88-F88 -> 0 | EE88: =BS88-G88 -> 0 | EF88: =BT88-H88 -> 0 | EG88: =BU88-I88 -> 0.35041673 | EH88: =BV88-J88 -> 22.868118 | EI88: =BW88-K88 -> 23.227255 | EJ88: =BX88-L88 -> 25.763943 | EK88: =BY88-M88 -> 26.216467 | ... EX88: =CL88-Z88 -> 32.701607 | EY88: =IFERROR(AVERAGE(EH88:EX88),0) -> 28.416201
D89: Нефинансовые показатели | AV89: =AA89=F89 -> TRUE | AW89: =AB89=G89 -> TRUE | AX89: =AC89=H89 -> TRUE | AY89: =AD89=I89 -> TRUE | AZ89: =AE89=J89 -> TRUE | BA89: =AF89=K89 -> TRUE | BB89: =AG89=L89 -> TRUE | BC89: =AH89=M89 -> TRUE | ... BP89: =AU89=Z89 -> TRUE | DH89: =CM89=BR89 -> TRUE | DI89: =CN89=BS89 -> TRUE | DJ89: =CO89=BT89 -> TRUE | DK89: =CP89=BU89 -> TRUE | DL89: =CQ89=BV89 -> TRUE | DM89: =CR89=BW89 -> TRUE | DN89: =CS89=BX89 -> TRUE | DO89: =CT89=BY89 -> TRUE | ... EB89: =DG89=CL89 -> TRUE
D90: Численность обучающихся | AV90: =AA90=F90 -> TRUE | AW90: =AB90=G90 -> TRUE | AX90: =AC90=H90 -> TRUE | AY90: =AD90=I90 -> TRUE | AZ90: =AE90=J90 -> TRUE | BA90: =AF90=K90 -> TRUE | BB90: =AG90=L90 -> TRUE | BC90: =AH90=M90 -> TRUE | ... BP90: =AU90=Z90 -> TRUE | DH90: =CM90=BR90 -> TRUE | DI90: =CN90=BS90 -> TRUE | DJ90: =CO90=BT90 -> TRUE | DK90: =CP90=BU90 -> TRUE | DL90: =CQ90=BV90 -> TRUE | DM90: =CR90=BW90 -> TRUE | DN90: =CS90=BX90 -> TRUE | DO90: =CT90=BY90 -> TRUE | ... EB90: =DG90=CL90 -> TRUE | ED90: =ED91+ED92 -> 0 | EE90: =EE91+EE92 -> 0 | EF90: =EF91+EF92 -> 0 | EG90: =EG91+EG92 -> 166 | EH90: =EH91+EH92 -> 535 | EI90: =EI91+EI92 -> 981 | EJ90: =EJ91+EJ92 -> 1376 | EK90: =EK91+EK92 -> 1619 | ... EX90: =EX91+EX92 -> 3223
C91: 55 | D91: Численность обучающихся ВО | E91: чел. | F91: ='[10]Данные для переноса'!F92 -> 28156.3 | G91: ='[10]Данные для переноса'!G92 -> 29406.7 | H91: ='[10]Данные для переноса'!H92 -> 31474.1 | I91: ='[10]Данные для переноса'!I92 -> 34602 | J91: ='[10]Данные для переноса'!J92 -> 35222 | K91: ='[10]Данные для переноса'!K92 -> 35580 | L91: ='[10]Данные для переноса'!L92 -> 35572 | M91: ='[10]Данные для переноса'!M92 -> 35555 | ... Z91: ='[10]Данные для переноса'!Z92 -> 35555 | AA91: 28156.3 | AB91: 29406.7 | AC91: 31474.1 | AD91: 34602 | AE91: 35222 | AF91: 35580 | AG91: 35572 | AH91: 35555 | AI91: 35555 | AJ91: 35555 | AK91: 35555 | AL91: 35555 | AM91: 35555 | AN91: 35555 | AO91: 35555 | AP91: 35555 | AQ91: 35555 | AR91: 35555 | AS91: 35555 | AT91: 35555 | AU91: 35555 | AV91: =AA91=F91 -> TRUE | AW91: =AB91=G91 -> TRUE | AX91: =AC91=H91 -> TRUE | AY91: =AD91=I91 -> TRUE | AZ91: =AE91=J91 -> TRUE | BA91: =AF91=K91 -> TRUE | BB91: =AG91=L91 -> TRUE | BC91: =AH91=M91 -> TRUE | ... BP91: =AU91=Z91 -> TRUE | BQ91: =IFERROR(AVERAGE(J91:Z91),0) -> 35537.882 | BR91: ='[10]Данные для переноса'!AB92 -> 28156.3 | BS91: ='[10]Данные для переноса'!AC92 -> 29406.7 | BT91: ='[10]Данные для переноса'!AD92 -> 31474.1 | BU91: ='[10]Данные для переноса'!AE92 -> 34790 | BV91: ='[10]Данные для переноса'!AF92 -> 35787 | BW91: ='[10]Данные для переноса'!AG92 -> 36597 | BX91: ='[10]Данные для переноса'!AH92 -> 36990 | BY91: ='[10]Данные для переноса'!AI92 -> 37205 | ... CL91: ='[10]Данные для переноса'!AV92 -> 38809 | CM91: 28156.3 | CN91: 29406.7 | CO91: 31474.1 | CP91: 34790 | CQ91: 35787 | CR91: 36597 | CS91: 36990 | CT91: 37205 | CU91: 37329 | CV91: 37448 | CW91: 37569 | CX91: 37692 | CY91: 37817 | CZ91: 37931 | DA91: 38045 | DB91: 38204 | DC91: 38332 | DD91: 38446 | DE91: 38575 | DF91: 38684 | DG91: 38809 | DH91: =CM91=BR91 -> TRUE | DI91: =CN91=BS91 -> TRUE | DJ91: =CO91=BT91 -> TRUE | DK91: =CP91=BU91 -> TRUE | DL91: =CQ91=BV91 -> TRUE | DM91: =CR91=BW91 -> TRUE | DN91: =CS91=BX91 -> TRUE | DO91: =CT91=BY91 -> TRUE | ... EB91: =DG91=CL91 -> TRUE | EC91: =IFERROR(AVERAGE(BV91:CL91),0) -> 37732.941 | ED91: =BR91-F91 -> 0 | EE91: =BS91-G91 -> 0 | EF91: =BT91-H91 -> 0 | EG91: =BU91-I91 -> 188 | EH91: =BV91-J91 -> 565 | EI91: =BW91-K91 -> 1017 | EJ91: =BX91-L91 -> 1418 | EK91: =BY91-M91 -> 1650 | ... EX91: =CL91-Z91 -> 3254 | EY91: =IFERROR(AVERAGE(EH91:EX91),0) -> 2195.0588
C92: 56 | D92: Численность обучающихся СПО | E92: чел. | F92: ='[10]Данные для переноса'!F93 -> 1342 | G92: ='[10]Данные для переноса'!G93 -> 1504 | H92: ='[10]Данные для переноса'!H93 -> 1602.7 | I92: ='[10]Данные для переноса'!I93 -> 1535 | J92: ='[10]Данные для переноса'!J93 -> 1418 | K92: ='[10]Данные для переноса'!K93 -> 1293 | L92: ='[10]Данные для переноса'!L93 -> 1290 | M92: ='[10]Данные для переноса'!M93 -> 1290 | ... Z92: ='[10]Данные для переноса'!Z93 -> 1290 | AA92: 1342 | AB92: 1504 | AC92: 1602.7 | AD92: 1535 | AE92: 1418 | AF92: 1293 | AG92: 1290 | AH92: 1290 | AI92: 1290 | AJ92: 1290 | AK92: 1290 | AL92: 1290 | AM92: 1290 | AN92: 1290 | AO92: 1290 | AP92: 1290 | AQ92: 1290 | AR92: 1290 | AS92: 1290 | AT92: 1290 | AU92: 1290 | AV92: =AA92=F92 -> TRUE | AW92: =AB92=G92 -> TRUE | AX92: =AC92=H92 -> TRUE | AY92: =AD92=I92 -> TRUE | AZ92: =AE92=J92 -> TRUE | BA92: =AF92=K92 -> TRUE | BB92: =AG92=L92 -> TRUE | BC92: =AH92=M92 -> TRUE | ... BP92: =AU92=Z92 -> TRUE | BQ92: =IFERROR(AVERAGE(J92:Z92),0) -> 1297.7059 | BR92: ='[10]Данные для переноса'!AB93 -> 1342 | BS92: ='[10]Данные для переноса'!AC93 -> 1504 | BT92: ='[10]Данные для переноса'!AD93 -> 1602.7 | BU92: ='[10]Данные для переноса'!AE93 -> 1513 | BV92: ='[10]Данные для переноса'!AF93 -> 1388 | BW92: ='[10]Данные для переноса'!AG93 -> 1257 | BX92: ='[10]Данные для переноса'!AH93 -> 1248 | BY92: ='[10]Данные для переноса'!AI93 -> 1259 | ... CL92: ='[10]Данные для переноса'!AV93 -> 1259 | CM92: 1342 | CN92: 1504 | CO92: 1602.7 | CP92: 1513 | CQ92: 1388 | CR92: 1257 | CS92: 1248 | CT92: 1259 | CU92: 1259 | CV92: 1259 | CW92: 1259 | CX92: 1259 | CY92: 1259 | CZ92: 1259 | DA92: 1259 | DB92: 1259 | DC92: 1259 | DD92: 1259 | DE92: 1259 | DF92: 1259 | DG92: 1259 | DH92: =CM92=BR92 -> TRUE | DI92: =CN92=BS92 -> TRUE | DJ92: =CO92=BT92 -> TRUE | DK92: =CP92=BU92 -> TRUE | DL92: =CQ92=BV92 -> TRUE | DM92: =CR92=BW92 -> TRUE | DN92: =CS92=BX92 -> TRUE | DO92: =CT92=BY92 -> TRUE | ... EB92: =DG92=CL92 -> TRUE | EC92: =IFERROR(AVERAGE(BV92:CL92),0) -> 1265.8235 | ED92: =BR92-F92 -> 0 | EE92: =BS92-G92 -> 0 | EF92: =BT92-H92 -> 0 | EG92: =BU92-I92 -> -22 | EH92: =BV92-J92 -> -30 | EI92: =BW92-K92 -> -36 | EJ92: =BX92-L92 -> -42 | EK92: =BY92-M92 -> -31 | ... EX92: =CL92-Z92 -> -31 | EY92: =IFERROR(AVERAGE(EH92:EX92),0) -> -31.882353
C93: 57 | D93: Количество студентов ВО на 1 ППС | E93: чел. | F93: ='[10]Данные для переноса'!F94 -> 25.311309 | G93: ='[10]Данные для переноса'!G94 -> 25.215829 | H93: ='[10]Данные для переноса'!H94 -> 25.169212 | I93: ='[10]Данные для переноса'!I94 -> 26.947141 | J93: ='[10]Данные для переноса'!J94 -> 26.947141 | K93: ='[10]Данные для переноса'!K94 -> 26.947141 | L93: ='[10]Данные для переноса'!L94 -> 26.947141 | M93: ='[10]Данные для переноса'!M94 -> 26.947141 | ... Z93: ='[10]Данные для переноса'!Z94 -> 26.947141 | AA93: 25.311309 | AB93: 25.215829 | AC93: 25.169212 | AD93: 26.947141 | AE93: 26.947141 | AF93: 26.947141 | AG93: 26.947141 | AH93: 26.947141 | AI93: 26.947141 | AJ93: 26.947141 | AK93: 26.947141 | AL93: 26.947141 | AM93: 26.947141 | AN93: 26.947141 | AO93: 26.947141 | AP93: 26.947141 | AQ93: 26.947141 | AR93: 26.947141 | AS93: 26.947141 | AT93: 26.947141 | AU93: 26.947141 | AV93: =AA93=F93 -> TRUE | AW93: =AB93=G93 -> TRUE | AX93: =AC93=H93 -> TRUE | AY93: =AD93=I93 -> TRUE | AZ93: =AE93=J93 -> TRUE | BA93: =AF93=K93 -> TRUE | BB93: =AG93=L93 -> TRUE | BC93: =AH93=M93 -> TRUE | ... BP93: =AU93=Z93 -> TRUE | BQ93: =IFERROR(AVERAGE(J93:Z93),0) -> 26.947141 | BR93: ='[10]Данные для переноса'!AB94 -> 25.311309 | BS93: ='[10]Данные для переноса'!AC94 -> 25.215829 | BT93: ='[10]Данные для переноса'!AD94 -> 25.169212 | BU93: ='[10]Данные для переноса'!AE94 -> 26.947141 | BV93: ='[10]Данные для переноса'!AF94 -> 26.947141 | BW93: ='[10]Данные для переноса'!AG94 -> 26.947141 | BX93: ='[10]Данные для переноса'!AH94 -> 26.947141 | BY93: ='[10]Данные для переноса'!AI94 -> 26.947141 | ... CL93: ='[10]Данные для переноса'!AV94 -> 26.947141 | CM93: 25.311309 | CN93: 25.215829 | CO93: 25.169212 | CP93: 26.947141 | CQ93: 26.947141 | CR93: 26.947141 | CS93: 26.947141 | CT93: 26.947141 | CU93: 26.947141 | CV93: 26.947141 | CW93: 26.947141 | CX93: 26.947141 | CY93: 26.947141 | CZ93: 26.947141 | DA93: 26.947141 | DB93: 26.947141 | DC93: 26.947141 | DD93: 26.947141 | DE93: 26.947141 | DF93: 26.947141 | DG93: 26.947141 | DH93: =CM93=BR93 -> TRUE | DI93: =CN93=BS93 -> TRUE | DJ93: =CO93=BT93 -> TRUE | DK93: =CP93=BU93 -> TRUE | DL93: =CQ93=BV93 -> TRUE | DM93: =CR93=BW93 -> TRUE | DN93: =CS93=BX93 -> TRUE | DO93: =CT93=BY93 -> TRUE | ... EB93: =DG93=CL93 -> TRUE | EC93: =IFERROR(AVERAGE(BV93:CL93),0) -> 26.947141 | ED93: =BR93-F93 -> 0 | EE93: =BS93-G93 -> 0 | EF93: =BT93-H93 -> 0 | EG93: =BU93-I93 -> 0 | EH93: =BV93-J93 -> 0 | EI93: =BW93-K93 -> 0 | EJ93: =BX93-L93 -> 0 | EK93: =BY93-M93 -> 0 | ... EX93: =CL93-Z93 -> 0 | EY93: =IFERROR(AVERAGE(EH93:EX93),0) -> 0
D94: Количество персонала (по модели вуза) | AV94: =AA94=F94 -> TRUE | AW94: =AB94=G94 -> TRUE | AX94: =AC94=H94 -> TRUE | AY94: =AD94=I94 -> TRUE | AZ94: =AE94=J94 -> TRUE | BA94: =AF94=K94 -> TRUE | BB94: =AG94=L94 -> TRUE | BC94: =AH94=M94 -> TRUE | ... BP94: =AU94=Z94 -> TRUE | DH94: =CM94=BR94 -> TRUE | DI94: =CN94=BS94 -> TRUE | DJ94: =CO94=BT94 -> TRUE | DK94: =CP94=BU94 -> TRUE | DL94: =CQ94=BV94 -> TRUE | DM94: =CR94=BW94 -> TRUE | DN94: =CS94=BX94 -> TRUE | DO94: =CT94=BY94 -> TRUE | ... EB94: =DG94=CL94 -> TRUE
C95: 58 | D95: Количество преподавателей | E95: чел. | F95: ='[10]Данные для переноса'!F96 -> 1166.9 | G95: ='[10]Данные для переноса'!G96 -> 1223.9 | H95: ='[10]Данные для переноса'!H96 -> 1308.7 | I95: ='[10]Данные для переноса'!I96 -> 1336.0757 | J95: ='[10]Данные для переноса'!J96 -> 1355.1197 | K95: ='[10]Данные для переноса'!K96 -> 1364.17 | L95: ='[10]Данные для переноса'!L96 -> 1363.7714 | M95: ='[10]Данные для переноса'!M96 -> 1363.1406 | ... Z95: ='[10]Данные для переноса'!Z96 -> 1363.1406 | AA95: 1166.9 | AB95: 1223.9 | AC95: 1308.7 | AD95: 1336.0757 | AE95: 1355.1197 | AF95: 1364.17 | AG95: 1363.7714 | AH95: 1363.1406 | AI95: 1363.1406 | AJ95: 1363.1406 | AK95: 1363.1406 | AL95: 1363.1406 | AM95: 1363.1406 | AN95: 1363.1406 | AO95: 1363.1406 | AP95: 1363.1406 | AQ95: 1363.1406 | AR95: 1363.1406 | AS95: 1363.1406 | AT95: 1363.1406 | AU95: 1363.1406 | AV95: =AA95=F95 -> TRUE | AW95: =AB95=G95 -> TRUE | AX95: =AC95=H95 -> TRUE | AY95: =AD95=I95 -> TRUE | AZ95: =AE95=J95 -> TRUE | BA95: =AF95=K95 -> TRUE | BB95: =AG95=L95 -> TRUE | BC95: =AH95=M95 -> TRUE | ... BP95: =AU95=Z95 -> TRUE | BQ95: =IFERROR(AVERAGE(J95:Z95),0) -> 1362.7664 | BR95: ='[10]Данные для переноса'!AB96 -> 1166.9 | BS95: ='[10]Данные для переноса'!AC96 -> 1223.9 | BT95: ='[10]Данные для переноса'!AD96 -> 1308.7 | BU95: ='[10]Данные для переноса'!AE96 -> 1342.307 | BV95: ='[10]Данные для переноса'!AF96 -> 1375.0703 | BW95: ='[10]Данные для переноса'!AG96 -> 1400.6908 | BX95: ='[10]Данные для переноса'!AH96 -> 1414.97 | BY95: ='[10]Данные для переноса'!AI96 -> 1423.3213 | ... CL95: ='[10]Данные для переноса'!AV96 -> 1482.8452 | CM95: 1166.9 | CN95: 1223.9 | CO95: 1308.7 | CP95: 1342.307 | CQ95: 1375.0703 | CR95: 1400.6908 | CS95: 1414.97 | CT95: 1423.3213 | CU95: 1427.9229 | CV95: 1432.3389 | CW95: 1436.8292 | CX95: 1441.3937 | CY95: 1446.0324 | CZ95: 1450.2629 | DA95: 1454.4934 | DB95: 1460.3938 | DC95: 1465.1439 | DD95: 1469.3744 | DE95: 1474.1615 | DF95: 1478.2065 | DG95: 1482.8452 | DH95: =CM95=BR95 -> TRUE | DI95: =CN95=BS95 -> TRUE | DJ95: =CO95=BT95 -> TRUE | DK95: =CP95=BU95 -> TRUE | DL95: =CQ95=BV95 -> TRUE | DM95: =CR95=BW95 -> TRUE | DN95: =CS95=BX95 -> TRUE | DO95: =CT95=BY95 -> TRUE | ... EB95: =DG95=CL95 -> TRUE | EC95: =IFERROR(AVERAGE(BV95:CL95),0) -> 1443.1442 | ED95: =BR95-F95 -> 0 | EE95: =BS95-G95 -> 0 | EF95: =BT95-H95 -> 0 | EG95: =BU95-I95 -> 6.2312541 | EH95: =BV95-J95 -> 19.950564 | EI95: =BW95-K95 -> 36.520861 | EJ95: =BX95-L95 -> 51.198563 | EK95: =BY95-M95 -> 60.180695 | ... EX95: =CL95-Z95 -> 119.70463 | EY95: =IFERROR(AVERAGE(EH95:EX95),0) -> 80.377763
C96: 59 | D96: Количество ППС (ВО, ДО) | E96: чел. | F96: ='[10]Данные для переноса'!F97 -> 1112.8 | G96: ='[10]Данные для переноса'!G97 -> 1166.7 | H96: ='[10]Данные для переноса'!H97 -> 1250.5 | I96: ='[10]Данные для переноса'!I97 -> 1284.0694 | J96: ='[10]Данные для переноса'!J97 -> 1307.0774 | K96: ='[10]Данные для переноса'!K97 -> 1320.3627 | L96: ='[10]Данные для переноса'!L97 -> 1320.0658 | M96: ='[10]Данные для переноса'!M97 -> 1319.4349 | ... Z96: ='[10]Данные для переноса'!Z97 -> 1319.4349 | AA96: 1112.8 | AB96: 1166.7 | AC96: 1250.5 | AD96: 1284.0694 | AE96: 1307.0774 | AF96: 1320.3627 | AG96: 1320.0658 | AH96: 1319.4349 | AI96: 1319.4349 | AJ96: 1319.4349 | AK96: 1319.4349 | AL96: 1319.4349 | AM96: 1319.4349 | AN96: 1319.4349 | AO96: 1319.4349 | AP96: 1319.4349 | AQ96: 1319.4349 | AR96: 1319.4349 | AS96: 1319.4349 | AT96: 1319.4349 | AU96: 1319.4349 | AV96: =AA96=F96 -> TRUE | AW96: =AB96=G96 -> TRUE | AX96: =AC96=H96 -> TRUE | AY96: =AD96=I96 -> TRUE | AZ96: =AE96=J96 -> TRUE | BA96: =AF96=K96 -> TRUE | BB96: =AG96=L96 -> TRUE | BC96: =AH96=M96 -> TRUE | ... BP96: =AU96=Z96 -> TRUE | BQ96: =IFERROR(AVERAGE(J96:Z96),0) -> 1318.7997 | BR96: ='[10]Данные для переноса'!AB97 -> 1112.8 | BS96: ='[10]Данные для переноса'!AC97 -> 1166.7 | BT96: ='[10]Данные для переноса'!AD97 -> 1250.5 | BU96: ='[10]Данные для переноса'!AE97 -> 1291.046 | BV96: ='[10]Данные для переноса'!AF97 -> 1328.0444 | BW96: ='[10]Данные для переноса'!AG97 -> 1358.1032 | BX96: ='[10]Данные для переноса'!AH97 -> 1372.6873 | BY96: ='[10]Данные для переноса'!AI97 -> 1380.6659 | ... CL96: ='[10]Данные для переноса'!AV97 -> 1440.1899 | CM96: 1112.8 | CN96: 1166.7 | CO96: 1250.5 | CP96: 1291.046 | CQ96: 1328.0444 | CR96: 1358.1032 | CS96: 1372.6873 | CT96: 1380.6659 | CU96: 1385.2675 | CV96: 1389.6836 | CW96: 1394.1739 | CX96: 1398.7384 | CY96: 1403.3771 | CZ96: 1407.6076 | DA96: 1411.8381 | DB96: 1417.7385 | DC96: 1422.4886 | DD96: 1426.7191 | DE96: 1431.5062 | DF96: 1435.5512 | DG96: 1440.1899 | DH96: =CM96=BR96 -> TRUE | DI96: =CN96=BS96 -> TRUE | DJ96: =CO96=BT96 -> TRUE | DK96: =CP96=BU96 -> TRUE | DL96: =CQ96=BV96 -> TRUE | DM96: =CR96=BW96 -> TRUE | DN96: =CS96=BX96 -> TRUE | DO96: =CT96=BY96 -> TRUE | ... EB96: =DG96=CL96 -> TRUE | EC96: =IFERROR(AVERAGE(BV96:CL96),0) -> 1400.2577 | ED96: =BR96-F96 -> 0 | EE96: =BS96-G96 -> 0 | EF96: =BT96-H96 -> 0 | EG96: =BU96-I96 -> 6.9766213 | EH96: =BV96-J96 -> 20.966974 | EI96: =BW96-K96 -> 37.740552 | EJ96: =BX96-L96 -> 52.621537 | EK96: =BY96-M96 -> 61.230985 | ... EX96: =CL96-Z96 -> 120.75492 | EY96: =IFERROR(AVERAGE(EH96:EX96),0) -> 81.457948
